Workbook

Sheet To do
B2: To do:
B3: Add chart on net worth by quintile?
B4: Include waterfall chart that builds up to household income?
B5: Include pie chart for household expenditure?
B7: Key insight:
B8: ~60% of Canadians are in a negative cash flow situation
B9: Bottom Canadians are paying for their expenses with student loans / LOC / gifts from parents / credit cards / spending down their savings? What else?
B10: Income / cash flow inequality is increasing over time -- gap between top 20% and bottom 20% is increasing over time (even adjusting for inflation)
B12: For website:
B14: Put each chart in a separate H2 that be can navigated to easily / link shared indepdently
B15: Table of contents / back to top buttons
B16: Button to click to generate shareable link
... B18: Need URI parameter functionality for the dynamic charts?

Sheet 2023 Drill Down
B1: Annual Household Income
B2: $ per Household, 2023
C3: Age Group
B4: Income Quintile | C4: Less than 35 years | D4: 35 to 44 years | E4: 45 to 54 years | F4: 55 to 64 years | G4: 65 years and over | H4: All
B5: 1 | C5: ='2023 per HH by Age and Quintile'!M16 -> 32144 | D5: ='2023 per HH by Age and Quintile'!N16 -> 39230 | E5: ='2023 per HH by Age and Quintile'!O16 -> 39715 | F5: ='2023 per HH by Age and Quintile'!P16 -> 24610 | G5: ='2023 per HH by Age and Quintile'!Q16 -> 28735 | H5: ='2023 per HH by Age and Quintile'!C16 -> 31604
B6: 2 | C6: ='2023 per HH by Age and Quintile'!R16 -> 75128 | D6: ='2023 per HH by Age and Quintile'!S16 -> 79366 | E6: ='2023 per HH by Age and Quintile'!T16 -> 62668 | F6: ='2023 per HH by Age and Quintile'!U16 -> 55594 | G6: ='2023 per HH by Age and Quintile'!V16 -> 44502 | H6: ='2023 per HH by Age and Quintile'!D16 -> 59447
B7: 3 | C7: ='2023 per HH by Age and Quintile'!W16 -> 89104 | D7: ='2023 per HH by Age and Quintile'!X16 -> 93589 | E7: ='2023 per HH by Age and Quintile'!Y16 -> 98250 | F7: ='2023 per HH by Age and Quintile'!Z16 -> 70228 | G7: ='2023 per HH by Age and Quintile'!AA16 -> 58049 | H7: ='2023 per HH by Age and Quintile'!E16 -> 78998
B8: 4 | C8: ='2023 per HH by Age and Quintile'!AB16 -> 119463 | D8: ='2023 per HH by Age and Quintile'!AC16 -> 137538 | E8: ='2023 per HH by Age and Quintile'!AD16 -> 135803 | F8: ='2023 per HH by Age and Quintile'!AE16 -> 106872 | G8: ='2023 per HH by Age and Quintile'!AF16 -> 79024 | H8: ='2023 per HH by Age and Quintile'!F16 -> 114315
B9: 5 | C9: ='2023 per HH by Age and Quintile'!AG16 -> 182418 | D9: ='2023 per HH by Age and Quintile'!AH16 -> 187629 | E9: ='2023 per HH by Age and Quintile'!AI16 -> 262002 | F9: ='2023 per HH by Age and Quintile'!AJ16 -> 193320 | G9: ='2023 per HH by Age and Quintile'!AK16 -> 167492 | H9: ='2023 per HH by Age and Quintile'!G16 -> 197667
B10: All | C10: ='2023 per HH by Age and Quintile'!H16 -> 97767 | D10: ='2023 per HH by Age and Quintile'!I16 -> 112274 | E10: ='2023 per HH by Age and Quintile'!J16 -> 130133 | F10: ='2023 per HH by Age and Quintile'!K16 -> 101450 | G10: ='2023 per HH by Age and Quintile'!L16 -> 65738 | H10: ='2023 per HH by Age and Quintile'!B16 -> 96406
B15: Annual Household Spending
B16: $ per Household, 2023
C17: Age Group
B18: Income Quintile | C18: Less than 35 years | D18: 35 to 44 years | E18: 45 to 54 years | F18: 55 to 64 years | G18: 65 years and over | H18: All
B19: 1 | C19: ='2023 per HH by Age and Quintile'!M23 -> 62761 | D19: ='2023 per HH by Age and Quintile'!N23 -> 63254 | E19: ='2023 per HH by Age and Quintile'!O23 -> 76767 | F19: ='2023 per HH by Age and Quintile'!P23 -> 71238 | G19: ='2023 per HH by Age and Quintile'!Q23 -> 52572 | H19: {=TRANSPOSE('2023 per HH by Age and Quintile'!C23:G23)} -> 61968
B20: 2 | C20: ='2023 per HH by Age and Quintile'!R23 -> 81310 | D20: ='2023 per HH by Age and Quintile'!S23 -> 97176 | E20: ='2023 per HH by Age and Quintile'!T23 -> 86855 | F20: ='2023 per HH by Age and Quintile'!U23 -> 84889 | G20: ='2023 per HH by Age and Quintile'!V23 -> 55746 | H20: 75118
B21: 3 | C21: ='2023 per HH by Age and Quintile'!W23 -> 88214 | D21: ='2023 per HH by Age and Quintile'!X23 -> 99908 | E21: ='2023 per HH by Age and Quintile'!Y23 -> 126342 | F21: ='2023 per HH by Age and Quintile'!Z23 -> 93812 | G21: ='2023 per HH by Age and Quintile'!AA23 -> 68078 | H21: 91266
B22: 4 | C22: ='2023 per HH by Age and Quintile'!AB23 -> 88615 | D22: ='2023 per HH by Age and Quintile'!AC23 -> 112438 | E22: ='2023 per HH by Age and Quintile'!AD23 -> 135533 | F22: ='2023 per HH by Age and Quintile'!AE23 -> 114766 | G22: ='2023 per HH by Age and Quintile'!AF23 -> 72967 | H22: 103168
B23: 5 | C23: ='2023 per HH by Age and Quintile'!AG23 -> 128919 | D23: ='2023 per HH by Age and Quintile'!AH23 -> 131586 | E23: ='2023 per HH by Age and Quintile'!AI23 -> 183861 | F23: ='2023 per HH by Age and Quintile'!AJ23 -> 146632 | G23: ='2023 per HH by Age and Quintile'!AK23 -> 96602 | H23: 137015
B24: All | C24: ='2023 per HH by Age and Quintile'!H23 -> 88914 | D24: ='2023 per HH by Age and Quintile'!I23 -> 103075 | E24: ='2023 per HH by Age and Quintile'!J23 -> 127283 | F24: ='2023 per HH by Age and Quintile'!K23 -> 107382 | G24: ='2023 per HH by Age and Quintile'!L23 -> 65742 | H24: ='2023 per HH by Age and Quintile'!B23 -> 93707
B29: Annual Cash Flow (excl. pension entitlements)
B30: $ per Household, 2023
C31: Age Group
B32: Income Quintile | C32: Less than 35 years | D32: 35 to 44 years | E32: 45 to 54 years | F32: 55 to 64 years | G32: 65 years and over | H32: All
B33: 1 | C33: =C5-C19 -> -30617 | D33: =D5-D19 -> -24024 | E33: =E5-E19 -> -37052 | F33: =F5-F19 -> -46628 | G33: =G5-G19 -> -23837 | H33: =H5-H19 -> -30364
B34: 2 | C34: =C6-C20 -> -6182 | D34: =D6-D20 -> -17810 | E34: =E6-E20 -> -24187 | F34: =F6-F20 -> -29295 | G34: =G6-G20 -> -11244 | H34: =H6-H20 -> -15671
B35: 3 | C35: =C7-C21 -> 890 | D35: =D7-D21 -> -6319 | E35: =E7-E21 -> -28092 | F35: =F7-F21 -> -23584 | G35: =G7-G21 -> -10029 | H35: =H7-H21 -> -12268
B36: 4 | C36: =C8-C22 -> 30848 | D36: =D8-D22 -> 25100 | E36: =E8-E22 -> 270 | F36: =F8-F22 -> -7894 | G36: =G8-G22 -> 6057 | H36: =H8-H22 -> 11147
B37: 5 | C37: =C9-C23 -> 53499 | D37: =D9-D23 -> 56043 | E37: =E9-E23 -> 78141 | F37: =F9-F23 -> 46688 | G37: =G9-G23 -> 70890 | H37: =H9-H23 -> 60652
B38: All | C38: =C10-C24 -> 8853 | D38: =D10-D24 -> 9199 | E38: =E10-E24 -> 2850 | F38: =F10-F24 -> -5932 | G38: =G10-G24 -> -4 | H38: =H10-H24 -> 2699
B43: Implied Savings Rate
B44: Annual cash flow as a % of annual income
C45: Age Group
B46: Income Quintile | C46: Less than 35 years | D46: 35 to 44 years | E46: 45 to 54 years | F46: 55 to 64 years | G46: 65 years and over | H46: All
B47: 1 | C47: =C33/C5 -> -0.95249502 | D47: =D33/D5 -> -0.61238848 | E47: =E33/E5 -> -0.93294725 | F47: =F33/F5 -> -1.894677 | G47: =G33/G5 -> -0.82954585 | H47: =H33/H5 -> -0.96076446
B48: 2 | C48: =C34/C6 -> -0.082286231 | D48: =D34/D6 -> -0.2244034 | E48: =E34/E6 -> -0.38595455 | F48: =F34/F6 -> -0.52694535 | G48: =G34/G6 -> -0.2526628 | H48: =H34/H6 -> -0.26361297
B49: 3 | C49: =C35/C7 -> 0.0099883282 | D49: =D35/D7 -> -0.067518619 | E49: =E35/E7 -> -0.28592366 | F49: =F35/F7 -> -0.33582047 | G49: =G35/G7 -> -0.17276783 | H49: =H35/H7 -> -0.15529507
B50: 4 | C50: =C36/C8 -> 0.25822221 | D50: =D36/D8 -> 0.18249502 | E50: =E36/E8 -> 0.001988174 | F50: =F36/F8 -> -0.073864062 | G50: =G36/G8 -> 0.076647601 | H50: =H36/H8 -> 0.097511263
B51: 5 | C51: =C37/C9 -> 0.29327698 | D51: =D37/D9 -> 0.2986905 | E51: =E37/E9 -> 0.29824581 | F51: =F37/F9 -> 0.24150631 | G51: =G37/G9 -> 0.4232441 | H51: =H37/H9 -> 0.30683928
B52: All | C52: =C38/C10 -> 0.090552027 | D52: =D38/D10 -> 0.081933484 | E52: =E38/E10 -> 0.021900671 | F52: =F38/F10 -> -0.058472154 | G52: =G38/G10 -> -6.0847607e-05 | H52: =H38/H10 -> 0.027996183

Sheet All Ages Over Time
B2: All Ages
B3: Current Prices, per HH
C4: 1999 | D4: =C4+1 -> 2000 | E4: =D4+1 -> 2001 | F4: =E4+1 -> 2002 | G4: =F4+1 -> 2003 | H4: =G4+1 -> 2004 | I4: =H4+1 -> 2005 | J4: =I4+1 -> 2006 | K4: =J4+1 -> 2007 | ... AA4: =Z4+1 -> 2023
B5: Quintile 1
B6: Income | C6: ='All Ages Over Time Data'!B14 -> 14555 | D6: ='All Ages Over Time Data'!C14 -> 14731 | E6: ='All Ages Over Time Data'!D14 -> 15985 | F6: ='All Ages Over Time Data'!E14 -> 16110 | G6: ='All Ages Over Time Data'!F14 -> 16719 | H6: ='All Ages Over Time Data'!G14 -> 16792 | I6: ='All Ages Over Time Data'!H14 -> 16468 | J6: ='All Ages Over Time Data'!I14 -> 18060 | ... AA6: ='All Ages Over Time Data'!Z14 -> 31604
B7: Spending | C7: ='All Ages Over Time Data'!B21 -> 24102 | D7: ='All Ages Over Time Data'!C21 -> 25810 | E7: ='All Ages Over Time Data'!D21 -> 25104 | F7: ='All Ages Over Time Data'!E21 -> 27210 | G7: ='All Ages Over Time Data'!F21 -> 27705 | H7: ='All Ages Over Time Data'!G21 -> 29959 | I7: ='All Ages Over Time Data'!H21 -> 32395 | J7: ='All Ages Over Time Data'!I21 -> 35870 | ... AA7: ='All Ages Over Time Data'!Z21 -> 61968
B8: Cash Flow | C8: =C6-C7 -> -9547 | D8: =D6-D7 -> -11079 | E8: =E6-E7 -> -9119 | F8: =F6-F7 -> -11100 | G8: =G6-G7 -> -10986 | H8: =H6-H7 -> -13167 | I8: =I6-I7 -> -15927 | J8: =J6-J7 -> -17810 | ... AA8: =AA6-AA7 -> -30364
B9: Y/Y Change | D9: =D8/C8-1 -> 0.16046926 | E9: =E8/D8-1 -> -0.17691127 | F9: =F8/E8-1 -> 0.21723873 | G9: =G8/F8-1 -> -0.01027027 | H9: =H8/G8-1 -> 0.1985254 | I9: =I8/H8-1 -> 0.20961495 | J9: =J8/I8-1 -> 0.11822691 | K9: =K8/J8-1 -> 0.029365525 | ... AA9: =AA8/Z8-1 -> 0.058310969
B11: Quintile 2
B12: Income | C12: ='All Ages Over Time Data'!AA14 -> 28992 | D12: ='All Ages Over Time Data'!AB14 -> 29772 | E12: ='All Ages Over Time Data'!AC14 -> 31982 | F12: ='All Ages Over Time Data'!AD14 -> 32572 | G12: ='All Ages Over Time Data'!AE14 -> 32696 | H12: ='All Ages Over Time Data'!AF14 -> 33458 | I12: ='All Ages Over Time Data'!AG14 -> 34434 | J12: ='All Ages Over Time Data'!AH14 -> 36489 | ... AA12: ='All Ages Over Time Data'!AY14 -> 59447
B13: Spending | C13: ='All Ages Over Time Data'!AA21 -> 35653 | D13: ='All Ages Over Time Data'!AB21 -> 36532 | E13: ='All Ages Over Time Data'!AC21 -> 37719 | F13: ='All Ages Over Time Data'!AD21 -> 39584 | G13: ='All Ages Over Time Data'!AE21 -> 40794 | H13: ='All Ages Over Time Data'!AF21 -> 42638 | I13: ='All Ages Over Time Data'!AG21 -> 44142 | J13: ='All Ages Over Time Data'!AH21 -> 45967 | ... AA13: ='All Ages Over Time Data'!AY21 -> 75118
B14: Cash Flow | C14: =C12-C13 -> -6661 | D14: =D12-D13 -> -6760 | E14: =E12-E13 -> -5737 | F14: =F12-F13 -> -7012 | G14: =G12-G13 -> -8098 | H14: =H12-H13 -> -9180 | I14: =I12-I13 -> -9708 | J14: =J12-J13 -> -9478 | ... AA14: =AA12-AA13 -> -15671
B15: Y/Y Change | D15: =D14/C14-1 -> 0.014862633 | E15: =E14/D14-1 -> -0.15133136 | F15: =F14/E14-1 -> 0.22224159 | G15: =G14/F14-1 -> 0.15487735 | H15: =H14/G14-1 -> 0.13361324 | I15: =I14/H14-1 -> 0.05751634 | J15: =J14/I14-1 -> -0.023691801 | K15: =K14/J14-1 -> 0.10592952 | ... AA15: =AA14/Z14-1 -> 0.20157951
B17: Quintile 3
B18: Income | C18: ='All Ages Over Time Data'!AZ14 -> 40456 | D18: ='All Ages Over Time Data'!BA14 -> 41187 | E18: ='All Ages Over Time Data'!BB14 -> 42930 | F18: ='All Ages Over Time Data'!BC14 -> 43409 | G18: ='All Ages Over Time Data'!BD14 -> 44902 | H18: ='All Ages Over Time Data'!BE14 -> 45754 | I18: ='All Ages Over Time Data'!BF14 -> 46857 | J18: ='All Ages Over Time Data'!BG14 -> 49509 | ... AA18: ='All Ages Over Time Data'!BX14 -> 78998
B19: Spending | C19: ='All Ages Over Time Data'!AZ21 -> 45044 | D19: ='All Ages Over Time Data'!BA21 -> 46513 | E19: ='All Ages Over Time Data'!BB21 -> 48811 | F19: ='All Ages Over Time Data'!BC21 -> 50036 | G19: ='All Ages Over Time Data'!BD21 -> 51391 | H19: ='All Ages Over Time Data'!BE21 -> 52277 | I19: ='All Ages Over Time Data'!BF21 -> 54391 | J19: ='All Ages Over Time Data'!BG21 -> 56189 | ... AA19: ='All Ages Over Time Data'!BX21 -> 91266
B20: Cash Flow | C20: =C18-C19 -> -4588 | D20: =D18-D19 -> -5326 | E20: =E18-E19 -> -5881 | F20: =F18-F19 -> -6627 | G20: =G18-G19 -> -6489 | H20: =H18-H19 -> -6523 | I20: =I18-I19 -> -7534 | J20: =J18-J19 -> -6680 | ... AA20: =AA18-AA19 -> -12268
B21: Y/Y Change | D21: =D20/C20-1 -> 0.1608544 | E21: =E20/D20-1 -> 0.10420578 | F21: =F20/E20-1 -> 0.12684918 | G21: =G20/F20-1 -> -0.020823902 | H21: =H20/G20-1 -> 0.0052396363 | I21: =I20/H20-1 -> 0.15499004 | J21: =J20/I20-1 -> -0.1133528 | K21: =K20/J20-1 -> 0.087275449 | ... AA21: =AA20/Z20-1 -> 0.14922717
B23: Quintile 4
B24: Income | C24: ='All Ages Over Time Data'!BY14 -> 53967 | D24: ='All Ages Over Time Data'!BZ14 -> 55257 | E24: ='All Ages Over Time Data'!CA14 -> 57948 | F24: ='All Ages Over Time Data'!CB14 -> 60528 | G24: ='All Ages Over Time Data'!CC14 -> 60636 | H24: ='All Ages Over Time Data'!CD14 -> 62590 | I24: ='All Ages Over Time Data'!CE14 -> 64135 | J24: ='All Ages Over Time Data'!CF14 -> 66336 | ... AA24: ='All Ages Over Time Data'!CW14 -> 114315
B25: Spending | C25: ='All Ages Over Time Data'!BY21 -> 53527 | D25: ='All Ages Over Time Data'!BZ21 -> 56197 | E25: ='All Ages Over Time Data'!CA21 -> 58443 | F25: ='All Ages Over Time Data'!CB21 -> 60269 | G25: ='All Ages Over Time Data'!CC21 -> 63583 | H25: ='All Ages Over Time Data'!CD21 -> 63006 | I25: ='All Ages Over Time Data'!CE21 -> 65997 | J25: ='All Ages Over Time Data'!CF21 -> 67937 | ... AA25: ='All Ages Over Time Data'!CW21 -> 103168
B26: Cash Flow | C26: =C24-C25 -> 440 | D26: =D24-D25 -> -940 | E26: =E24-E25 -> -495 | F26: =F24-F25 -> 259 | G26: =G24-G25 -> -2947 | H26: =H24-H25 -> -416 | I26: =I24-I25 -> -1862 | J26: =J24-J25 -> -1601 | ... AA26: =AA24-AA25 -> 11147
B27: Y/Y Change | D27: =D26/C26-1 -> -3.1363636 | E27: =E26/D26-1 -> -0.47340426 | F27: =F26/E26-1 -> -1.5232323 | G27: =G26/F26-1 -> -12.378378 | H27: =H26/G26-1 -> -0.8588395 | I27: =I26/H26-1 -> 3.4759615 | J27: =J26/I26-1 -> -0.14017186 | K27: =K26/J26-1 -> 0.18488445 | ... AA27: =AA26/Z26-1 -> 0.023317727
B29: Quintile 5
B30: Income | C30: ='All Ages Over Time Data'!CX14 -> 92502 | D30: ='All Ages Over Time Data'!CY14 -> 99880 | E30: ='All Ages Over Time Data'!CZ14 -> 102327 | F30: ='All Ages Over Time Data'!DA14 -> 105850 | G30: ='All Ages Over Time Data'!DB14 -> 108511 | H30: ='All Ages Over Time Data'!DC14 -> 113861 | I30: ='All Ages Over Time Data'!DD14 -> 117390 | J30: ='All Ages Over Time Data'!DE14 -> 125058 | ... AA30: ='All Ages Over Time Data'!DV14 -> 197667
B31: Spending | C31: ='All Ages Over Time Data'!CX21 -> 75203 | D31: ='All Ages Over Time Data'!CY21 -> 79655 | E31: ='All Ages Over Time Data'!CZ21 -> 81051 | F31: ='All Ages Over Time Data'!DA21 -> 84998 | G31: ='All Ages Over Time Data'!DB21 -> 87129 | H31: ='All Ages Over Time Data'!DC21 -> 91512 | I31: ='All Ages Over Time Data'!DD21 -> 94322 | J31: ='All Ages Over Time Data'!DE21 -> 96839 | ... AA31: ='All Ages Over Time Data'!DV21 -> 137015
B32: Cash Flow | C32: =C30-C31 -> 17299 | D32: =D30-D31 -> 20225 | E32: =E30-E31 -> 21276 | F32: =F30-F31 -> 20852 | G32: =G30-G31 -> 21382 | H32: =H30-H31 -> 22349 | I32: =I30-I31 -> 23068 | J32: =J30-J31 -> 28219 | ... AA32: =AA30-AA31 -> 60652
B33: Y/Y Change | D33: =D32/C32-1 -> 0.16914273 | E33: =E32/D32-1 -> 0.051965389 | F33: =F32/E32-1 -> -0.019928558 | G33: =G32/F32-1 -> 0.025417226 | H33: =H32/G32-1 -> 0.045224956 | I33: =I32/H32-1 -> 0.032171462 | J33: =J32/I32-1 -> 0.22329634 | K33: =K32/J32-1 -> 0.0030121549 | ... AA33: =AA32/Z32-1 -> 0.12210464
B35: CPI | C35: =CPI!B12 -> 92.9 | D35: =CPI!C12 -> 95.4 | E35: =CPI!D12 -> 97.8 | F35: =CPI!E12 -> 100 | G35: =CPI!F12 -> 102.8 | H35: =CPI!G12 -> 104.7 | I35: =CPI!H12 -> 107 | J35: =CPI!I12 -> 109.1 | ... AA35: =CPI!Z12 -> 157.1
B37: Under 35 Age Group -- Per Household Values
B38: 2023 Dollars, per HH
C39: 1999 | D39: =C39+1 -> 2000 | E39: =D39+1 -> 2001 | F39: =E39+1 -> 2002 | G39: =F39+1 -> 2003 | H39: =G39+1 -> 2004 | I39: =H39+1 -> 2005 | J39: =I39+1 -> 2006 | K39: =J39+1 -> 2007 | ... AA39: =Z39+1 -> 2023
B40: Quintile 1
B41: Income | C41: =C6*($AA$35/C$35) -> 24613.461 | D41: =D6*($AA$35/D$35) -> 24258.282 | E41: =E6*($AA$35/E$35) -> 25677.336 | F41: =F6*($AA$35/F$35) -> 25308.81 | G41: =G6*($AA$35/G$35) -> 25550.145 | H41: =H6*($AA$35/H$35) -> 25196.019 | I41: =I6*($AA$35/I$35) -> 24178.718 | J41: =J6*($AA$35/J$35) -> 26005.738 | ... AA41: =AA6*($AA$35/AA$35) -> 31604
B42: Spending | C42: =C7*($AA$35/C$35) -> 40758.065 | D42: =D7*($AA$35/D$35) -> 42502.631 | E42: =E7*($AA$35/E$35) -> 40325.546 | F42: =F7*($AA$35/F$35) -> 42746.91 | G42: =G7*($AA$35/G$35) -> 42339.061 | H42: =H7*($AA$35/H$35) -> 44952.807 | I42: =I7*($AA$35/I$35) -> 47563.126 | J42: =J7*($AA$35/J$35) -> 51651.485 | ... AA42: =AA7*($AA$35/AA$35) -> 61968
B43: Cash Flow | C43: =C41-C42 -> -16144.604 | D43: =D41-D42 -> -18244.349 | E43: =E41-E42 -> -14648.21 | F43: =F41-F42 -> -17438.1 | G43: =G41-G42 -> -16788.916 | H43: =H41-H42 -> -19756.788 | I43: =I41-I42 -> -23384.408 | J43: =J41-J42 -> -25645.747 | ... AA43: =AA41-AA42 -> -30364
B44: Y/Y Change | D44: =D43/C43-1 -> 0.13005864 | E44: =E43/D43-1 -> -0.19710977 | F44: =F43/E43-1 -> 0.19045948 | G44: =G43/F43-1 -> -0.037227889 | H44: =H43/G43-1 -> 0.17677565 | I44: =I43/H43-1 -> 0.18361388 | J44: =J43/I43-1 -> 0.096702836 | K44: =K43/J43-1 -> 0.0072087783 | ... AA44: =AA43/Z43-1 -> 0.018565363
B46: Quintile 2
B47: Income | C47: =C12*($AA$35/C$35) -> 49027.376 | D47: =D12*($AA$35/D$35) -> 49027.057 | E47: =E12*($AA$35/E$35) -> 51373.949 | F47: =F12*($AA$35/F$35) -> 51170.612 | G47: =G12*($AA$35/G$35) -> 49966.358 | H47: =H12*($AA$35/H$35) -> 50202.978 | I47: =I12*($AA$35/I$35) -> 50556.836 | J47: =J12*($AA$35/J$35) -> 52542.822 | ... AA47: =AA12*($AA$35/AA$35) -> 59447
B48: Spending | C48: =C13*($AA$35/C$35) -> 60291.564 | D48: =D13*($AA$35/D$35) -> 60159.09 | E48: =E13*($AA$35/E$35) -> 60589.518 | F48: =F13*($AA$35/F$35) -> 62186.464 | G48: =G13*($AA$35/G$35) -> 62341.804 | H48: =H13*($AA$35/H$35) -> 63977.362 | I48: =I13*($AA$35/I$35) -> 64810.357 | J48: =J13*($AA$35/J$35) -> 66190.795 | ... AA48: =AA13*($AA$35/AA$35) -> 75118
B49: Cash Flow | C49: =C47-C48 -> -11264.188 | D49: =D47-D48 -> -11132.034 | E49: =E47-E48 -> -9215.5695 | F49: =F47-F48 -> -11015.852 | G49: =G47-G48 -> -12375.446 | H49: =H47-H48 -> -13774.384 | I49: =I47-I48 -> -14253.521 | J49: =J47-J48 -> -13647.973 | ... AA49: =AA47-AA48 -> -15671
B50: Y/Y Change | D50: =D49/C49-1 -> -0.011732299 | E50: =E49/D49-1 -> -0.17215759 | F50: =F49/E49-1 -> 0.19535227 | G50: =G49/F49-1 -> 0.12342155 | H50: =H49/G49-1 -> 0.11304146 | I50: =I49/H49-1 -> 0.03478468 | J50: =J49/I49-1 -> -0.042484167 | K50: =K49/J49-1 -> 0.08212476 | ... AA50: =AA49/Z49-1 -> 0.15645336
B52: Quintile 3
B53: Income | C53: =C18*($AA$35/C$35) -> 68413.752 | D53: =D18*($AA$35/D$35) -> 67824.714 | E53: =E18*($AA$35/E$35) -> 68960.153 | F53: =F18*($AA$35/F$35) -> 68195.539 | G53: =G18*($AA$35/G$35) -> 68619.691 | H53: =H18*($AA$35/H$35) -> 68652.85 | I53: =I18*($AA$35/I$35) -> 68796.586 | J53: =J18*($AA$35/J$35) -> 71291.145 | ... AA53: =AA18*($AA$35/AA$35) -> 78998
B54: Spending | C54: =C19*($AA$35/C$35) -> 76172.362 | D54: =D19*($AA$35/D$35) -> 76595.307 | E54: =E19*($AA$35/E$35) -> 78407.036 | F54: =F19*($AA$35/F$35) -> 78606.556 | G54: =G19*($AA$35/G$35) -> 78536.246 | H54: =H19*($AA$35/H$35) -> 78440.465 | I54: =I19*($AA$35/I$35) -> 79858.188 | J54: =J19*($AA$35/J$35) -> 80910.1 | ... AA54: =AA19*($AA$35/AA$35) -> 91266
B55: Cash Flow | C55: =C53-C54 -> -7758.6093 | D55: =D53-D54 -> -8770.5933 | E55: =E53-E54 -> -9446.8824 | F55: =F53-F54 -> -10411.017 | G55: =G53-G54 -> -9916.5554 | H55: =H53-H54 -> -9787.6151 | I55: =I53-I54 -> -11061.602 | J55: =J53-J54 -> -9618.9551 | ... AA55: =AA53-AA54 -> -12268
B56: Y/Y Change | D56: =D55/C55-1 -> 0.13043369 | E56: =E55/D55-1 -> 0.077108709 | F56: =F55/E55-1 -> 0.10205849 | G56: =G55/F55-1 -> -0.047494068 | H56: =H55/G55-1 -> -0.013002535 | I56: =I55/H55-1 -> 0.13016315 | J56: =J55/I55-1 -> -0.13041934 | K56: =K55/J55-1 -> 0.063872211 | ... AA56: =AA55/Z55-1 -> 0.10606714
B58: Quintile 4
B59: Income | C59: =C24*($AA$35/C$35) -> 91261.741 | D59: =D24*($AA$35/D$35) -> 90994.494 | E59: =E24*($AA$35/E$35) -> 93084.16 | F59: =F24*($AA$35/F$35) -> 95089.488 | G59: =G24*($AA$35/G$35) -> 92664.549 | H59: =H24*($AA$35/H$35) -> 93914.89 | I59: =I24*($AA$35/I$35) -> 94164.565 | J59: =J24*($AA$35/J$35) -> 95521.408 | ... AA59: =AA24*($AA$35/AA$35) -> 114315
B60: Spending | C60: =C25*($AA$35/C$35) -> 90517.672 | D60: =D25*($AA$35/D$35) -> 92542.439 | E60: =E25*($AA$35/E$35) -> 93879.298 | F60: =F25*($AA$35/F$35) -> 94682.599 | G60: =G25*($AA$35/G$35) -> 97168.184 | H60: =H25*($AA$35/H$35) -> 94539.089 | I60: =I25*($AA$35/I$35) -> 96898.399 | J60: =J25*($AA$35/J$35) -> 97826.789 | ... AA60: =AA25*($AA$35/AA$35) -> 103168
B61: Cash Flow | C61: =C59-C60 -> 744.06889 | D61: =D59-D60 -> -1547.9455 | E61: =E59-E60 -> -795.13804 | F61: =F59-F60 -> 406.889 | G61: =G59-G60 -> -4503.6352 | H61: =H59-H60 -> -624.19866 | I61: =I59-I60 -> -2733.8336 | J61: =J59-J60 -> -2305.3813 | ... AA61: =AA59-AA60 -> 11147
B62: Y/Y Change | D62: =D61/C61-1 -> -3.0803793 | E62: =E61/D61-1 -> -0.48632685 | F62: =F61/E61-1 -> -1.5117212 | G62: =G61/F61-1 -> -12.068461 | H62: =H61/G61-1 -> -0.86140115 | I62: =I61/H61-1 -> 3.3797493 | J62: =J61/I61-1 -> -0.15672217 | K62: =K61/J61-1 -> 0.15938021 | ... AA62: =AA61/Z61-1 -> -0.015113684
B64: Quintile 5
B65: Income | C65: =C30*($AA$35/C$35) -> 156426.96 | D65: =D30*($AA$35/D$35) -> 164477.44 | E65: =E30*($AA$35/E$35) -> 164371.9 | F65: =F30*($AA$35/F$35) -> 166290.35 | G65: =G30*($AA$35/G$35) -> 165827.61 | H65: =H30*($AA$35/H$35) -> 170845.87 | I65: =I30*($AA$35/I$35) -> 172354.85 | J65: =J30*($AA$35/J$35) -> 180078.93 | ... AA65: =AA30*($AA$35/AA$35) -> 197667
B66: Spending | C66: =C31*($AA$35/C$35) -> 127173.21 | D66: =D31*($AA$35/D$35) -> 131171.91 | E66: =E31*($AA$35/E$35) -> 130195.42 | F66: =F31*($AA$35/F$35) -> 133531.86 | G66: =G31*($AA$35/G$35) -> 133151.42 | H66: =H31*($AA$35/H$35) -> 137311.7 | I66: =I31*($AA$35/I$35) -> 138485.85 | J66: =J31*($AA$35/J$35) -> 139444.61 | ... AA66: =AA31*($AA$35/AA$35) -> 137015
B67: Cash Flow | C67: =C65-C66 -> 29253.745 | D67: =D65-D66 -> 33305.529 | E67: =E65-E66 -> 34176.479 | F67: =F65-F66 -> 32758.492 | G67: =G65-G66 -> 32676.189 | H67: =H65-H66 -> 33534.173 | I67: =I65-I66 -> 33868.998 | J67: =J65-J66 -> 40634.325 | ... AA67: =AA65-AA66 -> 60652
B68: Y/Y Change | D68: =D67/C67-1 -> 0.13850481 | E68: =E67/D67-1 -> 0.026150288 | F68: =F67/E67-1 -> -0.04149013 | G68: =G67/F67-1 -> -0.0025124259 | H68: =H67/G67-1 -> 0.026257167 | I68: =I67/H67-1 -> 0.0099845986 | J68: =J67/I67-1 -> 0.19974985 | K68: =K67/J67-1 -> -0.018577344 | ... AA68: =AA67/Z67-1 -> 0.079963218
B70: Delta | C70: =C67-C43 -> 45398.349 | D70: =D67-D43 -> 51549.878 | E70: =E67-E43 -> 48824.688 | F70: =F67-F43 -> 50196.592 | G70: =G67-G43 -> 49465.105 | H70: =H67-H43 -> 53290.961 | I70: =I67-I43 -> 57253.407 | J70: =J67-J43 -> 66280.072 | ... AA70: =AA67-AA43 -> 91016
Q73: Consider showing this as an area chart instead -- with color fill between line and y=0 axis

Sheet Under 35 Over Time
B2: Under 35 Age Group -- Per Household Values
B3: Current Prices
C4: 1999 | D4: =C4+1 -> 2000 | E4: =D4+1 -> 2001 | F4: =E4+1 -> 2002 | G4: =F4+1 -> 2003 | H4: =G4+1 -> 2004 | I4: =H4+1 -> 2005 | J4: =I4+1 -> 2006 | K4: =J4+1 -> 2007 | ... AA4: =Z4+1 -> 2023
B5: Under 35 -- Lowest Quintile
B6: Income | C6: ='Under 35 per HH Over Time'!B14 -> 14002 | D6: ='Under 35 per HH Over Time'!C14 -> 14089 | E6: ='Under 35 per HH Over Time'!D14 -> 14590 | F6: ='Under 35 per HH Over Time'!E14 -> 14976 | G6: ='Under 35 per HH Over Time'!F14 -> 15216 | H6: ='Under 35 per HH Over Time'!G14 -> 16089 | I6: ='Under 35 per HH Over Time'!H14 -> 15822 | J6: ='Under 35 per HH Over Time'!I14 -> 17790 | ... AA6: ='Under 35 per HH Over Time'!Z14 -> 32144
B7: Spending | C7: ='Under 35 per HH Over Time'!B21 -> 21246 | D7: ='Under 35 per HH Over Time'!C21 -> 23543 | E7: ='Under 35 per HH Over Time'!D21 -> 23106 | F7: ='Under 35 per HH Over Time'!E21 -> 25293 | G7: ='Under 35 per HH Over Time'!F21 -> 25826 | H7: ='Under 35 per HH Over Time'!G21 -> 27761 | I7: ='Under 35 per HH Over Time'!H21 -> 30538 | J7: ='Under 35 per HH Over Time'!I21 -> 35167 | ... AA7: ='Under 35 per HH Over Time'!Z21 -> 62761
B8: Cash Flow | C8: =C6-C7 -> -7244 | D8: =D6-D7 -> -9454 | E8: =E6-E7 -> -8516 | F8: =F6-F7 -> -10317 | G8: =G6-G7 -> -10610 | H8: =H6-H7 -> -11672 | I8: =I6-I7 -> -14716 | J8: =J6-J7 -> -17377 | ... AA8: =AA6-AA7 -> -30617
B9: Y/Y Change | D9: =D8/C8-1 -> 0.30508007 | E9: =E8/D8-1 -> -0.099217263 | F9: =F8/E8-1 -> 0.21148426 | G9: =G8/F8-1 -> 0.028399729 | H9: =H8/G8-1 -> 0.10009425 | I9: =I8/H8-1 -> 0.26079507 | J9: =J8/I8-1 -> 0.18082359 | K9: =K8/J8-1 -> 0.068366231 | ... AA9: =AA8/Z8-1 -> 0.10038097
B11: Under 35 -- Highest Quintile
B12: Income | C12: ='Under 35 per HH Over Time'!AA14 -> 82093 | D12: ='Under 35 per HH Over Time'!AB14 -> 85719 | E12: ='Under 35 per HH Over Time'!AC14 -> 86051 | F12: ='Under 35 per HH Over Time'!AD14 -> 88957 | G12: ='Under 35 per HH Over Time'!AE14 -> 88944 | H12: ='Under 35 per HH Over Time'!AF14 -> 93273 | I12: ='Under 35 per HH Over Time'!AG14 -> 100011 | J12: ='Under 35 per HH Over Time'!AH14 -> 98445 | ... AA12: ='Under 35 per HH Over Time'!AY14 -> 182418
B13: Spending | C13: ='Under 35 per HH Over Time'!AA21 -> 69707 | D13: ='Under 35 per HH Over Time'!AB21 -> 68117 | E13: ='Under 35 per HH Over Time'!AC21 -> 66937 | F13: ='Under 35 per HH Over Time'!AD21 -> 69533 | G13: ='Under 35 per HH Over Time'!AE21 -> 70861 | H13: ='Under 35 per HH Over Time'!AF21 -> 72890 | I13: ='Under 35 per HH Over Time'!AG21 -> 81337 | J13: ='Under 35 per HH Over Time'!AH21 -> 80414 | ... AA13: ='Under 35 per HH Over Time'!AY21 -> 128919
B14: Cash Flow | C14: =C12-C13 -> 12386 | D14: =D12-D13 -> 17602 | E14: =E12-E13 -> 19114 | F14: =F12-F13 -> 19424 | G14: =G12-G13 -> 18083 | H14: =H12-H13 -> 20383 | I14: =I12-I13 -> 18674 | J14: =J12-J13 -> 18031 | ... AA14: =AA12-AA13 -> 53499
B15: Y/Y Change | D15: =D14/C14-1 -> 0.42112062 | E15: =E14/D14-1 -> 0.08589933 | F15: =F14/E14-1 -> 0.016218479 | G15: =G14/F14-1 -> -0.069038303 | H15: =H14/G14-1 -> 0.12719128 | I15: =I14/H14-1 -> -0.08384438 | J15: =J14/I14-1 -> -0.034432901 | K15: =K14/J14-1 -> 0.1949975 | ... AA15: =AA14/Z14-1 -> -0.21098739
B17: CPI | C17: =CPI!B12 -> 92.9 | D17: =CPI!C12 -> 95.4 | E17: =CPI!D12 -> 97.8 | F17: =CPI!E12 -> 100 | G17: =CPI!F12 -> 102.8 | H17: =CPI!G12 -> 104.7 | I17: =CPI!H12 -> 107 | J17: =CPI!I12 -> 109.1 | ... AA17: =CPI!Z12 -> 157.1
B19: Under 35 Age Group -- Per Household Values
B20: 2023 Dollars
C21: 1999 | D21: =C21+1 -> 2000 | E21: =D21+1 -> 2001 | F21: =E21+1 -> 2002 | G21: =F21+1 -> 2003 | H21: =G21+1 -> 2004 | I21: =H21+1 -> 2005 | J21: =I21+1 -> 2006 | K21: =J21+1 -> 2007 | ... AA21: =Z21+1 -> 2023
B22: Under 35 -- Lowest Quintile
B23: Income | C23: =C6*($AA$17/C$17) -> 23678.301 | D23: =D6*($AA$17/D$17) -> 23201.068 | E23: =E6*($AA$17/E$17) -> 23436.493 | F23: =F6*($AA$17/F$17) -> 23527.296 | G23: =G6*($AA$17/G$17) -> 23253.245 | H23: =H6*($AA$17/H$17) -> 24141.183 | I23: =I6*($AA$17/I$17) -> 23230.245 | J23: =J6*($AA$17/J$17) -> 25616.948 | ... AA23: =AA6*($AA$17/AA$17) -> 32144
B24: Spending | C24: =C7*($AA$17/C$17) -> 35928.381 | D24: =D7*($AA$17/D$17) -> 38769.448 | E24: =E7*($AA$17/E$17) -> 37116.08 | F24: =F7*($AA$17/F$17) -> 39735.303 | G24: =G7*($AA$17/G$17) -> 39467.554 | H24: =H7*($AA$17/H$17) -> 41654.757 | I24: =I7*($AA$17/I$17) -> 44836.634 | J24: =J7*($AA$17/J$17) -> 50639.191 | ... AA24: =AA7*($AA$17/AA$17) -> 62761
B25: Cash Flow | C25: =C23-C24 -> -12250.08 | D25: =D23-D24 -> -15568.379 | E25: =E23-E24 -> -13679.587 | F25: =F23-F24 -> -16208.007 | G25: =G23-G24 -> -16214.309 | H25: =H23-H24 -> -17513.574 | I25: =I23-I24 -> -21606.389 | J25: =J23-J24 -> -25022.243 | ... AA25: =AA23-AA24 -> -30617
B26: Y/Y Change | D26: =D25/C25-1 -> 0.27087985 | E26: =E25/D25-1 -> -0.12132236 | F26: =F25/E25-1 -> 0.18483161 | G26: =G25/F25-1 -> 0.00038884105 | H26: =H25/G25-1 -> 0.080130745 | I26: =I25/H25-1 -> 0.23369386 | J26: =J25/I25-1 -> 0.15809463 | K26: =K25/J25-1 -> 0.045370007 | ... AA26: =AA25/Z25-1 -> 0.059055392
B28: Under 35 -- Highest Quintile
B29: Income | C29: =C12*($AA$17/C$17) -> 138824.65 | D29: =D12*($AA$17/D$17) -> 141157.81 | E29: =E12*($AA$17/E$17) -> 138227.12 | F29: =F12*($AA$17/F$17) -> 139751.45 | G29: =G12*($AA$17/G$17) -> 135925.12 | H29: =H12*($AA$17/H$17) -> 139954.04 | I29: =I12*($AA$17/I$17) -> 146838.58 | J29: =J12*($AA$17/J$17) -> 141757.19 | ... AA29: =AA12*($AA$17/AA$17) -> 182418
B30: Spending | C30: =C13*($AA$17/C$17) -> 117879.11 | D30: =D13*($AA$17/D$17) -> 112171.71 | E30: =E13*($AA$17/E$17) -> 107523.54 | F30: =F13*($AA$17/F$17) -> 109236.34 | G30: =G13*($AA$17/G$17) -> 108290.5 | H30: =H13*($AA$17/H$17) -> 109369.81 | I30: =I13*($AA$17/I$17) -> 119420.96 | J30: =J13*($AA$17/J$17) -> 115793.21 | ... AA30: =AA13*($AA$17/AA$17) -> 128919
B31: Cash Flow | C31: =C29-C30 -> 20945.539 | D31: =D29-D30 -> 28986.103 | E31: =E29-E30 -> 30703.573 | F31: =F29-F30 -> 30515.104 | G31: =G29-G30 -> 27634.624 | H31: =H29-H30 -> 30584.234 | I31: =I29-I30 -> 27417.621 | J31: =J29-J30 -> 25963.979 | ... AA31: =AA29-AA30 -> 53499
B32: Y/Y Change | D32: =D31/C31-1 -> 0.38387951 | E32: =E31/D31-1 -> 0.059251493 | F32: =F31/E31-1 -> -0.0061383279 | G32: =G31/F31-1 -> -0.094395237 | H32: =H31/G31-1 -> 0.10673605 | I32: =I31/H31-1 -> -0.10353744 | J32: =J31/I31-1 -> -0.053018519 | K32: =K31/J31-1 -> 0.16927558 | ... AA32: =AA31/Z31-1 -> -0.24061931
B34: Delta | C34: =C31-C25 -> 33195.619 | D34: =D31-D25 -> 44554.482 | E34: =E31-E25 -> 44383.16 | F34: =F31-F25 -> 46723.111 | G34: =G31-G25 -> 43848.933 | H34: =H31-H25 -> 48097.808 | I34: =I31-I25 -> 49024.009 | J34: =J31-J25 -> 50986.222 | ... AA34: =AA31-AA25 -> 84116

Sheet Net Worth
C3: Quintile
B4: Net Worth (Nominal) | C4: 1 | D4: 2 | E4: 3 | F4: 4 | G4: 5 | H4: All
B5: Q4 2010 | C5: ='Net Worth Over Time by Quintile'!BJ24 -> -11976 | D5: ='Net Worth Over Time by Quintile'!DO24 -> 49882 | E5: ='Net Worth Over Time by Quintile'!FT24 -> 219359 | F5: ='Net Worth Over Time by Quintile'!HY24 -> 530601 | G5: ='Net Worth Over Time by Quintile'!KD24 -> 1748713 | H5: ='Net Worth Over Time by Quintile'!E24 -> 507316
B6: Q4 2023 | C6: ='Net Worth Over Time by Quintile'!DJ24 -> -1141 | D6: ='Net Worth Over Time by Quintile'!FO24 -> 135497 | E6: ='Net Worth Over Time by Quintile'!HT24 -> 454074 | F6: ='Net Worth Over Time by Quintile'!JY24 -> 996641 | G6: ='Net Worth Over Time by Quintile'!MD24 -> 3311107 | H6: ='Net Worth Over Time by Quintile'!BE24 -> 979236
B8: CPI
B9: Q4 2010 | H9: =CPI!M12 -> 116.5
B10: Q4 2023 | H10: =CPI!Z12 -> 157.1
C12: Quintile
B13: Net Worth (Real) | C13: Quintile 1 | D13: Quintile 2 | E13: Quintile 3 | F13: Quintile 4 | G13: Quintile 5 | H13: All Quintiles
B14: Q4 2010 | C14: =C5*$H$10/$H$9 -> -16149.61 | D14: =D5*$H$10/$H$9 -> 67265.77 | E14: =E5*$H$10/$H$9 -> 295805.14 | F14: =F5*$H$10/$H$9 -> 715514.31 | G14: =G5*$H$10/$H$9 -> 2358135.7 | H14: =H5*$H$10/$H$9 -> 684114.54
B15: Q4 2023 | C15: =C6 -> -1141 | D15: =D6 -> 135497 | E15: =E6 -> 454074 | F15: =F6 -> 996641 | G15: =G6 -> 3311107 | H15: =H6 -> 979236
B16: $ Change | C16: =C15-C14 -> 15008.61 | D16: =D15-D14 -> 68231.23 | E16: =E15-E14 -> 158268.86 | F16: =F15-F14 -> 281126.69 | G16: =G15-G14 -> 952971.27 | H16: =H15-H14 -> 295121.46
B17: % Change | C17: =C16/C14 -> -0.92934814 | D17: =D16/D14 -> 1.0143529 | E17: =E16/E14 -> 0.53504432 | F17: =F16/F14 -> 0.39290156 | G17: =G16/G14 -> 0.40412062 | H17: =H16/H14 -> 0.43139189

Sheet Net Worth Over Time by Quintile
A1: Distributions of household economic accounts, wealth, by characteristic, Canada, quarterly
A2: Frequency: Quarterly
A3: Table: 36-10-0660-01
A4: Release date: 2024-07-17
A5: Geography: Canada
A6: https://www150.statcan.gc.ca/t1/tbl1/en/cv!recreate.action?pid=3610066001&selectedNodeIds=2D3,3D53,3D54,3D55,3D56,3D57&checkedLevels=0D1,2D1,3D1,3D2,3D3&refPeriods=20100101,20241001&dimensionLayouts=layout2,layout2,layout2,layout3,layout2&vectorDisplay=false
A9: Geography | B9: Canada
A10: Statistics | B10: Value per household
A11: Characteristics | B11: All households | BG11: Lowest wealth quintile 1 2 | DL11: Second wealth quintile 1 2 | FQ11: Third wealth quintile 1 2 | HV11: Fourth wealth quintile 1 2 | KA11: Highest wealth quintile 1 2
A12: Wealth | B12: Q1 2010 | C12: Q2 2010 | D12: Q3 2010 | E12: Q4 2010 | F12: Q1 2011 | G12: Q2 2011 | H12: Q3 2011 | I12: Q4 2011 | J12: Q1 2012 | K12: Q2 2012 | L12: Q3 2012 | M12: Q4 2012 | N12: Q1 2013 | O12: Q2 2013 | P12: Q3 2013 | Q12: Q4 2013 | R12: Q1 2014 | S12: Q2 2014 | T12: Q3 2014 | U12: Q4 2014 | V12: Q1 2015 | W12: Q2 2015 | X12: Q3 2015 | Y12: Q4 2015 | Z12: Q1 2016 | AA12: Q2 2016 | AB12: Q3 2016 | AC12: Q4 2016 | AD12: Q1 2017 | AE12: Q2 2017 | AF12: Q3 2017 | AG12: Q4 2017 | AH12: Q1 2018 | AI12: Q2 2018 | AJ12: Q3 2018 | AK12: Q4 2018 | AL12: Q1 2019 | AM12: Q2 2019 | AN12: Q3 2019 | AO12: Q4 2019 | AP12: Q1 2020 | AQ12: Q2 2020 | AR12: Q3 2020 | AS12: Q4 2020 | AT12: Q1 2021 | AU12: Q2 2021 | AV12: Q3 2021 | AW12: Q4 2021 | AX12: Q1 2022 | AY12: Q2 2022 | AZ12: Q3 2022 | BA12: Q4 2022 | BB12: Q1 2023 | BC12: Q2 2023 | BD12: Q3 2023 | BE12: Q4 2023 | BF12: Q1 2024 | BG12: Q1 2010 | BH12: Q2 2010 | BI12: Q3 2010 | BJ12: Q4 2010 | BK12: Q1 2011 | BL12: Q2 2011 | BM12: Q3 2011 | BN12: Q4 2011 | BO12: Q1 2012 | BP12: Q2 2012 | BQ12: Q3 2012 | BR12: Q4 2012 | BS12: Q1 2013 | BT12: Q2 2013 | BU12: Q3 2013 | BV12: Q4 2013 | BW12: Q1 2014 | BX12: Q2 2014 | BY12: Q3 2014 | BZ12: Q4 2014 | CA12: Q1 2015 | CB12: Q2 2015 | CC12: Q3 2015 | CD12: Q4 2015 | CE12: Q1 2016 | CF12: Q2 2016 | CG12: Q3 2016 | CH12: Q4 2016 | CI12: Q1 2017 | CJ12: Q2 2017 | CK12: Q3 2017 | CL12: Q4 2017 | CM12: Q1 2018 | CN12: Q2 2018 | CO12: Q3 2018 | CP12: Q4 2018 | CQ12: Q1 2019 | CR12: Q2 2019 | CS12: Q3 2019 | CT12: Q4 2019 | CU12: Q1 2020 | CV12: Q2 2020 | CW12: Q3 2020 | CX12: Q4 2020 | CY12: Q1 2021 | CZ12: Q2 2021 | DA12: Q3 2021 | DB12: Q4 2021 | DC12: Q1 2022 | DD12: Q2 2022 | DE12: Q3 2022 | DF12: Q4 2022 | DG12: Q1 2023 | DH12: Q2 2023 | DI12: Q3 2023 | DJ12: Q4 2023 | DK12: Q1 2024 | DL12: Q1 2010 | DM12: Q2 2010 | DN12: Q3 2010 | DO12: Q4 2010 | DP12: Q1 2011 | DQ12: Q2 2011 | DR12: Q3 2011 | DS12: Q4 2011 | DT12: Q1 2012 | DU12: Q2 2012 | DV12: Q3 2012 | DW12: Q4 2012 | DX12: Q1 2013 | DY12: Q2 2013 | DZ12: Q3 2013 | EA12: Q4 2013 | EB12: Q1 2014 | EC12: Q2 2014 | ED12: Q3 2014 | EE12: Q4 2014 | EF12: Q1 2015 | EG12: Q2 2015 | EH12: Q3 2015 | EI12: Q4 2015 | EJ12: Q1 2016 | EK12: Q2 2016 | EL12: Q3 2016 | EM12: Q4 2016 | EN12: Q1 2017 | EO12: Q2 2017 | EP12: Q3 2017 | EQ12: Q4 2017 | ER12: Q1 2018 | ES12: Q2 2018 | ET12: Q3 2018 | EU12: Q4 2018 | EV12: Q1 2019 | EW12: Q2 2019 | EX12: Q3 2019 | EY12: Q4 2019 | EZ12: Q1 2020 | FA12: Q2 2020 | FB12: Q3 2020 | FC12: Q4 2020 | FD12: Q1 2021 | FE12: Q2 2021 | FF12: Q3 2021 | FG12: Q4 2021 | FH12: Q1 2022 | FI12: Q2 2022 | FJ12: Q3 2022 | FK12: Q4 2022 | FL12: Q1 2023 | FM12: Q2 2023 | FN12: Q3 2023 | FO12: Q4 2023 | FP12: Q1 2024 | FQ12: Q1 2010 | FR12: Q2 2010 | FS12: Q3 2010 | FT12: Q4 2010 | FU12: Q1 2011 | FV12: Q2 2011 | FW12: Q3 2011 | FX12: Q4 2011 | FY12: Q1 2012 | FZ12: Q2 2012 | GA12: Q3 2012 | GB12: Q4 2012 | GC12: Q1 2013 | GD12: Q2 2013 | GE12: Q3 2013 | GF12: Q4 2013 | GG12: Q1 2014 | GH12: Q2 2014 | GI12: Q3 2014 | GJ12: Q4 2014 | GK12: Q1 2015 | GL12: Q2 2015 | GM12: Q3 2015 | GN12: Q4 2015 | GO12: Q1 2016 | GP12: Q2 2016 | GQ12: Q3 2016 | GR12: Q4 2016 | GS12: Q1 2017 | GT12: Q2 2017 | GU12: Q3 2017 | GV12: Q4 2017 | GW12: Q1 2018 | GX12: Q2 2018 | GY12: Q3 2018 | GZ12: Q4 2018 | HA12: Q1 2019 | HB12: Q2 2019 | HC12: Q3 2019 | HD12: Q4 2019 | HE12: Q1 2020 | HF12: Q2 2020 | HG12: Q3 2020 | HH12: Q4 2020 | HI12: Q1 2021 | HJ12: Q2 2021 | HK12: Q3 2021 | HL12: Q4 2021 | HM12: Q1 2022 | HN12: Q2 2022 | HO12: Q3 2022 | HP12: Q4 2022 | HQ12: Q1 2023 | HR12: Q2 2023 | HS12: Q3 2023 | HT12: Q4 2023 | HU12: Q1 2024 | HV12: Q1 2010 | HW12: Q2 2010 | HX12: Q3 2010 | HY12: Q4 2010 | HZ12: Q1 2011 | IA12: Q2 2011 | IB12: Q3 2011 | IC12: Q4 2011 | ID12: Q1 2012 | IE12: Q2 2012 | IF12: Q3 2012 | IG12: Q4 2012 | IH12: Q1 2013 | II12: Q2 2013 | IJ12: Q3 2013 | IK12: Q4 2013 | IL12: Q1 2014 | IM12: Q2 2014 | IN12: Q3 2014 | IO12: Q4 2014 | IP12: Q1 2015 | IQ12: Q2 2015 | IR12: Q3 2015 | IS12: Q4 2015 | IT12: Q1 2016 | IU12: Q2 2016 | IV12: Q3 2016 | IW12: Q4 2016 | IX12: Q1 2017 | IY12: Q2 2017 | IZ12: Q3 2017 | JA12: Q4 2017 | JB12: Q1 2018 | JC12: Q2 2018 | JD12: Q3 2018 | JE12: Q4 2018 | JF12: Q1 2019 | JG12: Q2 2019 | JH12: Q3 2019 | JI12: Q4 2019 | JJ12: Q1 2020 | JK12: Q2 2020 | JL12: Q3 2020 | JM12: Q4 2020 | JN12: Q1 2021 | JO12: Q2 2021 | JP12: Q3 2021 | JQ12: Q4 2021 | JR12: Q1 2022 | JS12: Q2 2022 | JT12: Q3 2022 | JU12: Q4 2022 | JV12: Q1 2023 | JW12: Q2 2023 | JX12: Q3 2023 | JY12: Q4 2023 | JZ12: Q1 2024 | KA12: Q1 2010 | KB12: Q2 2010 | KC12: Q3 2010 | KD12: Q4 2010 | KE12: Q1 2011 | KF12: Q2 2011 | KG12: Q3 2011 | KH12: Q4 2011 | KI12: Q1 2012 | KJ12: Q2 2012 | KK12: Q3 2012 | KL12: Q4 2012 | KM12: Q1 2013 | KN12: Q2 2013 | KO12: Q3 2013 | KP12: Q4 2013 | KQ12: Q1 2014 | KR12: Q2 2014 | KS12: Q3 2014 | KT12: Q4 2014 | KU12: Q1 2015 | KV12: Q2 2015 | KW12: Q3 2015 | KX12: Q4 2015 | KY12: Q1 2016 | KZ12: Q2 2016 | LA12: Q3 2016 | LB12: Q4 2016 | LC12: Q1 2017 | LD12: Q2 2017 | LE12: Q3 2017 | LF12: Q4 2017 | LG12: Q1 2018 | LH12: Q2 2018 | LI12: Q3 2018 | LJ12: Q4 2018 | LK12: Q1 2019 | LL12: Q2 2019 | LM12: Q3 2019 | LN12: Q4 2019 | LO12: Q1 2020 | LP12: Q2 2020 | LQ12: Q3 2020 | LR12: Q4 2020 | LS12: Q1 2021 | LT12: Q2 2021 | LU12: Q3 2021 | LV12: Q4 2021 | LW12: Q1 2022 | LX12: Q2 2022 | LY12: Q3 2022 | LZ12: Q4 2022 | MA12: Q1 2023 | MB12: Q2 2023 | MC12: Q3 2023 | MD12: Q4 2023 | ME12: Q1 2024
B13: Dollars
A14: Total assets | B14: .. | C14: .. | D14: .. | E14: 622328 | F14: .. | G14: .. | H14: .. | I14: 641989 | J14: .. | K14: .. | L14: .. | M14: 681101 | N14: .. | O14: .. | P14: .. | Q14: 718604 | R14: .. | S14: .. | T14: .. | U14: 764153 | V14: .. | W14: .. | X14: .. | Y14: 803842 | Z14: .. | AA14: .. | AB14: .. | AC14: 857986 | AD14: .. | AE14: .. | AF14: .. | AG14: 893533 | AH14: .. | AI14: .. | AJ14: .. | AK14: 887910 | AL14: .. | AM14: .. | AN14: .. | AO14: 942989 | AP14: 914050 | AQ14: 962238 | AR14: 1006339 | AS14: 1044575 | AT14: 1110209 | AU14: 1156751 | AV14: 1195905 | AW14: 1211594 | AX14: 1214538 | AY14: 1156192 | AZ14: 1130975 | BA14: 1134821 | BB14: 1159192 | BC14: 1171626 | BD14: 1147002 | BE14: 1156039 | BF14: 1186363 | BG14: .. | BH14: .. | BI14: .. | BJ14: 57373 | BK14: .. | BL14: .. | BM14: .. | BN14: 58384 | BO14: .. | BP14: .. | BQ14: .. | BR14: 56974 | BS14: .. | BT14: .. | BU14: .. | BV14: 55127 | BW14: .. | BX14: .. | BY14: .. | BZ14: 54832 | CA14: .. | CB14: .. | CC14: .. | CD14: 56577 | CE14: .. | CF14: .. | CG14: .. | CH14: 56535 | CI14: .. | CJ14: .. | CK14: .. | CL14: 57559 | CM14: .. | CN14: .. | CO14: .. | CP14: 66248 | CQ14: .. | CR14: .. | CS14: .. | CT14: 68561 | CU14: 65897 | CV14: 65305 | CW14: 65191 | CX14: 59781 | CY14: 49431 | CZ14: 49960 | DA14: 45923 | DB14: 41097 | DC14: 40446 | DD14: 47350 | DE14: 56530 | DF14: 58444 | DG14: 55136 | DH14: 55413 | DI14: 57804 | DJ14: 60593 | DK14: 58162 | DL14: .. | DM14: .. | DN14: .. | DO14: 143755 | DP14: .. | DQ14: .. | DR14: .. | DS14: 149382 | DT14: .. | DU14: .. | DV14: .. | DW14: 160793 | DX14: .. | DY14: .. | DZ14: .. | EA14: 171429 | EB14: .. | EC14: .. | ED14: .. | EE14: 178845 | EF14: .. | EG14: .. | EH14: .. | EI14: 190393 | EJ14: .. | EK14: .. | EL14: .. | EM14: 204129 | EN14: .. | EO14: .. | EP14: .. | EQ14: 212756 | ER14: .. | ES14: .. | ET14: .. | EU14: 212194 | EV14: .. | EW14: .. | EX14: .. | EY14: 225740 | EZ14: 222392 | FA14: 229405 | FB14: 239796 | FC14: 247213 | FD14: 264593 | FE14: 274008 | FF14: 284910 | FG14: 285691 | FH14: 287726 | FI14: 279390 | FJ14: 270350 | FK14: 271022 | FL14: 275853 | FM14: 277835 | FN14: 273079 | FO14: 276100 | FP14: 279832 | FQ14: .. | FR14: .. | FS14: .. | FT14: 356779 | FU14: .. | FV14: .. | FW14: .. | FX14: 375404 | FY14: .. | FZ14: .. | GA14: .. | GB14: 398516 | GC14: .. | GD14: .. | GE14: .. | GF14: 419331 | GG14: .. | GH14: .. | GI14: .. | GJ14: 444767 | GK14: .. | GL14: .. | GM14: .. | GN14: 466940 | GO14: .. | GP14: .. | GQ14: .. | GR14: 497114 | GS14: .. | GT14: .. | GU14: .. | GV14: 515555 | GW14: .. | GX14: .. | GY14: .. | GZ14: 506548 | HA14: .. | HB14: .. | HC14: .. | HD14: 529477 | HE14: 515887 | HF14: 543187 | HG14: 569001 | HH14: 587560 | HI14: 629812 | HJ14: 658334 | HK14: 689651 | HL14: 705075 | HM14: 711932 | HN14: 674108 | HO14: 657795 | HP14: 653783 | HQ14: 668490 | HR14: 676793 | HS14: 662456 | HT14: 656384 | HU14: 675017 | HV14: .. | HW14: .. | HX14: .. | HY14: 657337 | HZ14: .. | IA14: .. | IB14: .. | IC14: 682427 | ID14: .. | IE14: .. | IF14: .. | IG14: 725971 | IH14: .. | II14: .. | IJ14: .. | IK14: 766960 | IL14: .. | IM14: .. | IN14: .. | IO14: 814295 | IP14: .. | IQ14: .. | IR14: .. | IS14: 856559 | IT14: .. | IU14: .. | IV14: .. | IW14: 912924 | IX14: .. | IY14: .. | IZ14: .. | JA14: 948964 | JB14: .. | JC14: .. | JD14: .. | JE14: 933016 | JF14: .. | JG14: .. | JH14: .. | JI14: 990795 | JJ14: 966947 | JK14: 1014096 | JL14: 1059961 | JM14: 1110189 | JN14: 1186914 | JO14: 1236495 | JP14: 1282096 | JQ14: 1299421 | JR14: 1301117 | JS14: 1243397 | JT14: 1207937 | JU14: 1205986 | JV14: 1232535 | JW14: 1244937 | JX14: 1218190 | JY14: 1224305 | JZ14: 1253928 | KA14: .. | KB14: .. | KC14: .. | KD14: 1896395 | KE14: .. | KF14: .. | KG14: .. | KH14: 1944349 | KI14: .. | KJ14: .. | KK14: .. | KL14: 2063251 | KM14: .. | KN14: .. | KO14: .. | KP14: 2180175 | KQ14: .. | KR14: .. | KS14: .. | KT14: 2328025 | KU14: .. | KV14: .. | KW14: .. | KX14: 2448743 | KY14: .. | KZ14: .. | LA14: .. | LB14: 2619228 | LC14: .. | LD14: .. | LE14: .. | LF14: 2732831 | LG14: .. | LH14: .. | LI14: .. | LJ14: 2721546 | LK14: .. | LL14: .. | LM14: .. | LN14: 2900372 | LO14: 2799128 | LP14: 2959196 | LQ14: 3097745 | LR14: 3218134 | LS14: 3420294 | LT14: 3564956 | LU14: 3676947 | LV14: 3726684 | LW14: 3731469 | LX14: 3536713 | LY14: 3462261 | LZ14: 3484870 | MA14: 3563946 | MB14: 3603153 | MC14: 3523480 | MD14: 3562812 | ME14: 3664878
A15: Financial assets | B15: .. | C15: .. | D15: .. | E15: 333473 | F15: .. | G15: .. | H15: .. | I15: 336850 | J15: .. | K15: .. | L15: .. | M15: 357632 | N15: .. | O15: .. | P15: .. | Q15: 378521 | R15: .. | S15: .. | T15: .. | U15: 409472 | V15: .. | W15: .. | X15: .. | Y15: 426725 | Z15: .. | AA15: .. | AB15: .. | AC15: 453871 | AD15: .. | AE15: .. | AF15: .. | AG15: 474448 | AH15: .. | AI15: .. | AJ15: .. | AK15: 471682 | AL15: .. | AM15: .. | AN15: .. | AO15: 509287 | AP15: 476010 | AQ15: 507061 | AR15: 529110 | AS15: 544932 | AT15: 565225 | AU15: 588120 | AV15: 592085 | AW15: 590985 | AX15: 574253 | AY15: 544621 | AZ15: 542952 | BA15: 556352 | BB15: 567752 | BC15: 571559 | BD15: 558239 | BE15: 578383 | BF15: 597772 | BG15: .. | BH15: .. | BI15: .. | BJ15: 8044 | BK15: .. | BL15: .. | BM15: .. | BN15: 7940 | BO15: .. | BP15: .. | BQ15: .. | BR15: 8140 | BS15: .. | BT15: .. | BU15: .. | BV15: 8554 | BW15: .. | BX15: .. | BY15: .. | BZ15: 9108 | CA15: .. | CB15: .. | CC15: .. | CD15: 10005 | CE15: .. | CF15: .. | CG15: .. | CH15: 10729 | CI15: .. | CJ15: .. | CK15: .. | CL15: 11207 | CM15: .. | CN15: .. | CO15: .. | CP15: 11595 | CQ15: .. | CR15: .. | CS15: .. | CT15: 12033 | CU15: 11071 | CV15: 10851 | CW15: 11310 | CX15: 11217 | CY15: 11097 | CZ15: 11411 | DA15: 10902 | DB15: 10870 | DC15: 10844 | DD15: 10666 | DE15: 11266 | DF15: 11434 | DG15: 11466 | DH15: 11676 | DI15: 11563 | DJ15: 11805 | DK15: 11974 | DL15: .. | DM15: .. | DN15: .. | DO15: 33604 | DP15: .. | DQ15: .. | DR15: .. | DS15: 34427 | DT15: .. | DU15: .. | DV15: .. | DW15: 37781 | DX15: .. | DY15: .. | DZ15: .. | EA15: 42182 | EB15: .. | EC15: .. | ED15: .. | EE15: 47658 | EF15: .. | EG15: .. | EH15: .. | EI15: 52641 | EJ15: .. | EK15: .. | EL15: .. | EM15: 57969 | EN15: .. | EO15: .. | EP15: .. | EQ15: 61395 | ER15: .. | ES15: .. | ET15: .. | EU15: 62074 | EV15: .. | EW15: .. | EX15: .. | EY15: 68341 | EZ15: 65206 | FA15: 69532 | FB15: 72758 | FC15: 75502 | FD15: 79710 | FE15: 83596 | FF15: 87215 | FG15: 88705 | FH15: 87549 | FI15: 82224 | FJ15: 80055 | FK15: 80721 | FL15: 82931 | FM15: 83336 | FN15: 81333 | FO15: 82344 | FP15: 85275 | FQ15: .. | FR15: .. | FS15: .. | FT15: 113248 | FU15: .. | FV15: .. | FW15: .. | FX15: 117214 | FY15: .. | FZ15: .. | GA15: .. | GB15: 125834 | GC15: .. | GD15: .. | GE15: .. | GF15: 136523 | GG15: .. | GH15: .. | GI15: .. | GJ15: 150937 | GK15: .. | GL15: .. | GM15: .. | GN15: 164004 | GO15: .. | GP15: .. | GQ15: .. | GR15: 177986 | GS15: .. | GT15: .. | GU15: .. | GV15: 187480 | GW15: .. | GX15: .. | GY15: .. | GZ15: 184269 | HA15: .. | HB15: .. | HC15: .. | HD15: 199834 | HE15: 188969 | HF15: 198424 | HG15: 206509 | HH15: 212961 | HI15: 223758 | HJ15: 231704 | HK15: 235252 | HL15: 236487 | HM15: 232514 | HN15: 221395 | HO15: 219229 | HP15: 221232 | HQ15: 225068 | HR15: 226610 | HS15: 222206 | HT15: 227456 | HU15: 233758 | HV15: .. | HW15: .. | HX15: .. | HY15: 306266 | HZ15: .. | IA15: .. | IB15: .. | IC15: 312937 | ID15: .. | IE15: .. | IF15: .. | IG15: 333797 | IH15: .. | II15: .. | IJ15: .. | IK15: 354819 | IL15: .. | IM15: .. | IN15: .. | IO15: 386305 | IP15: .. | IQ15: .. | IR15: .. | IS15: 404421 | IT15: .. | IU15: .. | IV15: .. | IW15: 432377 | IX15: .. | IY15: .. | IZ15: .. | JA15: 452087 | JB15: .. | JC15: .. | JD15: .. | JE15: 435715 | JF15: .. | JG15: .. | JH15: .. | JI15: 460743 | JJ15: 428186 | JK15: 455456 | JL15: 472439 | JM15: 485744 | JN15: 502522 | JO15: 521710 | JP15: 524116 | JQ15: 524105 | JR15: 510683 | JS15: 479341 | JT15: 476162 | JU15: 486292 | JV15: 497142 | JW15: 500615 | JX15: 487259 | JY15: 503197 | JZ15: 517997 | KA15: .. | KB15: .. | KC15: .. | KD15: 1206204 | KE15: .. | KF15: .. | KG15: .. | KH15: 1211731 | KI15: .. | KJ15: .. | KK15: .. | KL15: 1282607 | KM15: .. | KN15: .. | KO15: .. | KP15: 1350527 | KQ15: .. | KR15: .. | KS15: .. | KT15: 1453350 | KU15: .. | KV15: .. | KW15: .. | KX15: 1502554 | KY15: .. | KZ15: .. | LA15: .. | LB15: 1590294 | LC15: .. | LD15: .. | LE15: .. | LF15: 1660072 | LG15: .. | LH15: .. | LI15: .. | LJ15: 1664755 | LK15: .. | LL15: .. | LM15: .. | LN15: 1805484 | LO15: 1686616 | LP15: 1801042 | LQ15: 1882535 | LR15: 1939238 | LS15: 2009038 | LT15: 2092179 | LU15: 2102941 | LV15: 2094758 | LW15: 2029675 | LX15: 1929481 | LY15: 1928046 | LZ15: 1982080 | MA15: 2022152 | MB15: 2035559 | MC15: 1988833 | MD15: 2067110 | ME15: 2139853
A16: Life insurance and pensions 3 | B16: .. | C16: .. | D16: .. | E16: 117973 | F16: .. | G16: .. | H16: .. | I16: 126773 | J16: .. | K16: .. | L16: .. | M16: 135424 | N16: .. | O16: .. | P16: .. | Q16: 139755 | R16: .. | S16: .. | T16: .. | U16: 151269 | V16: .. | W16: .. | X16: .. | Y16: 155575 | Z16: .. | AA16: .. | AB16: .. | AC16: 162531 | AD16: .. | AE16: .. | AF16: .. | AG16: 167154 | AH16: .. | AI16: .. | AJ16: .. | AK16: 164504 | AL16: .. | AM16: .. | AN16: .. | AO16: 178136 | AP16: 170097 | AQ16: 178252 | AR16: 183091 | AS16: 186538 | AT16: 187920 | AU16: 193075 | AV16: 191060 | AW16: 189471 | AX16: 180304 | AY16: 167824 | AZ16: 167578 | BA16: 170031 | BB16: 172701 | BC16: 172643 | BD16: 167415 | BE16: 173931 | BF16: 177962 | BG16: .. | BH16: .. | BI16: .. | BJ16: 2655 | BK16: .. | BL16: .. | BM16: .. | BN16: 2665 | BO16: .. | BP16: .. | BQ16: .. | BR16: 2678 | BS16: .. | BT16: .. | BU16: .. | BV16: 2651 | BW16: .. | BX16: .. | BY16: .. | BZ16: 2679 | CA16: .. | CB16: .. | CC16: .. | CD16: 2979 | CE16: .. | CF16: .. | CG16: .. | CH16: 3025 | CI16: .. | CJ16: .. | CK16: .. | CL16: 3063 | CM16: .. | CN16: .. | CO16: .. | CP16: 3445 | CQ16: .. | CR16: .. | CS16: .. | CT16: 3672 | CU16: 3471 | CV16: 3233 | CW16: 3395 | CX16: 3252 | CY16: 2861 | CZ16: 2879 | DA16: 2752 | DB16: 2626 | DC16: 2771 | DD16: 2891 | DE16: 3051 | DF16: 3077 | DG16: 2922 | DH16: 3080 | DI16: 3180 | DJ16: 3148 | DK16: 3030 | DL16: .. | DM16: .. | DN16: .. | DO16: 12515 | DP16: .. | DQ16: .. | DR16: .. | DS16: 13065 | DT16: .. | DU16: .. | DV16: .. | DW16: 14785 | DX16: .. | DY16: .. | DZ16: .. | EA16: 16987 | EB16: .. | EC16: .. | ED16: .. | EE16: 20221 | EF16: .. | EG16: .. | EH16: .. | EI16: 22847 | EJ16: .. | EK16: .. | EL16: .. | EM16: 26126 | EN16: .. | EO16: .. | EP16: .. | EQ16: 27799 | ER16: .. | ES16: .. | ET16: .. | EU16: 25446 | EV16: .. | EW16: .. | EX16: .. | EY16: 25942 | EZ16: 24712 | FA16: 26082 | FB16: 27481 | FC16: 28922 | FD16: 30416 | FE16: 31728 | FF16: 33569 | FG16: 34161 | FH16: 33452 | FI16: 30975 | FJ16: 30491 | FK16: 30332 | FL16: 31658 | FM16: 31683 | FN16: 30608 | FO16: 30469 | FP16: 31963 | FQ16: .. | FR16: .. | FS16: .. | FT16: 47708 | FU16: .. | FV16: .. | FW16: .. | FX16: 51067 | FY16: .. | FZ16: .. | GA16: .. | GB16: 55372 | GC16: .. | GD16: .. | GE16: .. | GF16: 60720 | GG16: .. | GH16: .. | GI16: .. | GJ16: 68570 | GK16: .. | GL16: .. | GM16: .. | GN16: 76566 | GO16: .. | GP16: .. | GQ16: .. | GR16: 83133 | GS16: .. | GT16: .. | GU16: .. | GV16: 87214 | GW16: .. | GX16: .. | GY16: .. | GZ16: 84335 | HA16: .. | HB16: .. | HC16: .. | HD16: 91325 | HE16: 87809 | HF16: 91706 | HG16: 94276 | HH16: 95642 | HI16: 99136 | HJ16: 102682 | HK16: 104047 | HL16: 104724 | HM16: 103386 | HN16: 97378 | HO16: 95660 | HP16: 96761 | HQ16: 98229 | HR16: 98742 | HS16: 96228 | HT16: 99003 | HU16: 100777 | HV16: .. | HW16: .. | HX16: .. | HY16: 148070 | HZ16: .. | IA16: .. | IB16: .. | IC16: 158053 | ID16: .. | IE16: .. | IF16: .. | IG16: 170107 | IH16: .. | II16: .. | IJ16: .. | IK16: 177861 | IL16: .. | IM16: .. | IN16: .. | IO16: 194293 | IP16: .. | IQ16: .. | IR16: .. | IS16: 203744 | IT16: .. | IU16: .. | IV16: .. | IW16: 217488 | IX16: .. | IY16: .. | IZ16: .. | JA16: 225563 | JB16: .. | JC16: .. | JD16: .. | JE16: 220511 | JF16: .. | JG16: .. | JH16: .. | JI16: 237268 | JJ16: 224306 | JK16: 235790 | JL16: 242979 | JM16: 248865 | JN16: 253599 | JO16: 261193 | JP16: 258794 | JQ16: 258200 | JR16: 247494 | JS16: 230830 | JT16: 230869 | JU16: 232411 | JV16: 237756 | JW16: 238416 | JX16: 230937 | JY16: 238243 | JZ16: 243281 | KA16: .. | KB16: .. | KC16: .. | KD16: 378917 | KE16: .. | KF16: .. | KG16: .. | KH16: 409012 | KI16: .. | KJ16: .. | KK16: .. | KL16: 434180 | KM16: .. | KN16: .. | KO16: .. | KP16: 440558 | KQ16: .. | KR16: .. | KS16: .. | KT16: 470583 | KU16: .. | KV16: .. | KW16: .. | KX16: 471741 | KY16: .. | KZ16: .. | LA16: .. | LB16: 482883 | LC16: .. | LD16: .. | LE16: .. | LF16: 492132 | LG16: .. | LH16: .. | LI16: .. | LJ16: 488780 | LK16: .. | LL16: .. | LM16: .. | LN16: 532472 | LO16: 510185 | LP16: 534451 | LQ16: 547324 | LR16: 556007 | LS16: 553590 | LT16: 566895 | LU16: 556139 | LV16: 547644 | LW16: 514418 | LX16: 477044 | LY16: 477817 | LZ16: 487577 | MA16: 492941 | MB16: 491294 | MC16: 476125 | MD16: 498793 | ME16: 510759
A17: Other financial assets 4 | B17: .. | C17: .. | D17: .. | E17: 215500 | F17: .. | G17: .. | H17: .. | I17: 210077 | J17: .. | K17: .. | L17: .. | M17: 222208 | N17: .. | O17: .. | P17: .. | Q17: 238766 | R17: .. | S17: .. | T17: .. | U17: 258202 | V17: .. | W17: .. | X17: .. | Y17: 271150 | Z17: .. | AA17: .. | AB17: .. | AC17: 291340 | AD17: .. | AE17: .. | AF17: .. | AG17: 307294 | AH17: .. | AI17: .. | AJ17: .. | AK17: 307178 | AL17: .. | AM17: .. | AN17: .. | AO17: 331151 | AP17: 305913 | AQ17: 328809 | AR17: 346019 | AS17: 358395 | AT17: 377305 | AU17: 395045 | AV17: 401025 | AW17: 401514 | AX17: 393949 | AY17: 376798 | AZ17: 375374 | BA17: 386320 | BB17: 395051 | BC17: 398916 | BD17: 390823 | BE17: 404452 | BF17: 419810 | BG17: .. | BH17: .. | BI17: .. | BJ17: 5389 | BK17: .. | BL17: .. | BM17: .. | BN17: 5275 | BO17: .. | BP17: .. | BQ17: .. | BR17: 5463 | BS17: .. | BT17: .. | BU17: .. | BV17: 5903 | BW17: .. | BX17: .. | BY17: .. | BZ17: 6430 | CA17: .. | CB17: .. | CC17: .. | CD17: 7026 | CE17: .. | CF17: .. | CG17: .. | CH17: 7704 | CI17: .. | CJ17: .. | CK17: .. | CL17: 8145 | CM17: .. | CN17: .. | CO17: .. | CP17: 8150 | CQ17: .. | CR17: .. | CS17: .. | CT17: 8361 | CU17: 7600 | CV17: 7618 | CW17: 7915 | CX17: 7964 | CY17: 8236 | CZ17: 8532 | DA17: 8150 | DB17: 8244 | DC17: 8072 | DD17: 7775 | DE17: 8215 | DF17: 8357 | DG17: 8544 | DH17: 8596 | DI17: 8383 | DJ17: 8657 | DK17: 8944 | DL17: .. | DM17: .. | DN17: .. | DO17: 21089 | DP17: .. | DQ17: .. | DR17: .. | DS17: 21362 | DT17: .. | DU17: .. | DV17: .. | DW17: 22996 | DX17: .. | DY17: .. | DZ17: .. | EA17: 25196 | EB17: .. | EC17: .. | ED17: .. | EE17: 27436 | EF17: .. | EG17: .. | EH17: .. | EI17: 29795 | EJ17: .. | EK17: .. | EL17: .. | EM17: 31843 | EN17: .. | EO17: .. | EP17: .. | EQ17: 33595 | ER17: .. | ES17: .. | ET17: .. | EU17: 36628 | EV17: .. | EW17: .. | EX17: .. | EY17: 42398 | EZ17: 40493 | FA17: 43450 | FB17: 45277 | FC17: 46580 | FD17: 49294 | FE17: 51868 | FF17: 53646 | FG17: 54544 | FH17: 54098 | FI17: 51249 | FJ17: 49564 | FK17: 50390 | FL17: 51274 | FM17: 51653 | FN17: 50725 | FO17: 51876 | FP17: 53313 | FQ17: .. | FR17: .. | FS17: .. | FT17: 65540 | FU17: .. | FV17: .. | FW17: .. | FX17: 66147 | FY17: .. | FZ17: .. | GA17: .. | GB17: 70461 | GC17: .. | GD17: .. | GE17: .. | GF17: 75803 | GG17: .. | GH17: .. | GI17: .. | GJ17: 82366 | GK17: .. | GL17: .. | GM17: .. | GN17: 87437 | GO17: .. | GP17: .. | GQ17: .. | GR17: 94853 | GS17: .. | GT17: .. | GU17: .. | GV17: 100265 | GW17: .. | GX17: .. | GY17: .. | GZ17: 99934 | HA17: .. | HB17: .. | HC17: .. | HD17: 108509 | HE17: 101161 | HF17: 106717 | HG17: 112232 | HH17: 117319 | HI17: 124622 | HJ17: 129022 | HK17: 131205 | HL17: 131763 | HM17: 129129 | HN17: 124017 | HO17: 123569 | HP17: 124471 | HQ17: 126839 | HR17: 127868 | HS17: 125978 | HT17: 128453 | HU17: 132981 | HV17: .. | HW17: .. | HX17: .. | HY17: 158197 | HZ17: .. | IA17: .. | IB17: .. | IC17: 154883 | ID17: .. | IE17: .. | IF17: .. | IG17: 163690 | IH17: .. | II17: .. | IJ17: .. | IK17: 176958 | IL17: .. | IM17: .. | IN17: .. | IO17: 192012 | IP17: .. | IQ17: .. | IR17: .. | IS17: 200677 | IT17: .. | IU17: .. | IV17: .. | IW17: 214889 | IX17: .. | IY17: .. | IZ17: .. | JA17: 226523 | JB17: .. | JC17: .. | JD17: .. | JE17: 215204 | JF17: .. | JG17: .. | JH17: .. | JI17: 223475 | JJ17: 203881 | JK17: 219666 | JL17: 229460 | JM17: 236878 | JN17: 248923 | JO17: 260518 | JP17: 265321 | JQ17: 265905 | JR17: 263190 | JS17: 248511 | JT17: 245293 | JU17: 253881 | JV17: 259386 | JW17: 262199 | JX17: 256322 | JY17: 264955 | JZ17: 274716 | KA17: .. | KB17: .. | KC17: .. | KD17: 827287 | KE17: .. | KF17: .. | KG17: .. | KH17: 802719 | KI17: .. | KJ17: .. | KK17: .. | KL17: 848428 | KM17: .. | KN17: .. | KO17: .. | KP17: 909970 | KQ17: .. | KR17: .. | KS17: .. | KT17: 982767 | KU17: .. | KV17: .. | KW17: .. | KX17: 1030814 | KY17: .. | KZ17: .. | LA17: .. | LB17: 1107411 | LC17: .. | LD17: .. | LE17: .. | LF17: 1167940 | LG17: .. | LH17: .. | LI17: .. | LJ17: 1175974 | LK17: .. | LL17: .. | LM17: .. | LN17: 1273012 | LO17: 1176430 | LP17: 1266592 | LQ17: 1335211 | LR17: 1383231 | LS17: 1455448 | LT17: 1525285 | LU17: 1546802 | LV17: 1547114 | LW17: 1515257 | LX17: 1452436 | LY17: 1450229 | LZ17: 1494503 | MA17: 1529211 | MB17: 1544265 | MC17: 1512709 | MD17: 1568318 | ME17: 1629093
A18: Non-financial assets | B18: .. | C18: .. | D18: .. | E18: 288854 | F18: .. | G18: .. | H18: .. | I18: 305139 | J18: .. | K18: .. | L18: .. | M18: 323469 | N18: .. | O18: .. | P18: .. | Q18: 340083 | R18: .. | S18: .. | T18: .. | U18: 354681 | V18: .. | W18: .. | X18: .. | Y18: 377117 | Z18: .. | AA18: .. | AB18: .. | AC18: 404115 | AD18: .. | AE18: .. | AF18: .. | AG18: 419085 | AH18: .. | AI18: .. | AJ18: .. | AK18: 416228 | AL18: .. | AM18: .. | AN18: .. | AO18: 433702 | AP18: 438040 | AQ18: 455177 | AR18: 477229 | AS18: 499643 | AT18: 544984 | AU18: 568631 | AV18: 603820 | AW18: 620609 | AX18: 640285 | AY18: 611570 | AZ18: 588023 | BA18: 578469 | BB18: 591440 | BC18: 600067 | BD18: 588763 | BE18: 577656 | BF18: 588592 | BG18: .. | BH18: .. | BI18: .. | BJ18: 49329 | BK18: .. | BL18: .. | BM18: .. | BN18: 50443 | BO18: .. | BP18: .. | BQ18: .. | BR18: 48834 | BS18: .. | BT18: .. | BU18: .. | BV18: 46573 | BW18: .. | BX18: .. | BY18: .. | BZ18: 45723 | CA18: .. | CB18: .. | CC18: .. | CD18: 46572 | CE18: .. | CF18: .. | CG18: .. | CH18: 45806 | CI18: .. | CJ18: .. | CK18: .. | CL18: 46351 | CM18: .. | CN18: .. | CO18: .. | CP18: 54652 | CQ18: .. | CR18: .. | CS18: .. | CT18: 56528 | CU18: 54825 | CV18: 54454 | CW18: 53881 | CX18: 48564 | CY18: 38334 | CZ18: 38549 | DA18: 35021 | DB18: 30227 | DC18: 29602 | DD18: 36685 | DE18: 45264 | DF18: 47010 | DG18: 43670 | DH18: 43737 | DI18: 46241 | DJ18: 48788 | DK18: 46188 | DL18: .. | DM18: .. | DN18: .. | DO18: 110150 | DP18: .. | DQ18: .. | DR18: .. | DS18: 114955 | DT18: .. | DU18: .. | DV18: .. | DW18: 123012 | DX18: .. | DY18: .. | DZ18: .. | EA18: 129246 | EB18: .. | EC18: .. | ED18: .. | EE18: 131187 | EF18: .. | EG18: .. | EH18: .. | EI18: 137752 | EJ18: .. | EK18: .. | EL18: .. | EM18: 146161 | EN18: .. | EO18: .. | EP18: .. | EQ18: 151361 | ER18: .. | ES18: .. | ET18: .. | EU18: 150120 | EV18: .. | EW18: .. | EX18: .. | EY18: 157399 | EZ18: 157186 | FA18: 159874 | FB18: 167038 | FC18: 171711 | FD18: 184883 | FE18: 190412 | FF18: 197694 | FG18: 196986 | FH18: 200176 | FI18: 197166 | FJ18: 190296 | FK18: 190301 | FL18: 192922 | FM18: 194498 | FN18: 191746 | FO18: 193756 | FP18: 194557 | FQ18: .. | FR18: .. | FS18: .. | FT18: 243531 | FU18: .. | FV18: .. | FW18: .. | FX18: 258190 | FY18: .. | FZ18: .. | GA18: .. | GB18: 272682 | GC18: .. | GD18: .. | GE18: .. | GF18: 282808 | GG18: .. | GH18: .. | GI18: .. | GJ18: 293830 | GK18: .. | GL18: .. | GM18: .. | GN18: 302936 | GO18: .. | GP18: .. | GQ18: .. | GR18: 319128 | GS18: .. | GT18: .. | GU18: .. | GV18: 328075 | GW18: .. | GX18: .. | GY18: .. | GZ18: 322279 | HA18: .. | HB18: .. | HC18: .. | HD18: 329643 | HE18: 326917 | HF18: 344763 | HG18: 362493 | HH18: 374599 | HI18: 406054 | HJ18: 426630 | HK18: 454398 | HL18: 468589 | HM18: 479417 | HN18: 452713 | HO18: 438567 | HP18: 432551 | HQ18: 443422 | HR18: 450184 | HS18: 440250 | HT18: 428927 | HU18: 441258 | HV18: .. | HW18: .. | HX18: .. | HY18: 351070 | HZ18: .. | IA18: .. | IB18: .. | IC18: 369490 | ID18: .. | IE18: .. | IF18: .. | IG18: 392174 | IH18: .. | II18: .. | IJ18: .. | IK18: 412141 | IL18: .. | IM18: .. | IN18: .. | IO18: 427990 | IP18: .. | IQ18: .. | IR18: .. | IS18: 452138 | IT18: .. | IU18: .. | IV18: .. | IW18: 480546 | IX18: .. | IY18: .. | IZ18: .. | JA18: 496877 | JB18: .. | JC18: .. | JD18: .. | JE18: 497300 | JF18: .. | JG18: .. | JH18: .. | JI18: 530053 | JJ18: 538761 | JK18: 558639 | JL18: 587522 | JM18: 624445 | JN18: 684391 | JO18: 714784 | JP18: 757981 | JQ18: 775316 | JR18: 790433 | JS18: 764056 | JT18: 731775 | JU18: 719693 | JV18: 735393 | JW18: 744322 | JX18: 730931 | JY18: 721108 | JZ18: 735931 | KA18: .. | KB18: .. | KC18: .. | KD18: 690191 | KE18: .. | KF18: .. | KG18: .. | KH18: 732619 | KI18: .. | KJ18: .. | KK18: .. | KL18: 780644 | KM18: .. | KN18: .. | KO18: .. | KP18: 829647 | KQ18: .. | KR18: .. | KS18: .. | KT18: 874675 | KU18: .. | KV18: .. | KW18: .. | KX18: 946189 | KY18: .. | KZ18: .. | LA18: .. | LB18: 1028934 | LC18: .. | LD18: .. | LE18: .. | LF18: 1072759 | LG18: .. | LH18: .. | LI18: .. | LJ18: 1056791 | LK18: .. | LL18: .. | LM18: .. | LN18: 1094887 | LO18: 1112512 | LP18: 1158153 | LQ18: 1215210 | LR18: 1278895 | LS18: 1411256 | LT18: 1472777 | LU18: 1574005 | LV18: 1631926 | LW18: 1701794 | LX18: 1607232 | LY18: 1534215 | LZ18: 1502791 | MA18: 1541794 | MB18: 1567594 | MC18: 1534646 | MD18: 1495702 | ME18: 1525025
A19: Real estate | B19: .. | C19: .. | D19: .. | E19: 249348 | F19: .. | G19: .. | H19: .. | I19: 265356 | J19: .. | K19: .. | L19: .. | M19: 282961 | N19: .. | O19: .. | P19: .. | Q19: 298499 | R19: .. | S19: .. | T19: .. | U19: 311484 | V19: .. | W19: .. | X19: .. | Y19: 331993 | Z19: .. | AA19: .. | AB19: .. | AC19: 357082 | AD19: .. | AE19: .. | AF19: .. | AG19: 370992 | AH19: .. | AI19: .. | AJ19: .. | AK19: 367364 | AL19: .. | AM19: .. | AN19: .. | AO19: 383906 | AP19: 389447 | AQ19: 406460 | AR19: 426249 | AS19: 448651 | AT19: 493299 | AU19: 515047 | AV19: 548342 | AW19: 566129 | AX19: 585285 | AY19: 554822 | AZ19: 530835 | BA19: 521783 | BB19: 535719 | BC19: 543482 | BD19: 531709 | BE19: 520496 | BF19: 532186 | BG19: .. | BH19: .. | BI19: .. | BJ19: 36798 | BK19: .. | BL19: .. | BM19: .. | BN19: 37903 | BO19: .. | BP19: .. | BQ19: .. | BR19: 36295 | BS19: .. | BT19: .. | BU19: .. | BV19: 33927 | BW19: .. | BX19: .. | BY19: .. | BZ19: 32756 | CA19: .. | CB19: .. | CC19: .. | CD19: 33048 | CE19: .. | CF19: .. | CG19: .. | CH19: 32041 | CI19: .. | CJ19: .. | CK19: .. | CL19: 32422 | CM19: .. | CN19: .. | CO19: .. | CP19: 39114 | CQ19: .. | CR19: .. | CS19: .. | CT19: 40307 | CU19: 38956 | CV19: 38634 | CW19: 37781 | CX19: 33198 | CY19: 23393 | CZ19: 23173 | DA19: 19479 | DB19: 15265 | DC19: 14615 | DD19: 21009 | DE19: 29297 | DF19: 30933 | DG19: 28011 | DH19: 27934 | DI19: 30244 | DJ19: 32600 | DK19: 30214 | DL19: .. | DM19: .. | DN19: .. | DO19: 87900 | DP19: .. | DQ19: .. | DR19: .. | DS19: 92349 | DT19: .. | DU19: .. | DV19: .. | DW19: 99591 | DX19: .. | DY19: .. | DZ19: .. | EA19: 104704 | EB19: .. | EC19: .. | ED19: .. | EE19: 105439 | EF19: .. | EG19: .. | EH19: .. | EI19: 110543 | EJ19: .. | EK19: .. | EL19: .. | EM19: 117630 | EN19: .. | EO19: .. | EP19: .. | EQ19: 121973 | ER19: .. | ES19: .. | ET19: .. | EU19: 120370 | EV19: .. | EW19: .. | EX19: .. | EY19: 126803 | EZ19: 127272 | FA19: 129748 | FB19: 135463 | FC19: 138945 | FD19: 152267 | FE19: 156332 | FF19: 162619 | FG19: 162519 | FH19: 165452 | FI19: 161634 | FJ19: 153825 | FK19: 154259 | FL19: 157405 | FM19: 158498 | FN19: 155460 | FO19: 157324 | FP19: 158559 | FQ19: .. | FR19: .. | FS19: .. | FT19: 208044 | FU19: .. | FV19: .. | FW19: .. | FX19: 222411 | FY19: .. | FZ19: .. | GA19: .. | GB19: 236376 | GC19: .. | GD19: .. | GE19: .. | GF19: 245803 | GG19: .. | GH19: .. | GI19: .. | GJ19: 255604 | GK19: .. | GL19: .. | GM19: .. | GN19: 263313 | GO19: .. | GP19: .. | GQ19: .. | GR19: 277737 | GS19: .. | GT19: .. | GU19: .. | GV19: 285683 | GW19: .. | GX19: .. | GY19: .. | GZ19: 278320 | HA19: .. | HB19: .. | HC19: .. | HD19: 284590 | HE19: 283142 | HF19: 299911 | HG19: 315538 | HH19: 328547 | HI19: 358988 | HJ19: 378025 | HK19: 403531 | HL19: 417963 | HM19: 428263 | HN19: 400260 | HO19: 386946 | HP19: 380774 | HQ19: 392424 | HR19: 398290 | HS19: 388680 | HT19: 376861 | HU19: 389796 | HV19: .. | HW19: .. | HX19: .. | HY19: 305194 | HZ19: .. | IA19: .. | IB19: .. | IC19: 323425 | ID19: .. | IE19: .. | IF19: .. | IG19: 345078 | IH19: .. | II19: .. | IJ19: .. | IK19: 363119 | IL19: .. | IM19: .. | IN19: .. | IO19: 375985 | IP19: .. | IQ19: .. | IR19: .. | IS19: 396763 | IT19: .. | IU19: .. | IV19: .. | IW19: 422127 | IX19: .. | IY19: .. | IZ19: .. | JA19: 436887 | JB19: .. | JC19: .. | JD19: .. | JE19: 438580 | JF19: .. | JG19: .. | JH19: .. | JI19: 470776 | JJ19: 481160 | JK19: 501714 | JL19: 527625 | JM19: 563982 | JN19: 622561 | JO19: 650709 | JP19: 691587 | JQ19: 710377 | JR19: 724475 | JS19: 695856 | JT19: 662907 | JU19: 652367 | JV19: 669221 | JW19: 676992 | JX19: 662386 | JY19: 653417 | JZ19: 668867 | KA19: .. | KB19: .. | KC19: .. | KD19: 608802 | KE19: .. | KF19: .. | KG19: .. | KH19: 650694 | KI19: .. | KJ19: .. | KK19: .. | KL19: 697466 | KM19: .. | KN19: .. | KO19: .. | KP19: 744942 | KQ19: .. | KR19: .. | KS19: .. | KT19: 787635 | KU19: .. | KV19: .. | KW19: .. | KX19: 856299 | KY19: .. | KZ19: .. | LA19: .. | LB19: 935876 | LC19: .. | LD19: .. | LE19: .. | LF19: 977995 | LG19: .. | LH19: .. | LI19: .. | LJ19: 960437 | LK19: .. | LL19: .. | LM19: .. | LN19: 997054 | LO19: 1016704 | LP19: 1062293 | LQ19: 1114839 | LR19: 1178581 | LS19: 1309284 | LT19: 1366998 | LU19: 1464494 | LV19: 1524520 | LW19: 1593617 | LX19: 1495350 | LY19: 1421201 | LZ19: 1390585 | MA19: 1431533 | MB19: 1455698 | MC19: 1421775 | MD19: 1382276 | ME19: 1413495
A20: Other non-financial assets 5 | B20: .. | C20: .. | D20: .. | E20: 39507 | F20: .. | G20: .. | H20: .. | I20: 39783 | J20: .. | K20: .. | L20: .. | M20: 40508 | N20: .. | O20: .. | P20: .. | Q20: 41584 | R20: .. | S20: .. | T20: .. | U20: 43198 | V20: .. | W20: .. | X20: .. | Y20: 45124 | Z20: .. | AA20: .. | AB20: .. | AC20: 47033 | AD20: .. | AE20: .. | AF20: .. | AG20: 48093 | AH20: .. | AI20: .. | AJ20: .. | AK20: 48864 | AL20: .. | AM20: .. | AN20: .. | AO20: 49796 | AP20: 48594 | AQ20: 48717 | AR20: 50979 | AS20: 50992 | AT20: 51685 | AU20: 53583 | AV20: 55478 | AW20: 54480 | AX20: 55000 | AY20: 56748 | AZ20: 57188 | BA20: 56686 | BB20: 55722 | BC20: 56585 | BD20: 57054 | BE20: 57161 | BF20: 56406 | BG20: .. | BH20: .. | BI20: .. | BJ20: 12531 | BK20: .. | BL20: .. | BM20: .. | BN20: 12540 | BO20: .. | BP20: .. | BQ20: .. | BR20: 12539 | BS20: .. | BT20: .. | BU20: .. | BV20: 12646 | BW20: .. | BX20: .. | BY20: .. | BZ20: 12968 | CA20: .. | CB20: .. | CC20: .. | CD20: 13524 | CE20: .. | CF20: .. | CG20: .. | CH20: 13765 | CI20: .. | CJ20: .. | CK20: .. | CL20: 13930 | CM20: .. | CN20: .. | CO20: .. | CP20: 15538 | CQ20: .. | CR20: .. | CS20: .. | CT20: 16221 | CU20: 15870 | CV20: 15820 | CW20: 16099 | CX20: 15366 | CY20: 14941 | CZ20: 15376 | DA20: 15543 | DB20: 14962 | DC20: 14987 | DD20: 15676 | DE20: 15966 | DF20: 16077 | DG20: 15659 | DH20: 15803 | DI20: 15997 | DJ20: 16188 | DK20: 15974 | DL20: .. | DM20: .. | DN20: .. | DO20: 22250 | DP20: .. | DQ20: .. | DR20: .. | DS20: 22606 | DT20: .. | DU20: .. | DV20: .. | DW20: 23420 | DX20: .. | DY20: .. | DZ20: .. | EA20: 24543 | EB20: .. | EC20: .. | ED20: .. | EE20: 25748 | EF20: .. | EG20: .. | EH20: .. | EI20: 27209 | EJ20: .. | EK20: .. | EL20: .. | EM20: 28531 | EN20: .. | EO20: .. | EP20: .. | EQ20: 29388 | ER20: .. | ES20: .. | ET20: .. | EU20: 29750 | EV20: .. | EW20: .. | EX20: .. | EY20: 30596 | EZ20: 29914 | FA20: 30125 | FB20: 31574 | FC20: 32765 | FD20: 32615 | FE20: 34080 | FF20: 35075 | FG20: 34467 | FH20: 34725 | FI20: 35532 | FJ20: 36471 | FK20: 36042 | FL20: 35518 | FM20: 36000 | FN20: 36286 | FO20: 36432 | FP20: 35998 | FQ20: .. | FR20: .. | FS20: .. | FT20: 35488 | FU20: .. | FV20: .. | FW20: .. | FX20: 35778 | FY20: .. | FZ20: .. | GA20: .. | GB20: 36306 | GC20: .. | GD20: .. | GE20: .. | GF20: 37005 | GG20: .. | GH20: .. | GI20: .. | GJ20: 38226 | GK20: .. | GL20: .. | GM20: .. | GN20: 39623 | GO20: .. | GP20: .. | GQ20: .. | GR20: 41391 | GS20: .. | GT20: .. | GU20: .. | GV20: 42393 | GW20: .. | GX20: .. | GY20: .. | GZ20: 43959 | HA20: .. | HB20: .. | HC20: .. | HD20: 45054 | HE20: 43775 | HF20: 44853 | HG20: 46954 | HH20: 46051 | HI20: 47067 | HJ20: 48605 | HK20: 50867 | HL20: 50625 | HM20: 51154 | HN20: 52453 | HO20: 51621 | HP20: 51777 | HQ20: 50998 | HR20: 51894 | HS20: 51570 | HT20: 52066 | HU20: 51463 | HV20: .. | HW20: .. | HX20: .. | HY20: 45876 | HZ20: .. | IA20: .. | IB20: .. | IC20: 46065 | ID20: .. | IE20: .. | IF20: .. | IG20: 47096 | IH20: .. | II20: .. | IJ20: .. | IK20: 49023 | IL20: .. | IM20: .. | IN20: .. | IO20: 52005 | IP20: .. | IQ20: .. | IR20: .. | IS20: 55375 | IT20: .. | IU20: .. | IV20: .. | IW20: 58420 | IX20: .. | IY20: .. | IZ20: .. | JA20: 59990 | JB20: .. | JC20: .. | JD20: .. | JE20: 58721 | JF20: .. | JG20: .. | JH20: .. | JI20: 59277 | JJ20: 57601 | JK20: 56925 | JL20: 59897 | JM20: 60463 | JN20: 61830 | JO20: 64075 | JP20: 66394 | JQ20: 64939 | JR20: 65958 | JS20: 68199 | JT20: 68868 | JU20: 67326 | JV20: 66173 | JW20: 67330 | JX20: 68544 | JY20: 67691 | JZ20: 67065 | KA20: .. | KB20: .. | KC20: .. | KD20: 81390 | KE20: .. | KF20: .. | KG20: .. | KH20: 81925 | KI20: .. | KJ20: .. | KK20: .. | KL20: 83178 | KM20: .. | KN20: .. | KO20: .. | KP20: 84706 | KQ20: .. | KR20: .. | KS20: .. | KT20: 87041 | KU20: .. | KV20: .. | KW20: .. | KX20: 89890 | KY20: .. | KZ20: .. | LA20: .. | LB20: 93059 | LC20: .. | LD20: .. | LE20: .. | LF20: 94763 | LG20: .. | LH20: .. | LI20: .. | LJ20: 96354 | LK20: .. | LL20: .. | LM20: .. | LN20: 97833 | LO20: 95809 | LP20: 95861 | LQ20: 100371 | LR20: 100314 | LS20: 101973 | LT20: 105779 | LU20: 109511 | LV20: 107406 | LW20: 108177 | LX20: 111882 | LY20: 113014 | LZ20: 112206 | MA20: 110261 | MB20: 111897 | MC20: 112871 | MD20: 113426 | ME20: 111530
A21: Total liabilities | B21: .. | C21: .. | D21: .. | E21: 115012 | F21: .. | G21: .. | H21: .. | I21: 119307 | J21: .. | K21: .. | L21: .. | M21: 123197 | N21: .. | O21: .. | P21: .. | Q21: 126848 | R21: .. | S21: .. | T21: .. | U21: 131161 | V21: .. | W21: .. | X21: .. | Y21: 137567 | Z21: .. | AA21: .. | AB21: .. | AC21: 143303 | AD21: .. | AE21: .. | AF21: .. | AG21: 147733 | AH21: .. | AI21: .. | AJ21: .. | AK21: 150205 | AL21: .. | AM21: .. | AN21: .. | AO21: 153507 | AP21: 152035 | AQ21: 154276 | AR21: 158348 | AS21: 158144 | AT21: 160006 | AU21: 166121 | AV21: 170512 | AW21: 167306 | AX21: 169208 | AY21: 173065 | AZ21: 174757 | BA21: 175000 | BB21: 174272 | BC21: 175861 | BD21: 176612 | BE21: 176803 | BF21: 176880 | BG21: .. | BH21: .. | BI21: .. | BJ21: 69348 | BK21: .. | BL21: .. | BM21: .. | BN21: 70175 | BO21: .. | BP21: .. | BQ21: .. | BR21: 67744 | BS21: .. | BT21: .. | BU21: .. | BV21: 64658 | BW21: .. | BX21: .. | BY21: .. | BZ21: 63479 | CA21: .. | CB21: .. | CC21: .. | CD21: 64155 | CE21: .. | CF21: .. | CG21: .. | CH21: 62588 | CI21: .. | CJ21: .. | CK21: .. | CL21: 62840 | CM21: .. | CN21: .. | CO21: .. | CP21: 74617 | CQ21: .. | CR21: .. | CS21: .. | CT21: 77198 | CU21: 73930 | CV21: 72334 | CW21: 71023 | CX21: 63226 | CY21: 50636 | CZ21: 50627 | DA21: 45783 | DB21: 39852 | DC21: 39101 | DD21: 47255 | DE21: 57554 | DF21: 59760 | DG21: 55460 | DH21: 55528 | DI21: 58758 | DJ21: 61735 | DK21: 58482 | DL21: .. | DM21: .. | DN21: .. | DO21: 93872 | DP21: .. | DQ21: .. | DR21: .. | DS21: 97552 | DT21: .. | DU21: .. | DV21: .. | DW21: 102730 | DX21: .. | DY21: .. | DZ21: .. | EA21: 105945 | EB21: .. | EC21: .. | ED21: .. | EE21: 105664 | EF21: .. | EG21: .. | EH21: .. | EI21: 109601 | EJ21: .. | EK21: .. | EL21: .. | EM21: 113176 | EN21: .. | EO21: .. | EP21: .. | EQ21: 116721 | ER21: .. | ES21: .. | ET21: .. | EU21: 119385 | EV21: .. | EW21: .. | EX21: .. | EY21: 124875 | EZ21: 124404 | FA21: 124529 | FB21: 127702 | FC21: 125663 | FD21: 128701 | FE21: 131891 | FF21: 134743 | FG21: 128423 | FH21: 128705 | FI21: 135811 | FJ21: 135058 | FK21: 137028 | FL21: 136236 | FM21: 136550 | FN21: 137163 | FO21: 140604 | FP21: 138800 | FQ21: .. | FR21: .. | FS21: .. | FT21: 137420 | FU21: .. | FV21: .. | FW21: .. | FX21: 145298 | FY21: .. | FZ21: .. | GA21: .. | GB21: 149805 | GC21: .. | GD21: .. | GE21: .. | GF21: 152263 | GG21: .. | GH21: .. | GI21: .. | GJ21: 158280 | GK21: .. | GL21: .. | GM21: .. | GN21: 162925 | GO21: .. | GP21: .. | GQ21: .. | GR21: 167980 | GS21: .. | GT21: .. | GU21: .. | GV21: 171927 | GW21: .. | GX21: .. | GY21: .. | GZ21: 171801 | HA21: .. | HB21: .. | HC21: .. | HD21: 170560 | HE21: 167360 | HF21: 174456 | HG21: 179696 | HH21: 176103 | HI21: 180576 | HJ21: 190586 | HK21: 199708 | HL21: 199803 | HM21: 202633 | HN21: 202936 | HO21: 206165 | HP21: 204509 | HQ21: 204450 | HR21: 206609 | HS21: 207316 | HT21: 202310 | HU21: 205220 | HV21: .. | HW21: .. | HX21: .. | HY21: 126735 | HZ21: .. | IA21: .. | IB21: .. | IC21: 129195 | ID21: .. | IE21: .. | IF21: .. | IG21: 134935 | IH21: .. | II21: .. | IJ21: .. | IK21: 141536 | IL21: .. | IM21: .. | IN21: .. | IO21: 147918 | IP21: .. | IQ21: .. | IR21: .. | IS21: 156717 | IT21: .. | IU21: .. | IV21: .. | IW21: 164820 | IX21: .. | IY21: .. | IZ21: .. | JA21: 170462 | JB21: .. | JC21: .. | JD21: .. | JE21: 172111 | JF21: .. | JG21: .. | JH21: .. | JI21: 181858 | JJ21: 183808 | JK21: 185726 | JL21: 192517 | JM21: 201380 | JN21: 208226 | JO21: 216915 | JP21: 223080 | JQ21: 217136 | JR21: 215799 | JS21: 226074 | JT21: 223911 | JU21: 223973 | JV21: 223858 | JW21: 226372 | JX21: 226087 | JY21: 227664 | JZ21: 229131 | KA21: .. | KB21: .. | KC21: .. | KD21: 147682 | KE21: .. | KF21: .. | KG21: .. | KH21: 154314 | KI21: .. | KJ21: .. | KK21: .. | KL21: 160772 | KM21: .. | KN21: .. | KO21: .. | KP21: 169840 | KQ21: .. | KR21: .. | KS21: .. | KT21: 180461 | KU21: .. | KV21: .. | KW21: .. | KX21: 194439 | KY21: .. | KZ21: .. | LA21: .. | LB21: 207951 | LC21: .. | LD21: .. | LE21: .. | LF21: 216713 | LG21: .. | LH21: .. | LI21: .. | LJ21: 213110 | LK21: .. | LL21: .. | LM21: .. | LN21: 213043 | LO21: 210673 | LP21: 214333 | LQ21: 220802 | LR21: 224350 | LS21: 231891 | LT21: 240584 | LU21: 249244 | LV21: 251315 | LW21: 259802 | LX21: 253250 | LY21: 251100 | LZ21: 249731 | MA21: 251354 | MB21: 254246 | MC21: 253735 | MD21: 251705 | ME21: 252767
A22: Mortgage liabilities | B22: .. | C22: .. | D22: .. | E22: 72886 | F22: .. | G22: .. | H22: .. | I22: 76603 | J22: .. | K22: .. | L22: .. | M22: 79944 | N22: .. | O22: .. | P22: .. | Q22: 82763 | R22: .. | S22: .. | T22: .. | U22: 86075 | V22: .. | W22: .. | X22: .. | Y22: 91635 | Z22: .. | AA22: .. | AB22: .. | AC22: 96510 | AD22: .. | AE22: .. | AF22: .. | AG22: 100099 | AH22: .. | AI22: .. | AJ22: .. | AK22: 101965 | AL22: .. | AM22: .. | AN22: .. | AO22: 105283 | AP22: 105378 | AQ22: 107902 | AR22: 111116 | AS22: 111888 | AT22: 114348 | AU22: 119528 | AV22: 123145 | AW22: 121419 | AX22: 123364 | AY22: 126400 | AZ22: 127804 | BA22: 128069 | BB22: 127940 | BC22: 128925 | BD22: 129504 | BE22: 129588 | BF22: 129685 | BG22: .. | BH22: .. | BI22: .. | BJ22: 30440 | BK22: .. | BL22: .. | BM22: .. | BN22: 31243 | BO22: .. | BP22: .. | BQ22: .. | BR22: 29524 | BS22: .. | BT22: .. | BU22: .. | BV22: 27000 | BW22: .. | BX22: .. | BY22: .. | BZ22: 26054 | CA22: .. | CB22: .. | CC22: .. | CD22: 25922 | CE22: .. | CF22: .. | CG22: .. | CH22: 24277 | CI22: .. | CJ22: .. | CK22: .. | CL22: 24623 | CM22: .. | CN22: .. | CO22: .. | CP22: 33511 | CQ22: .. | CR22: .. | CS22: .. | CT22: 35275 | CU22: 33835 | CV22: 33617 | CW22: 32513 | CX22: 27411 | CY22: 18338 | CZ22: 18430 | DA22: 14955 | DB22: 11019 | DC22: 10478 | DD22: 16596 | DE22: 24526 | DF22: 26412 | DG22: 23628 | DH22: 23403 | DI22: 25577 | DJ22: 27910 | DK22: 25516 | DL22: .. | DM22: .. | DN22: .. | DO22: 64620 | DP22: .. | DQ22: .. | DR22: .. | DS22: 68322 | DT22: .. | DU22: .. | DV22: .. | DW22: 72417 | DX22: .. | DY22: .. | DZ22: .. | EA22: 73786 | EB22: .. | EC22: .. | ED22: .. | EE22: 72755 | EF22: .. | EG22: .. | EH22: .. | EI22: 75461 | EJ22: .. | EK22: .. | EL22: .. | EM22: 78372 | EN22: .. | EO22: .. | EP22: .. | EQ22: 80911 | ER22: .. | ES22: .. | ET22: .. | EU22: 82232 | EV22: .. | EW22: .. | EX22: .. | EY22: 86778 | EZ22: 87099 | FA22: 87286 | FB22: 89740 | FC22: 87209 | FD22: 89451 | FE22: 95292 | FF22: 96556 | FG22: 91890 | FH22: 92496 | FI22: 99038 | FJ22: 99068 | FK22: 100799 | FL22: 100147 | FM22: 100146 | FN22: 101318 | FO22: 104539 | FP22: 102535 | FQ22: .. | FR22: .. | FS22: .. | FT22: 97514 | FU22: .. | FV22: .. | FW22: .. | FX22: 104603 | FY22: .. | FZ22: .. | GA22: .. | GB22: 108810 | GC22: .. | GD22: .. | GE22: .. | GF22: 111354 | GG22: .. | GH22: .. | GI22: .. | GJ22: 114381 | GK22: .. | GL22: .. | GM22: .. | GN22: 118039 | GO22: .. | GP22: .. | GQ22: .. | GR22: 121152 | GS22: .. | GT22: .. | GU22: .. | GV22: 124221 | GW22: .. | GX22: .. | GY22: .. | GZ22: 124611 | HA22: .. | HB22: .. | HC22: .. | HD22: 125899 | HE22: 125294 | HF22: 131334 | HG22: 136244 | HH22: 136548 | HI22: 140959 | HJ22: 146515 | HK22: 154034 | HL22: 154492 | HM22: 156646 | HN22: 156860 | HO22: 159718 | HP22: 159012 | HQ22: 159578 | HR22: 160804 | HS22: 161414 | HT22: 157405 | HU22: 159839 | HV22: .. | HW22: .. | HX22: .. | HY22: 82921 | HZ22: .. | IA22: .. | IB22: .. | IC22: 84835 | ID22: .. | IE22: .. | IF22: .. | IG22: 89343 | IH22: .. | II22: .. | IJ22: .. | IK22: 93597 | IL22: .. | IM22: .. | IN22: .. | IO22: 99521 | IP22: .. | IQ22: .. | IR22: .. | IS22: 106713 | IT22: .. | IU22: .. | IV22: .. | IW22: 115445 | IX22: .. | IY22: .. | IZ22: .. | JA22: 120508 | JB22: .. | JC22: .. | JD22: .. | JE22: 121854 | JF22: .. | JG22: .. | JH22: .. | JI22: 129128 | JJ22: 132281 | JK22: 135687 | JL22: 140600 | JM22: 148441 | JN22: 155317 | JO22: 162695 | JP22: 167850 | JQ22: 164703 | JR22: 163592 | JS22: 171978 | JT22: 170243 | JU22: 170032 | JV22: 170219 | JW22: 172043 | JX22: 171620 | JY22: 172761 | JZ22: 174210 | KA22: .. | KB22: .. | KC22: .. | KD22: 88936 | KE22: .. | KF22: .. | KG22: .. | KH22: 94012 | KI22: .. | KJ22: .. | KK22: .. | KL22: 99625 | KM22: .. | KN22: .. | KO22: .. | KP22: 108078 | KQ22: .. | KR22: .. | KS22: .. | KT22: 117662 | KU22: .. | KV22: .. | KW22: .. | KX22: 132043 | KY22: .. | KZ22: .. | LA22: .. | LB22: 143306 | LC22: .. | LD22: .. | LE22: .. | LF22: 150230 | LG22: .. | LH22: .. | LI22: .. | LJ22: 147617 | LK22: .. | LL22: .. | LM22: .. | LN22: 149335 | LO22: 148383 | LP22: 151585 | LQ22: 156485 | LR22: 159832 | LS22: 167677 | LT22: 174707 | LU22: 182329 | LV22: 184995 | LW22: 193608 | LX22: 187530 | LY22: 185464 | LZ22: 184088 | MA22: 186127 | MB22: 188228 | MC22: 187590 | MD22: 185328 | ME22: 186327
A23: Other liabilities 6 | B23: .. | C23: .. | D23: .. | E23: 42125 | F23: .. | G23: .. | H23: .. | I23: 42704 | J23: .. | K23: .. | L23: .. | M23: 43253 | N23: .. | O23: .. | P23: .. | Q23: 44085 | R23: .. | S23: .. | T23: .. | U23: 45086 | V23: .. | W23: .. | X23: .. | Y23: 45932 | Z23: .. | AA23: .. | AB23: .. | AC23: 46793 | AD23: .. | AE23: .. | AF23: .. | AG23: 47634 | AH23: .. | AI23: .. | AJ23: .. | AK23: 48240 | AL23: .. | AM23: .. | AN23: .. | AO23: 48224 | AP23: 46657 | AQ23: 46374 | AR23: 47232 | AS23: 46256 | AT23: 45658 | AU23: 46593 | AV23: 47367 | AW23: 45886 | AX23: 45844 | AY23: 46665 | AZ23: 46953 | BA23: 46931 | BB23: 46332 | BC23: 46936 | BD23: 47108 | BE23: 47215 | BF23: 47194 | BG23: .. | BH23: .. | BI23: .. | BJ23: 38908 | BK23: .. | BL23: .. | BM23: .. | BN23: 38932 | BO23: .. | BP23: .. | BQ23: .. | BR23: 38219 | BS23: .. | BT23: .. | BU23: .. | BV23: 37657 | BW23: .. | BX23: .. | BY23: .. | BZ23: 37425 | CA23: .. | CB23: .. | CC23: .. | CD23: 38234 | CE23: .. | CF23: .. | CG23: .. | CH23: 38312 | CI23: .. | CJ23: .. | CK23: .. | CL23: 38216 | CM23: .. | CN23: .. | CO23: .. | CP23: 41106 | CQ23: .. | CR23: .. | CS23: .. | CT23: 41923 | CU23: 40095 | CV23: 38717 | CW23: 38509 | CX23: 35815 | CY23: 32298 | CZ23: 32196 | DA23: 30828 | DB23: 28833 | DC23: 28622 | DD23: 30660 | DE23: 33028 | DF23: 33348 | DG23: 31832 | DH23: 32125 | DI23: 33181 | DJ23: 33825 | DK23: 32966 | DL23: .. | DM23: .. | DN23: .. | DO23: 29252 | DP23: .. | DQ23: .. | DR23: .. | DS23: 29231 | DT23: .. | DU23: .. | DV23: .. | DW23: 30313 | DX23: .. | DY23: .. | DZ23: .. | EA23: 32159 | EB23: .. | EC23: .. | ED23: .. | EE23: 32908 | EF23: .. | EG23: .. | EH23: .. | EI23: 34140 | EJ23: .. | EK23: .. | EL23: .. | EM23: 34803 | EN23: .. | EO23: .. | EP23: .. | EQ23: 35811 | ER23: .. | ES23: .. | ET23: .. | EU23: 37153 | EV23: .. | EW23: .. | EX23: .. | EY23: 38097 | EZ23: 37306 | FA23: 37243 | FB23: 37963 | FC23: 38454 | FD23: 39250 | FE23: 36599 | FF23: 38187 | FG23: 36534 | FH23: 36209 | FI23: 36772 | FJ23: 35991 | FK23: 36229 | FL23: 36089 | FM23: 36404 | FN23: 35845 | FO23: 36065 | FP23: 36264 | FQ23: .. | FR23: .. | FS23: .. | FT23: 39905 | FU23: .. | FV23: .. | FW23: .. | FX23: 40695 | FY23: .. | FZ23: .. | GA23: .. | GB23: 40995 | GC23: .. | GD23: .. | GE23: .. | GF23: 40909 | GG23: .. | GH23: .. | GI23: .. | GJ23: 43900 | GK23: .. | GL23: .. | GM23: .. | GN23: 44886 | GO23: .. | GP23: .. | GQ23: .. | GR23: 46828 | GS23: .. | GT23: .. | GU23: .. | GV23: 47706 | GW23: .. | GX23: .. | GY23: .. | GZ23: 47190 | HA23: .. | HB23: .. | HC23: .. | HD23: 44660 | HE23: 42066 | HF23: 43122 | HG23: 43452 | HH23: 39555 | HI23: 39617 | HJ23: 44072 | HK23: 45674 | HL23: 45311 | HM23: 45987 | HN23: 46076 | HO23: 46446 | HP23: 45497 | HQ23: 44872 | HR23: 45805 | HS23: 45902 | HT23: 44905 | HU23: 45381 | HV23: .. | HW23: .. | HX23: .. | HY23: 43814 | HZ23: .. | IA23: .. | IB23: .. | IC23: 44360 | ID23: .. | IE23: .. | IF23: .. | IG23: 45592 | IH23: .. | II23: .. | IJ23: .. | IK23: 47939 | IL23: .. | IM23: .. | IN23: .. | IO23: 48397 | IP23: .. | IQ23: .. | IR23: .. | IS23: 50005 | IT23: .. | IU23: .. | IV23: .. | IW23: 49374 | IX23: .. | IY23: .. | IZ23: .. | JA23: 49954 | JB23: .. | JC23: .. | JD23: .. | JE23: 50257 | JF23: .. | JG23: .. | JH23: .. | JI23: 52731 | JJ23: 51528 | JK23: 50040 | JL23: 51917 | JM23: 52939 | JN23: 52909 | JO23: 54220 | JP23: 55231 | JQ23: 52433 | JR23: 52206 | JS23: 54096 | JT23: 53668 | JU23: 53941 | JV23: 53640 | JW23: 54329 | JX23: 54468 | JY23: 54903 | JZ23: 54922 | KA23: .. | KB23: .. | KC23: .. | KD23: 58746 | KE23: .. | KF23: .. | KG23: .. | KH23: 60302 | KI23: .. | KJ23: .. | KK23: .. | KL23: 61146 | KM23: .. | KN23: .. | KO23: .. | KP23: 61762 | KQ23: .. | KR23: .. | KS23: .. | KT23: 62800 | KU23: .. | KV23: .. | KW23: .. | KX23: 62395 | KY23: .. | KZ23: .. | LA23: .. | LB23: 64645 | LC23: .. | LD23: .. | LE23: .. | LF23: 66483 | LG23: .. | LH23: .. | LI23: .. | LJ23: 65493 | LK23: .. | LL23: .. | LM23: .. | LN23: 63708 | LO23: 62291 | LP23: 62747 | LQ23: 64317 | LR23: 64518 | LS23: 64214 | LT23: 65877 | LU23: 66915 | LV23: 66320 | LW23: 66194 | LX23: 65720 | LY23: 65635 | LZ23: 65643 | MA23: 65226 | MB23: 66018 | MC23: 66145 | MD23: 66378 | ME23: 66440
A24: Net worth (wealth) | B24: .. | C24: .. | D24: .. | E24: 507316 | F24: .. | G24: .. | H24: .. | I24: 522682 | J24: .. | K24: .. | L24: .. | M24: 557904 | N24: .. | O24: .. | P24: .. | Q24: 591756 | R24: .. | S24: .. | T24: .. | U24: 632992 | V24: .. | W24: .. | X24: .. | Y24: 666275 | Z24: .. | AA24: .. | AB24: .. | AC24: 714683 | AD24: .. | AE24: .. | AF24: .. | AG24: 745800 | AH24: .. | AI24: .. | AJ24: .. | AK24: 737705 | AL24: .. | AM24: .. | AN24: .. | AO24: 789482 | AP24: 762015 | AQ24: 807962 | AR24: 847991 | AS24: 886431 | AT24: 950203 | AU24: 990630 | AV24: 1025394 | AW24: 1044288 | AX24: 1045330 | AY24: 983126 | AZ24: 956217 | BA24: 959821 | BB24: 984921 | BC24: 995765 | BD24: 970390 | BE24: 979236 | BF24: 1009483 | BG24: .. | BH24: .. | BI24: .. | BJ24: -11976 | BK24: .. | BL24: .. | BM24: .. | BN24: -11791 | BO24: .. | BP24: .. | BQ24: .. | BR24: -10769 | BS24: .. | BT24: .. | BU24: .. | BV24: -9530 | BW24: .. | BX24: .. | BY24: .. | BZ24: -8647 | CA24: .. | CB24: .. | CC24: .. | CD24: -7578 | CE24: .. | CF24: .. | CG24: .. | CH24: -6053 | CI24: .. | CJ24: .. | CK24: .. | CL24: -5281 | CM24: .. | CN24: .. | CO24: .. | CP24: -8369 | CQ24: .. | CR24: .. | CS24: .. | CT24: -8637 | CU24: -8034 | CV24: -7029 | CW24: -5831 | CX24: -3445 | CY24: -1205 | CZ24: -666 | DA24: 140 | DB24: 1246 | DC24: 1345 | DD24: 95 | DE24: -1024 | DF24: -1316 | DG24: -324 | DH24: -115 | DI24: -954 | DJ24: -1141 | DK24: -320 | DL24: .. | DM24: .. | DN24: .. | DO24: 49882 | DP24: .. | DQ24: .. | DR24: .. | DS24: 51829 | DT24: .. | DU24: .. | DV24: .. | DW24: 58063 | DX24: .. | DY24: .. | DZ24: .. | EA24: 65484 | EB24: .. | EC24: .. | ED24: .. | EE24: 73182 | EF24: .. | EG24: .. | EH24: .. | EI24: 80792 | EJ24: .. | EK24: .. | EL24: .. | EM24: 90954 | EN24: .. | EO24: .. | EP24: .. | EQ24: 96035 | ER24: .. | ES24: .. | ET24: .. | EU24: 92809 | EV24: .. | EW24: .. | EX24: .. | EY24: 100865 | EZ24: 97987 | FA24: 104876 | FB24: 112094 | FC24: 121550 | FD24: 135892 | FE24: 142116 | FF24: 150167 | FG24: 157268 | FH24: 159020 | FI24: 143580 | FJ24: 135292 | FK24: 133994 | FL24: 139617 | FM24: 141285 | FN24: 135916 | FO24: 135497 | FP24: 141033 | FQ24: .. | FR24: .. | FS24: .. | FT24: 219359 | FU24: .. | FV24: .. | FW24: .. | FX24: 230106 | FY24: .. | FZ24: .. | GA24: .. | GB24: 248711 | GC24: .. | GD24: .. | GE24: .. | GF24: 267067 | GG24: .. | GH24: .. | GI24: .. | GJ24: 286486 | GK24: .. | GL24: .. | GM24: .. | GN24: 304015 | GO24: .. | GP24: .. | GQ24: .. | GR24: 329134 | GS24: .. | GT24: .. | GU24: .. | GV24: 343627 | GW24: .. | GX24: .. | GY24: .. | GZ24: 334747 | HA24: .. | HB24: .. | HC24: .. | HD24: 358918 | HE24: 348527 | HF24: 368731 | HG24: 389305 | HH24: 411457 | HI24: 449236 | HJ24: 467748 | HK24: 489943 | HL24: 505273 | HM24: 509299 | HN24: 471172 | HO24: 451631 | HP24: 449274 | HQ24: 464041 | HR24: 470184 | HS24: 455140 | HT24: 454074 | HU24: 469797 | HV24: .. | HW24: .. | HX24: .. | HY24: 530601 | HZ24: .. | IA24: .. | IB24: .. | IC24: 553232 | ID24: .. | IE24: .. | IF24: .. | IG24: 591036 | IH24: .. | II24: .. | IJ24: .. | IK24: 625425 | IL24: .. | IM24: .. | IN24: .. | IO24: 666376 | IP24: .. | IQ24: .. | IR24: .. | IS24: 699842 | IT24: .. | IU24: .. | IV24: .. | IW24: 748104 | IX24: .. | IY24: .. | IZ24: .. | JA24: 778501 | JB24: .. | JC24: .. | JD24: .. | JE24: 760904 | JF24: .. | JG24: .. | JH24: .. | JI24: 808937 | JJ24: 783139 | JK24: 828369 | JL24: 867444 | JM24: 908809 | JN24: 978688 | JO24: 1019580 | JP24: 1059016 | JQ24: 1082284 | JR24: 1085318 | JS24: 1017323 | JT24: 984026 | JU24: 982013 | JV24: 1008677 | JW24: 1018565 | JX24: 992102 | JY24: 996641 | JZ24: 1024797 | KA24: .. | KB24: .. | KC24: .. | KD24: 1748713 | KE24: .. | KF24: .. | KG24: .. | KH24: 1790035 | KI24: .. | KJ24: .. | KK24: .. | KL24: 1902479 | KM24: .. | KN24: .. | KO24: .. | KP24: 2010335 | KQ24: .. | KR24: .. | KS24: .. | KT24: 2147564 | KU24: .. | KV24: .. | KW24: .. | KX24: 2254305 | KY24: .. | KZ24: .. | LA24: .. | LB24: 2411277 | LC24: .. | LD24: .. | LE24: .. | LF24: 2516117 | LG24: .. | LH24: .. | LI24: .. | LJ24: 2508435 | LK24: .. | LL24: .. | LM24: .. | LN24: 2687328 | LO24: 2588455 | LP24: 2744863 | LQ24: 2876943 | LR24: 2993784 | LS24: 3188403 | LT24: 3324372 | LU24: 3427702 | LV24: 3475369 | LW24: 3471667 | LX24: 3283463 | LY24: 3211161 | LZ24: 3235140 | MA24: 3312592 | MB24: 3348907 | MC24: 3269745 | MD24: 3311107 | ME24: 3412111
A26: Symbol legend:
A27: .. | B27: not available for a specific reference period
A32: Footnotes:
A33: 1 | B33: The coefficients of variation from Statistics Canada's Survey of Financial Security for 2012, 2016 and 2019, which serve as indicators of the accuracy of these estimates for net worth and its components, are available in the appendix to Distributions of Household Economic Accounts, estimates of asset, liability and net worth distributions, 2010 to 2020, technical methodology and quality report for the August 2021 release.
A34: 2 | B34: Wealth quintiles are assigned based on the household net worth.
A35: 3 | B35: Life insurance and pensions include the value of all life insurance and employer pension plans, termination basis. Excludes public plans administered or sponsored by governments: Old Age Security (OAS) including the Guaranteed Income Supplement (GIS) and the Spouse's Allowance (SPA), as well as the Canada and Quebec Pension Plans (CPP/QPP).
A36: 4 | B36: Other financial assets include total currency and deposits, Canadian short-term paper, Canadian bonds and debentures, foreign investments in paper and bonds, mortgages, equity and investment funds, and other receivables.
A37: 5 | B37: Other non-financial assets include consumer durables, machinery and equipment, and intellectual property products. Excludes accumulation of value of collectibles including coins, stamps and art work.
A38: 6 | B38: Other liabilities include major credit cards and retail store cards, gasoline station cards, etc., vehicle loans, lines of credit, student loans, other loans from financial institutions and other money owed.
A42: How to cite: Statistics Canada. Table 36-10-0660-01 Distributions of household economic accounts, wealth, by characteristic, Canada, quarterly (x 1,000,000)
A43: https://www150.statcan.gc.ca/t1/tbl1/en/tv.action?pid=3610066001

Sheet CSV Input
B1: Annual Household Income
B2: $ per Household, 2023
C3: Age Group
B4: Income Quintile | C4: Less than 35 years | D4: 35 to 44 years | E4: 45 to 54 years | F4: 55 to 64 years | G4: 65 years and over | H4: All
B5: 1 | C5: ='2023 Drill Down'!C5 -> 32144 | D5: ='2023 Drill Down'!D5 -> 39230 | E5: ='2023 Drill Down'!E5 -> 39715 | F5: ='2023 Drill Down'!F5 -> 24610 | G5: ='2023 Drill Down'!G5 -> 28735 | H5: ='2023 Drill Down'!H5 -> 31604
B6: 2 | C6: ='2023 Drill Down'!C6 -> 75128 | D6: ='2023 Drill Down'!D6 -> 79366 | E6: ='2023 Drill Down'!E6 -> 62668 | F6: ='2023 Drill Down'!F6 -> 55594 | G6: ='2023 Drill Down'!G6 -> 44502 | H6: ='2023 Drill Down'!H6 -> 59447
B7: 3 | C7: ='2023 Drill Down'!C7 -> 89104 | D7: ='2023 Drill Down'!D7 -> 93589 | E7: ='2023 Drill Down'!E7 -> 98250 | F7: ='2023 Drill Down'!F7 -> 70228 | G7: ='2023 Drill Down'!G7 -> 58049 | H7: ='2023 Drill Down'!H7 -> 78998
B8: 4 | C8: ='2023 Drill Down'!C8 -> 119463 | D8: ='2023 Drill Down'!D8 -> 137538 | E8: ='2023 Drill Down'!E8 -> 135803 | F8: ='2023 Drill Down'!F8 -> 106872 | G8: ='2023 Drill Down'!G8 -> 79024 | H8: ='2023 Drill Down'!H8 -> 114315
B9: 5 | C9: ='2023 Drill Down'!C9 -> 182418 | D9: ='2023 Drill Down'!D9 -> 187629 | E9: ='2023 Drill Down'!E9 -> 262002 | F9: ='2023 Drill Down'!F9 -> 193320 | G9: ='2023 Drill Down'!G9 -> 167492 | H9: ='2023 Drill Down'!H9 -> 197667
B10: All | C10: ='2023 Drill Down'!C10 -> 97767 | D10: ='2023 Drill Down'!D10 -> 112274 | E10: ='2023 Drill Down'!E10 -> 130133 | F10: ='2023 Drill Down'!F10 -> 101450 | G10: ='2023 Drill Down'!G10 -> 65738 | H10: ='2023 Drill Down'!H10 -> 96406
B15: Annual Household Spending
B16: $ per Household, 2023
C17: Age Group
B18: Income Quintile | C18: Less than 35 years | D18: 35 to 44 years | E18: 45 to 54 years | F18: 55 to 64 years | G18: 65 years and over | H18: All
B19: 1 | C19: ='2023 Drill Down'!C19 -> 62761 | D19: ='2023 Drill Down'!D19 -> 63254 | E19: ='2023 Drill Down'!E19 -> 76767 | F19: ='2023 Drill Down'!F19 -> 71238 | G19: ='2023 Drill Down'!G19 -> 52572 | H19: ='2023 Drill Down'!H19 -> 61968
B20: 2 | C20: ='2023 Drill Down'!C20 -> 81310 | D20: ='2023 Drill Down'!D20 -> 97176 | E20: ='2023 Drill Down'!E20 -> 86855 | F20: ='2023 Drill Down'!F20 -> 84889 | G20: ='2023 Drill Down'!G20 -> 55746 | H20: ='2023 Drill Down'!H20 -> 75118
B21: 3 | C21: ='2023 Drill Down'!C21 -> 88214 | D21: ='2023 Drill Down'!D21 -> 99908 | E21: ='2023 Drill Down'!E21 -> 126342 | F21: ='2023 Drill Down'!F21 -> 93812 | G21: ='2023 Drill Down'!G21 -> 68078 | H21: ='2023 Drill Down'!H21 -> 91266
B22: 4 | C22: ='2023 Drill Down'!C22 -> 88615 | D22: ='2023 Drill Down'!D22 -> 112438 | E22: ='2023 Drill Down'!E22 -> 135533 | F22: ='2023 Drill Down'!F22 -> 114766 | G22: ='2023 Drill Down'!G22 -> 72967 | H22: ='2023 Drill Down'!H22 -> 103168
B23: 5 | C23: ='2023 Drill Down'!C23 -> 128919 | D23: ='2023 Drill Down'!D23 -> 131586 | E23: ='2023 Drill Down'!E23 -> 183861 | F23: ='2023 Drill Down'!F23 -> 146632 | G23: ='2023 Drill Down'!G23 -> 96602 | H23: ='2023 Drill Down'!H23 -> 137015
B24: All | C24: ='2023 Drill Down'!C24 -> 88914 | D24: ='2023 Drill Down'!D24 -> 103075 | E24: ='2023 Drill Down'!E24 -> 127283 | F24: ='2023 Drill Down'!F24 -> 107382 | G24: ='2023 Drill Down'!G24 -> 65742 | H24: ='2023 Drill Down'!H24 -> 93707
B29: Annual Cash Flow (excl. pension entitlements)
B30: $ per Household, 2023
C31: Age Group
B32: Income Quintile | C32: Less than 35 years | D32: 35 to 44 years | E32: 45 to 54 years | F32: 55 to 64 years | G32: 65 years and over | H32: All
B33: 1 | C33: ='2023 Drill Down'!C33 -> -30617 | D33: ='2023 Drill Down'!D33 -> -24024 | E33: ='2023 Drill Down'!E33 -> -37052 | F33: ='2023 Drill Down'!F33 -> -46628 | G33: ='2023 Drill Down'!G33 -> -23837 | H33: ='2023 Drill Down'!H33 -> -30364
B34: 2 | C34: ='2023 Drill Down'!C34 -> -6182 | D34: ='2023 Drill Down'!D34 -> -17810 | E34: ='2023 Drill Down'!E34 -> -24187 | F34: ='2023 Drill Down'!F34 -> -29295 | G34: ='2023 Drill Down'!G34 -> -11244 | H34: ='2023 Drill Down'!H34 -> -15671
B35: 3 | C35: ='2023 Drill Down'!C35 -> 890 | D35: ='2023 Drill Down'!D35 -> -6319 | E35: ='2023 Drill Down'!E35 -> -28092 | F35: ='2023 Drill Down'!F35 -> -23584 | G35: ='2023 Drill Down'!G35 -> -10029 | H35: ='2023 Drill Down'!H35 -> -12268
B36: 4 | C36: ='2023 Drill Down'!C36 -> 30848 | D36: ='2023 Drill Down'!D36 -> 25100 | E36: ='2023 Drill Down'!E36 -> 270 | F36: ='2023 Drill Down'!F36 -> -7894 | G36: ='2023 Drill Down'!G36 -> 6057 | H36: ='2023 Drill Down'!H36 -> 11147
B37: 5 | C37: ='2023 Drill Down'!C37 -> 53499 | D37: ='2023 Drill Down'!D37 -> 56043 | E37: ='2023 Drill Down'!E37 -> 78141 | F37: ='2023 Drill Down'!F37 -> 46688 | G37: ='2023 Drill Down'!G37 -> 70890 | H37: ='2023 Drill Down'!H37 -> 60652
B38: All | C38: ='2023 Drill Down'!C38 -> 8853 | D38: ='2023 Drill Down'!D38 -> 9199 | E38: ='2023 Drill Down'!E38 -> 2850 | F38: ='2023 Drill Down'!F38 -> -5932 | G38: ='2023 Drill Down'!G38 -> -4 | H38: ='2023 Drill Down'!H38 -> 2699
B43: Implied Savings Rate
B44: Annual cash flow as a % of annual income
C45: Age Group
B46: Income Quintile | C46: Less than 35 years | D46: 35 to 44 years | E46: 45 to 54 years | F46: 55 to 64 years | G46: 65 years and over | H46: All
B47: 1 | C47: ='2023 Drill Down'!C47 -> -0.95249502 | D47: ='2023 Drill Down'!D47 -> -0.61238848 | E47: ='2023 Drill Down'!E47 -> -0.93294725 | F47: ='2023 Drill Down'!F47 -> -1.894677 | G47: ='2023 Drill Down'!G47 -> -0.82954585 | H47: ='2023 Drill Down'!H47 -> -0.96076446
B48: 2 | C48: ='2023 Drill Down'!C48 -> -0.082286231 | D48: ='2023 Drill Down'!D48 -> -0.2244034 | E48: ='2023 Drill Down'!E48 -> -0.38595455 | F48: ='2023 Drill Down'!F48 -> -0.52694535 | G48: ='2023 Drill Down'!G48 -> -0.2526628 | H48: ='2023 Drill Down'!H48 -> -0.26361297
B49: 3 | C49: ='2023 Drill Down'!C49 -> 0.0099883282 | D49: ='2023 Drill Down'!D49 -> -0.067518619 | E49: ='2023 Drill Down'!E49 -> -0.28592366 | F49: ='2023 Drill Down'!F49 -> -0.33582047 | G49: ='2023 Drill Down'!G49 -> -0.17276783 | H49: ='2023 Drill Down'!H49 -> -0.15529507
B50: 4 | C50: ='2023 Drill Down'!C50 -> 0.25822221 | D50: ='2023 Drill Down'!D50 -> 0.18249502 | E50: ='2023 Drill Down'!E50 -> 0.001988174 | F50: ='2023 Drill Down'!F50 -> -0.073864062 | G50: ='2023 Drill Down'!G50 -> 0.076647601 | H50: ='2023 Drill Down'!H50 -> 0.097511263
B51: 5 | C51: ='2023 Drill Down'!C51 -> 0.29327698 | D51: ='2023 Drill Down'!D51 -> 0.2986905 | E51: ='2023 Drill Down'!E51 -> 0.29824581 | F51: ='2023 Drill Down'!F51 -> 0.24150631 | G51: ='2023 Drill Down'!G51 -> 0.4232441 | H51: ='2023 Drill Down'!H51 -> 0.30683928
B52: All | C52: ='2023 Drill Down'!C52 -> 0.090552027 | D52: ='2023 Drill Down'!D52 -> 0.081933484 | E52: ='2023 Drill Down'!E52 -> 0.021900671 | F52: ='2023 Drill Down'!F52 -> -0.058472154 | G52: ='2023 Drill Down'!G52 -> -6.0847607e-05 | H52: ='2023 Drill Down'!H52 -> 0.027996183
C54: Annual Cash Flow by Year
B55: Income Quintile | C55: 1999 | D55: =C55+1 -> 2000 | E55: =D55+1 -> 2001 | F55: =E55+1 -> 2002 | G55: =F55+1 -> 2003 | H55: =G55+1 -> 2004 | I55: =H55+1 -> 2005 | J55: =I55+1 -> 2006 | K55: =J55+1 -> 2007 | ... AA55: =Z55+1 -> 2023
B56: 1 | C56: ='All Ages Over Time'!C43 -> -16144.604 | D56: ='All Ages Over Time'!D43 -> -18244.349 | E56: ='All Ages Over Time'!E43 -> -14648.21 | F56: ='All Ages Over Time'!F43 -> -17438.1 | G56: ='All Ages Over Time'!G43 -> -16788.916 | H56: ='All Ages Over Time'!H43 -> -19756.788 | I56: ='All Ages Over Time'!I43 -> -23384.408 | J56: ='All Ages Over Time'!J43 -> -25645.747 | ... AA56: ='All Ages Over Time'!AA43 -> -30364
B57: 2 | C57: ='All Ages Over Time'!C49 -> -11264.188 | D57: ='All Ages Over Time'!D49 -> -11132.034 | E57: ='All Ages Over Time'!E49 -> -9215.5695 | F57: ='All Ages Over Time'!F49 -> -11015.852 | G57: ='All Ages Over Time'!G49 -> -12375.446 | H57: ='All Ages Over Time'!H49 -> -13774.384 | I57: ='All Ages Over Time'!I49 -> -14253.521 | J57: ='All Ages Over Time'!J49 -> -13647.973 | ... AA57: ='All Ages Over Time'!AA49 -> -15671
B58: 3 | C58: ='All Ages Over Time'!C55 -> -7758.6093 | D58: ='All Ages Over Time'!D55 -> -8770.5933 | E58: ='All Ages Over Time'!E55 -> -9446.8824 | F58: ='All Ages Over Time'!F55 -> -10411.017 | G58: ='All Ages Over Time'!G55 -> -9916.5554 | H58: ='All Ages Over Time'!H55 -> -9787.6151 | I58: ='All Ages Over Time'!I55 -> -11061.602 | J58: ='All Ages Over Time'!J55 -> -9618.9551 | ... AA58: ='All Ages Over Time'!AA55 -> -12268
B59: 4 | C59: ='All Ages Over Time'!C61 -> 744.06889 | D59: ='All Ages Over Time'!D61 -> -1547.9455 | E59: ='All Ages Over Time'!E61 -> -795.13804 | F59: ='All Ages Over Time'!F61 -> 406.889 | G59: ='All Ages Over Time'!G61 -> -4503.6352 | H59: ='All Ages Over Time'!H61 -> -624.19866 | I59: ='All Ages Over Time'!I61 -> -2733.8336 | J59: ='All Ages Over Time'!J61 -> -2305.3813 | ... AA59: ='All Ages Over Time'!AA61 -> 11147
B60: 5 | C60: ='All Ages Over Time'!C67 -> 29253.745 | D60: ='All Ages Over Time'!D67 -> 33305.529 | E60: ='All Ages Over Time'!E67 -> 34176.479 | F60: ='All Ages Over Time'!F67 -> 32758.492 | G60: ='All Ages Over Time'!G67 -> 32676.189 | H60: ='All Ages Over Time'!H67 -> 33534.173 | I60: ='All Ages Over Time'!I67 -> 33868.998 | J60: ='All Ages Over Time'!J67 -> 40634.325 | ... AA60: ='All Ages Over Time'!AA67 -> 60652

Sheet StatCan Data

Sheet 2023 per HH by Age and Quintile
A1: Distributions of household economic accounts, income, consumption and saving, by characteristic, annual
A2: Frequency: Annual
A3: Table: 36-10-0587-01 (formerly CANSIM 378-0152)
A4: Release date: 2024-07-17
A5: Geography: Canada
A6: https://www150.statcan.gc.ca/t1/tbl1/en/cv!recreate.action?pid=3610058701&selectedNodeIds=2D3,3D2,3D3,3D4,3D5,3D6,3D17,3D18,3D19,3D20,3D21,3D22,3D23,3D24,3D25,3D26,3D27,3D28,3D29,3D30,3D31,3D32,3D33,3D34,3D35,3D36,3D37,3D38,3D39,3D40,3D41,3D42,3D43,3D44,3D45,3D46,4D1,4D2,4D3,4D4,4D5,4D6,4D7,4D8,4D9,4D10,4D11,4D12,4D13,4D14,4D15,4D16,4D17,4D18,4D19,4D20,4D21,4D22,4D23&checkedLevels=0D1,2D1&refPeriods=20230101,20230101&dimensionLayouts=layout2,layout2,layout2,layout3,layout2&vectorDisplay=false
A9: Geography | B9: Canada
A10: Statistics | B10: Value per household
A11: Quintile | B11: All | C11: 1 | D11: 2 | E11: 3 | F11: 4 | G11: 5 | H11: All | I11: All | J11: All | K11: All | L11: All | M11: 1 | N11: 1 | O11: 1 | P11: 1 | Q11: 1 | R11: 2 | S11: 2 | T11: 2 | U11: 2 | V11: 2 | W11: 3 | X11: 3 | Y11: 3 | Z11: 3 | AA11: 3 | AB11: 4 | AC11: 4 | AD11: 4 | AE11: 4 | AF11: 4 | AG11: 5 | AH11: 5 | AI11: 5 | AJ11: 5 | AK11: 5
A12: Age | B12: All | C12: All | D12: All | E12: All | F12: All | G12: All | H12: Less than 35 years | I12: 35 to 44 years | J12: 45 to 54 years | K12: 55 to 64 years | L12: 65 years and over | M12: Less than 35 years | N12: 35 to 44 years | O12: 45 to 54 years | P12: 55 to 64 years | Q12: 65 years and over | R12: Less than 35 years | S12: 35 to 44 years | T12: 45 to 54 years | U12: 55 to 64 years | V12: 65 years and over | W12: Less than 35 years | X12: 35 to 44 years | Y12: 45 to 54 years | Z12: 55 to 64 years | AA12: 65 years and over | AB12: Less than 35 years | AC12: 35 to 44 years | AD12: 45 to 54 years | AE12: 55 to 64 years | AF12: 65 years and over | AG12: Less than 35 years | AH12: 35 to 44 years | AI12: 45 to 54 years | AJ12: 55 to 64 years | AK12: 65 years and over
A13: Characteristics | B13: All households | C13: Lowest income quintile 1 | D13: Second income quintile 1 | E13: Third income quintile 1 | F13: Fourth income quintile 1 | G13: Highest income quintile 1 | H13: Less than 35 years 2 | I13: 35 to 44 years 2 | J13: 45 to 54 years 2 | K13: 55 to 64 years 2 | L13: 65 years and over 2 | M13: Lowest income quintile, less than 35 years 1 2 | N13: Lowest income quintile, 35 to 44 years 1 2 | O13: Lowest income quintile, 45 to 54 years 1 2 | P13: Lowest income quintile, 55 to 64 years 1 2 | Q13: Lowest income quintile, 65 years and over 1 2 | R13: Second income quintile, less than 35 years 1 2 | S13: Second income quintile, 35 to 44 years 1 2 | T13: Second income quintile, 45 to 54 years 1 2 | U13: Second income quintile, 55 to 64 years 1 2 | V13: Second income quintile, 65 years and over 1 2 | W13: Third income quintile, less than 35 years 1 2 | X13: Third income quintile, 35 to 44 years 1 2 | Y13: Third income quintile, 45 to 54 years 1 2 | Z13: Third income quintile, 55 to 64 years 1 2 | AA13: Third income quintile, 65 years and over 1 2 | AB13: Fourth income quintile, less than 35 years 1 2 | AC13: Fourth income quintile, 35 to 44 years 1 2 | AD13: Fourth income quintile, 45 to 54 years 1 2 | AE13: Fourth income quintile, 55 to 64 years 1 2 | AF13: Fourth income quintile, 65 years and over 1 2 | AG13: Highest income quintile, less than 35 years 1 2 | AH13: Highest income quintile, 35 to 44 years 1 2 | AI13: Highest income quintile, 45 to 54 years 1 2 | AJ13: Highest income quintile, 55 to 64 years 1 2 | AK13: Highest income quintile, 65 years and over 1 2
A14: Income, consumption and savings | B14: 2023 | C14: 2023 | D14: 2023 | E14: 2023 | F14: 2023 | G14: 2023 | H14: 2023 | I14: 2023 | J14: 2023 | K14: 2023 | L14: 2023 | M14: 2023 | N14: 2023 | O14: 2023 | P14: 2023 | Q14: 2023 | R14: 2023 | S14: 2023 | T14: 2023 | U14: 2023 | V14: 2023 | W14: 2023 | X14: 2023 | Y14: 2023 | Z14: 2023 | AA14: 2023 | AB14: 2023 | AC14: 2023 | AD14: 2023 | AE14: 2023 | AF14: 2023 | AG14: 2023 | AH14: 2023 | AI14: 2023 | AJ14: 2023 | AK14: 2023
B15: Dollars
A16: Household disposable income | B16: 96406 | C16: 31604 | D16: 59447 | E16: 78998 | F16: 114315 | G16: 197667 | H16: 97767 | I16: 112274 | J16: 130133 | K16: 101450 | L16: 65738 | M16: 32144 | N16: 39230 | O16: 39715 | P16: 24610 | Q16: 28735 | R16: 75128 | S16: 79366 | T16: 62668 | U16: 55594 | V16: 44502 | W16: 89104 | X16: 93589 | Y16: 98250 | Z16: 70228 | AA16: 58049 | AB16: 119463 | AC16: 137538 | AD16: 135803 | AE16: 106872 | AF16: 79024 | AG16: 182418 | AH16: 187629 | AI16: 262002 | AJ16: 193320 | AK16: 167492
A17: Compensation of employees | B17: 88732 | C17: 13234 | D17: 37027 | E17: 69679 | F17: 120934 | G17: 202784 | H17: 111139 | I17: 127981 | J17: 149979 | K17: 102771 | L17: 12243 | M17: .. | N17: .. | O17: .. | P17: .. | Q17: .. | R17: .. | S17: .. | T17: .. | U17: .. | V17: .. | W17: .. | X17: .. | Y17: .. | Z17: .. | AA17: .. | AB17: .. | AC17: .. | AD17: .. | AE17: .. | AF17: .. | AG17: .. | AH17: .. | AI17: .. | AJ17: .. | AK17: ..
A18: Net mixed income | B18: 15541 | C18: 5471 | D18: 10806 | E18: 13610 | F18: 17590 | G18: 30226 | H18: 13266 | I18: 17759 | J18: 20355 | K18: 18286 | L18: 11499 | M18: .. | N18: .. | O18: .. | P18: .. | Q18: .. | R18: .. | S18: .. | T18: .. | U18: .. | V18: .. | W18: .. | X18: .. | Y18: .. | Z18: .. | AA18: .. | AB18: .. | AC18: .. | AD18: .. | AE18: .. | AF18: .. | AG18: .. | AH18: .. | AI18: .. | AJ18: .. | AK18: ..
A19: Property income received | B19: 17739 | C19: 3079 | D19: 4987 | E19: 8699 | F19: 14699 | G19: 57231 | H19: 7529 | I19: 13126 | J19: 19391 | K19: 21184 | L19: 23740 | M19: .. | N19: .. | O19: .. | P19: .. | Q19: .. | R19: .. | S19: .. | T19: .. | U19: .. | V19: .. | W19: .. | X19: .. | Y19: .. | Z19: .. | AA19: .. | AB19: .. | AC19: .. | AD19: .. | AE19: .. | AF19: .. | AG19: .. | AH19: .. | AI19: .. | AJ19: .. | AK19: ..
A20: Less: property income paid | B20: 8011 | C20: 5956 | D20: 6289 | E20: 7470 | F20: 9329 | G20: 11009 | H20: 9109 | I20: 12122 | J20: 11404 | K20: 7426 | L20: 3494 | M20: .. | N20: .. | O20: .. | P20: .. | Q20: .. | R20: .. | S20: .. | T20: .. | U20: .. | V20: .. | W20: .. | X20: .. | Y20: .. | Z20: .. | AA20: .. | AB20: .. | AC20: .. | AD20: .. | AE20: .. | AF20: .. | AG20: .. | AH20: .. | AI20: .. | AJ20: .. | AK20: ..
A21: Current transfers received | B21: 26656 | C21: 26107 | D21: 30786 | E21: 28248 | F21: 24546 | G21: 23596 | H21: 15296 | I21: 18880 | J21: 15711 | K21: 22042 | L21: 46399 | M21: .. | N21: .. | O21: .. | P21: .. | Q21: .. | R21: .. | S21: .. | T21: .. | U21: .. | V21: .. | W21: .. | X21: .. | Y21: .. | Z21: .. | AA21: .. | AB21: .. | AC21: .. | AD21: .. | AE21: .. | AF21: .. | AG21: .. | AH21: .. | AI21: .. | AJ21: .. | AK21: ..
A22: Less: current transfers paid | B22: 44251 | C22: 10330 | D22: 17871 | E22: 33768 | F22: 54126 | G22: 105162 | H22: 40354 | I22: 53350 | J22: 63900 | K22: 55407 | L22: 24649 | M22: .. | N22: .. | O22: .. | P22: .. | Q22: .. | R22: .. | S22: .. | T22: .. | U22: .. | V22: .. | W22: .. | X22: .. | Y22: .. | Z22: .. | AA22: .. | AB22: .. | AC22: .. | AD22: .. | AE22: .. | AF22: .. | AG22: .. | AH22: .. | AI22: .. | AJ22: .. | AK22: ..
A23: Household final consumption expenditure (HFCE) | B23: 93707 | C23: 61968 | D23: 75118 | E23: 91266 | F23: 103168 | G23: 137015 | H23: 88914 | I23: 103075 | J23: 127283 | K23: 107382 | L23: 65742 | M23: 62761 | N23: 63254 | O23: 76767 | P23: 71238 | Q23: 52572 | R23: 81310 | S23: 97176 | T23: 86855 | U23: 84889 | V23: 55746 | W23: 88214 | X23: 99908 | Y23: 126342 | Z23: 93812 | AA23: 68078 | AB23: 88615 | AC23: 112438 | AD23: 135533 | AE23: 114766 | AF23: 72967 | AG23: 128919 | AH23: 131586 | AI23: 183861 | AJ23: 146632 | AK23: 96602
A24: Food and non-alcoholic beverages | B24: 8923 | C24: 6876 | D24: 8272 | E24: 9429 | F24: 10204 | G24: 9834 | H24: 8114 | I24: 10103 | J24: 12186 | K24: 9779 | L24: 6525 | M24: .. | N24: .. | O24: .. | P24: .. | Q24: .. | R24: .. | S24: .. | T24: .. | U24: .. | V24: .. | W24: .. | X24: .. | Y24: .. | Z24: .. | AA24: .. | AB24: .. | AC24: .. | AD24: .. | AE24: .. | AF24: .. | AG24: .. | AH24: .. | AI24: .. | AJ24: .. | AK24: ..
A25: Alcoholic beverages and tobacco | B25: 3051 | C25: 2111 | D25: 2550 | E25: 3275 | F25: 3517 | G25: 3803 | H25: 3011 | I25: 3219 | J25: 4205 | K25: 3821 | L25: 1935 | M25: .. | N25: .. | O25: .. | P25: .. | Q25: .. | R25: .. | S25: .. | T25: .. | U25: .. | V25: .. | W25: .. | X25: .. | Y25: .. | Z25: .. | AA25: .. | AB25: .. | AC25: .. | AD25: .. | AE25: .. | AF25: .. | AG25: .. | AH25: .. | AI25: .. | AJ25: .. | AK25: ..
A26: Clothing and footwear | B26: 4453 | C26: 3130 | D26: 3347 | E26: 4367 | F26: 4578 | G26: 6843 | H26: 5100 | I26: 5856 | J26: 6389 | K26: 4688 | L26: 2084 | M26: .. | N26: .. | O26: .. | P26: .. | Q26: .. | R26: .. | S26: .. | T26: .. | U26: .. | V26: .. | W26: .. | X26: .. | Y26: .. | Z26: .. | AA26: .. | AB26: .. | AC26: .. | AD26: .. | AE26: .. | AF26: .. | AG26: .. | AH26: .. | AI26: .. | AJ26: .. | AK26: ..
A27: Housing, water, electricity, gas and other fuels | B27: 22097 | C27: 15022 | D27: 18068 | E27: 21737 | F27: 23350 | G27: 32310 | H27: 21725 | I27: 22619 | J27: 28118 | K27: 25443 | L27: 16966 | M27: .. | N27: .. | O27: .. | P27: .. | Q27: .. | R27: .. | S27: .. | T27: .. | U27: .. | V27: .. | W27: .. | X27: .. | Y27: .. | Z27: .. | AA27: .. | AB27: .. | AC27: .. | AD27: .. | AE27: .. | AF27: .. | AG27: .. | AH27: .. | AI27: .. | AJ27: .. | AK27: ..
A28: Furnishings, household equipment and other goods and services related to the dwelling and property | B28: 5615 | C28: 3419 | D28: 4274 | E28: 5271 | F28: 5830 | G28: 9279 | H28: 5219 | I28: 6662 | J28: 7381 | K28: 6732 | L28: 3669 | M28: .. | N28: .. | O28: .. | P28: .. | Q28: .. | R28: .. | S28: .. | T28: .. | U28: .. | V28: .. | W28: .. | X28: .. | Y28: .. | Z28: .. | AA28: .. | AB28: .. | AC28: .. | AD28: .. | AE28: .. | AF28: .. | AG28: .. | AH28: .. | AI28: .. | AJ28: .. | AK28: ..
A29: Health | B29: 3989 | C29: 2282 | D29: 3261 | E29: 4163 | F29: 4033 | G29: 6204 | H29: 2249 | I29: 2911 | J29: 4491 | K29: 5520 | L29: 4528 | M29: .. | N29: .. | O29: .. | P29: .. | Q29: .. | R29: .. | S29: .. | T29: .. | U29: .. | V29: .. | W29: .. | X29: .. | Y29: .. | Z29: .. | AA29: .. | AB29: .. | AC29: .. | AD29: .. | AE29: .. | AF29: .. | AG29: .. | AH29: .. | AI29: .. | AJ29: .. | AK29: ..
A30: Transport | B30: 14677 | C30: 9932 | D30: 12502 | E30: 13747 | F30: 16550 | G30: 20654 | H30: 14296 | I30: 17377 | J30: 22737 | K30: 15726 | L30: 8524 | M30: .. | N30: .. | O30: .. | P30: .. | Q30: .. | R30: .. | S30: .. | T30: .. | U30: .. | V30: .. | W30: .. | X30: .. | Y30: .. | Z30: .. | AA30: .. | AB30: .. | AC30: .. | AD30: .. | AE30: .. | AF30: .. | AG30: .. | AH30: .. | AI30: .. | AJ30: .. | AK30: ..
A31: Communications | B31: 2368 | C31: 1877 | D31: 2109 | E31: 2425 | F31: 2675 | G31: 2756 | H31: 2565 | I31: 2615 | J31: 3100 | K31: 2655 | L31: 1559 | M31: .. | N31: .. | O31: .. | P31: .. | Q31: .. | R31: .. | S31: .. | T31: .. | U31: .. | V31: .. | W31: .. | X31: .. | Y31: .. | Z31: .. | AA31: .. | AB31: .. | AC31: .. | AD31: .. | AE31: .. | AF31: .. | AG31: .. | AH31: .. | AI31: .. | AJ31: .. | AK31: ..
A32: Recreation and culture | B32: 8108 | C32: 5653 | D32: 6010 | E32: 7524 | F32: 9373 | G32: 11979 | H32: 7401 | I32: 10014 | J32: 10935 | K32: 9739 | L32: 4999 | M32: .. | N32: .. | O32: .. | P32: .. | Q32: .. | R32: .. | S32: .. | T32: .. | U32: .. | V32: .. | W32: .. | X32: .. | Y32: .. | Z32: .. | AA32: .. | AB32: .. | AC32: .. | AD32: .. | AE32: .. | AF32: .. | AG32: .. | AH32: .. | AI32: .. | AJ32: .. | AK32: ..
A33: Education | B33: 1197 | C33: 1223 | D33: 708 | E33: 906 | F33: 1139 | G33: 2011 | H33: 1779 | I33: 1156 | J33: 2571 | K33: 1343 | L33: 75 | M33: .. | N33: .. | O33: .. | P33: .. | Q33: .. | R33: .. | S33: .. | T33: .. | U33: .. | V33: .. | W33: .. | X33: .. | Y33: .. | Z33: .. | AA33: .. | AB33: .. | AC33: .. | AD33: .. | AE33: .. | AF33: .. | AG33: .. | AH33: .. | AI33: .. | AJ33: .. | AK33: ..
A34: Food, beverage and accommodation services | B34: 7023 | C34: 1508 | D34: 4165 | E34: 6765 | F34: 8654 | G34: 14023 | H34: 6081 | I34: 7700 | J34: 10452 | K34: 9113 | L34: 4208 | M34: .. | N34: .. | O34: .. | P34: .. | Q34: .. | R34: .. | S34: .. | T34: .. | U34: .. | V34: .. | W34: .. | X34: .. | Y34: .. | Z34: .. | AA34: .. | AB34: .. | AC34: .. | AD34: .. | AE34: .. | AF34: .. | AG34: .. | AH34: .. | AI34: .. | AJ34: .. | AK34: ..
A35: Insurance and financial services | B35: 7305 | C35: 5124 | D35: 5453 | E35: 6858 | F35: 7657 | G35: 11433 | H35: 6613 | I35: 7170 | J35: 9613 | K35: 8475 | L35: 5934 | M35: .. | N35: .. | O35: .. | P35: .. | Q35: .. | R35: .. | S35: .. | T35: .. | U35: .. | V35: .. | W35: .. | X35: .. | Y35: .. | Z35: .. | AA35: .. | AB35: .. | AC35: .. | AD35: .. | AE35: .. | AF35: .. | AG35: .. | AH35: .. | AI35: .. | AJ35: .. | AK35: ..
... A38: Household net saving | B38: 5342 | C38: -30984 | D38: -17105 | E38: -11380 | F38: 17517 | G38: 68660 | H38: 18173 | I38: 22507 | J38: 16522 | K38: -2654 | L38: -13756 | M38: .. | N38: .. | O38: .. | P38: .. | Q38: .. | R38: .. | S38: .. | T38: .. | U38: .. | V38: .. | W38: .. | X38: .. | Y38: .. | Z38: .. | AA38: .. | AB38: .. | AC38: .. | AD38: .. | AE38: .. | AF38: .. | AG38: .. | AH38: .. | AI38: .. | AJ38: .. | AK38: ..
A40: Symbol legend:
A41: .. | B41: not available for a specific reference period
A46: Footnotes:
A47: 1 | B47: Income quintiles are assigned based on equivalized household disposable income, which takes into account differences in household size and composition using a method proposed by the Organization for Economic Co-operation and Development (OECD). The OECD-modified" equivalence scale assigns a value of 1 to the first adult | C47: 0.5 to each additional person aged 14 and over | D47: and 0.3 for all children under 14."
A48: 2 | B48: Age groups refer to the age group of the major income earner.
A52: How to cite: Statistics Canada. Table 36-10-0587-01 Distributions of household economic accounts, income, consumption and saving, by characteristic, annual (x 1,000,000)
A53: https://www150.statcan.gc.ca/t1/tbl1/en/tv.action?pid=3610058701

Sheet Under 35 per HH Over Time
A1: Distributions of household economic accounts, income, consumption and saving, by characteristic, annual
A2: Frequency: Annual
A3: Table: 36-10-0587-01 (formerly CANSIM 378-0152)
A4: Release date: 2024-07-17
A5: Geography: Canada
A6: https://www150.statcan.gc.ca/t1/tbl1/en/cv!recreate.action?pid=3610058701&selectedNodeIds=2D3,3D22,3D42,4D1,4D2,4D3,4D4,4D5,4D6,4D7,4D8,4D9,4D10,4D11,4D12,4D13,4D14,4D15,4D16,4D17,4D18,4D19,4D20,4D21,4D22,4D23&checkedLevels=0D1&refPeriods=19990101,20230101&dimensionLayouts=layout2,layout2,layout2,layout3,layout2&vectorDisplay=false
A9: Geography | B9: Canada
A10: Statistics | B10: Value per household
A11: Characteristics | B11: Lowest income quintile, less than 35 years 1 2 | AA11: Highest income quintile, less than 35 years 1 2
A12: Income, consumption and savings | B12: 1999 | C12: 2000 | D12: 2001 | E12: 2002 | F12: 2003 | G12: 2004 | H12: 2005 | I12: 2006 | J12: 2007 | K12: 2008 | L12: 2009 | M12: 2010 | N12: 2011 | O12: 2012 | P12: 2013 | Q12: 2014 | R12: 2015 | S12: 2016 | T12: 2017 | U12: 2018 | V12: 2019 | W12: 2020 | X12: 2021 | Y12: 2022 | Z12: 2023 | AA12: 1999 | AB12: 2000 | AC12: 2001 | AD12: 2002 | AE12: 2003 | AF12: 2004 | AG12: 2005 | AH12: 2006 | AI12: 2007 | AJ12: 2008 | AK12: 2009 | AL12: 2010 | AM12: 2011 | AN12: 2012 | AO12: 2013 | AP12: 2014 | AQ12: 2015 | AR12: 2016 | AS12: 2017 | AT12: 2018 | AU12: 2019 | AV12: 2020 | AW12: 2021 | AX12: 2022 | AY12: 2023
B13: Dollars
A14: Household disposable income | B14: 14002 | C14: 14089 | D14: 14590 | E14: 14976 | F14: 15216 | G14: 16089 | H14: 15822 | I14: 17790 | J14: 18792 | K14: 20538 | L14: 18743 | M14: 20478 | N14: 22799 | O14: 21988 | P14: 21618 | Q14: 24945 | R14: 23185 | S14: 25297 | T14: 26845 | U14: 28147 | V14: 27995 | W14: 33616 | X14: 33595 | Y14: 33401 | Z14: 32144 | AA14: 82093 | AB14: 85719 | AC14: 86051 | AD14: 88957 | AE14: 88944 | AF14: 93273 | AG14: 100011 | AH14: 98445 | AI14: 105455 | AJ14: 106598 | AK14: 114417 | AL14: 112246 | AM14: 114151 | AN14: 123692 | AO14: 117129 | AP14: 130009 | AQ14: 128439 | AR14: 131995 | AS14: 136602 | AT14: 138373 | AU14: 146252 | AV14: 153590 | AW14: 177792 | AX14: 193694 | AY14: 182418
A15: Compensation of employees | B15: .. | C15: .. | D15: .. | E15: .. | F15: .. | G15: .. | H15: .. | I15: .. | J15: .. | K15: .. | L15: .. | M15: .. | N15: .. | O15: .. | P15: .. | Q15: .. | R15: .. | S15: .. | T15: .. | U15: .. | V15: .. | W15: .. | X15: .. | Y15: .. | Z15: .. | AA15: .. | AB15: .. | AC15: .. | AD15: .. | AE15: .. | AF15: .. | AG15: .. | AH15: .. | AI15: .. | AJ15: .. | AK15: .. | AL15: .. | AM15: .. | AN15: .. | AO15: .. | AP15: .. | AQ15: .. | AR15: .. | AS15: .. | AT15: .. | AU15: .. | AV15: .. | AW15: .. | AX15: .. | AY15: ..
A16: Net mixed income | B16: .. | C16: .. | D16: .. | E16: .. | F16: .. | G16: .. | H16: .. | I16: .. | J16: .. | K16: .. | L16: .. | M16: .. | N16: .. | O16: .. | P16: .. | Q16: .. | R16: .. | S16: .. | T16: .. | U16: .. | V16: .. | W16: .. | X16: .. | Y16: .. | Z16: .. | AA16: .. | AB16: .. | AC16: .. | AD16: .. | AE16: .. | AF16: .. | AG16: .. | AH16: .. | AI16: .. | AJ16: .. | AK16: .. | AL16: .. | AM16: .. | AN16: .. | AO16: .. | AP16: .. | AQ16: .. | AR16: .. | AS16: .. | AT16: .. | AU16: .. | AV16: .. | AW16: .. | AX16: .. | AY16: ..
A17: Property income received | B17: .. | C17: .. | D17: .. | E17: .. | F17: .. | G17: .. | H17: .. | I17: .. | J17: .. | K17: .. | L17: .. | M17: .. | N17: .. | O17: .. | P17: .. | Q17: .. | R17: .. | S17: .. | T17: .. | U17: .. | V17: .. | W17: .. | X17: .. | Y17: .. | Z17: .. | AA17: .. | AB17: .. | AC17: .. | AD17: .. | AE17: .. | AF17: .. | AG17: .. | AH17: .. | AI17: .. | AJ17: .. | AK17: .. | AL17: .. | AM17: .. | AN17: .. | AO17: .. | AP17: .. | AQ17: .. | AR17: .. | AS17: .. | AT17: .. | AU17: .. | AV17: .. | AW17: .. | AX17: .. | AY17: ..
A18: Less: property income paid | B18: .. | C18: .. | D18: .. | E18: .. | F18: .. | G18: .. | H18: .. | I18: .. | J18: .. | K18: .. | L18: .. | M18: .. | N18: .. | O18: .. | P18: .. | Q18: .. | R18: .. | S18: .. | T18: .. | U18: .. | V18: .. | W18: .. | X18: .. | Y18: .. | Z18: .. | AA18: .. | AB18: .. | AC18: .. | AD18: .. | AE18: .. | AF18: .. | AG18: .. | AH18: .. | AI18: .. | AJ18: .. | AK18: .. | AL18: .. | AM18: .. | AN18: .. | AO18: .. | AP18: .. | AQ18: .. | AR18: .. | AS18: .. | AT18: .. | AU18: .. | AV18: .. | AW18: .. | AX18: .. | AY18: ..
A19: Current transfers received | B19: .. | C19: .. | D19: .. | E19: .. | F19: .. | G19: .. | H19: .. | I19: .. | J19: .. | K19: .. | L19: .. | M19: .. | N19: .. | O19: .. | P19: .. | Q19: .. | R19: .. | S19: .. | T19: .. | U19: .. | V19: .. | W19: .. | X19: .. | Y19: .. | Z19: .. | AA19: .. | AB19: .. | AC19: .. | AD19: .. | AE19: .. | AF19: .. | AG19: .. | AH19: .. | AI19: .. | AJ19: .. | AK19: .. | AL19: .. | AM19: .. | AN19: .. | AO19: .. | AP19: .. | AQ19: .. | AR19: .. | AS19: .. | AT19: .. | AU19: .. | AV19: .. | AW19: .. | AX19: .. | AY19: ..
A20: Less: current transfers paid | B20: .. | C20: .. | D20: .. | E20: .. | F20: .. | G20: .. | H20: .. | I20: .. | J20: .. | K20: .. | L20: .. | M20: .. | N20: .. | O20: .. | P20: .. | Q20: .. | R20: .. | S20: .. | T20: .. | U20: .. | V20: .. | W20: .. | X20: .. | Y20: .. | Z20: .. | AA20: .. | AB20: .. | AC20: .. | AD20: .. | AE20: .. | AF20: .. | AG20: .. | AH20: .. | AI20: .. | AJ20: .. | AK20: .. | AL20: .. | AM20: .. | AN20: .. | AO20: .. | AP20: .. | AQ20: .. | AR20: .. | AS20: .. | AT20: .. | AU20: .. | AV20: .. | AW20: .. | AX20: .. | AY20: ..
A21: Household final consumption expenditure (HFCE) | B21: 21246 | C21: 23543 | D21: 23106 | E21: 25293 | F21: 25826 | G21: 27761 | H21: 30538 | I21: 35167 | J21: 37357 | K21: 36879 | L21: 36159 | M21: 36744 | N21: 40049 | O21: 39771 | P21: 42315 | Q21: 47887 | R21: 42974 | S21: 48049 | T21: 50726 | U21: 53374 | V21: 59276 | W21: 49864 | X21: 58354 | Y21: 61225 | Z21: 62761 | AA21: 69707 | AB21: 68117 | AC21: 66937 | AD21: 69533 | AE21: 70861 | AF21: 72890 | AG21: 81337 | AH21: 80414 | AI21: 83908 | AJ21: 84936 | AK21: 82011 | AL21: 83616 | AM21: 87750 | AN21: 91641 | AO21: 99946 | AP21: 105413 | AQ21: 101901 | AR21: 107483 | AS21: 110657 | AT21: 111995 | AU21: 102043 | AV21: 110523 | AW21: 118742 | AX21: 125889 | AY21: 128919
A22: Food and non-alcoholic beverages | B22: .. | C22: .. | D22: .. | E22: .. | F22: .. | G22: .. | H22: .. | I22: .. | J22: .. | K22: .. | L22: .. | M22: .. | N22: .. | O22: .. | P22: .. | Q22: .. | R22: .. | S22: .. | T22: .. | U22: .. | V22: .. | W22: .. | X22: .. | Y22: .. | Z22: .. | AA22: .. | AB22: .. | AC22: .. | AD22: .. | AE22: .. | AF22: .. | AG22: .. | AH22: .. | AI22: .. | AJ22: .. | AK22: .. | AL22: .. | AM22: .. | AN22: .. | AO22: .. | AP22: .. | AQ22: .. | AR22: .. | AS22: .. | AT22: .. | AU22: .. | AV22: .. | AW22: .. | AX22: .. | AY22: ..
A23: Alcoholic beverages and tobacco | B23: .. | C23: .. | D23: .. | E23: .. | F23: .. | G23: .. | H23: .. | I23: .. | J23: .. | K23: .. | L23: .. | M23: .. | N23: .. | O23: .. | P23: .. | Q23: .. | R23: .. | S23: .. | T23: .. | U23: .. | V23: .. | W23: .. | X23: .. | Y23: .. | Z23: .. | AA23: .. | AB23: .. | AC23: .. | AD23: .. | AE23: .. | AF23: .. | AG23: .. | AH23: .. | AI23: .. | AJ23: .. | AK23: .. | AL23: .. | AM23: .. | AN23: .. | AO23: .. | AP23: .. | AQ23: .. | AR23: .. | AS23: .. | AT23: .. | AU23: .. | AV23: .. | AW23: .. | AX23: .. | AY23: ..
A24: Clothing and footwear | B24: .. | C24: .. | D24: .. | E24: .. | F24: .. | G24: .. | H24: .. | I24: .. | J24: .. | K24: .. | L24: .. | M24: .. | N24: .. | O24: .. | P24: .. | Q24: .. | R24: .. | S24: .. | T24: .. | U24: .. | V24: .. | W24: .. | X24: .. | Y24: .. | Z24: .. | AA24: .. | AB24: .. | AC24: .. | AD24: .. | AE24: .. | AF24: .. | AG24: .. | AH24: .. | AI24: .. | AJ24: .. | AK24: .. | AL24: .. | AM24: .. | AN24: .. | AO24: .. | AP24: .. | AQ24: .. | AR24: .. | AS24: .. | AT24: .. | AU24: .. | AV24: .. | AW24: .. | AX24: .. | AY24: ..
A25: Housing, water, electricity, gas and other fuels | B25: .. | C25: .. | D25: .. | E25: .. | F25: .. | G25: .. | H25: .. | I25: .. | J25: .. | K25: .. | L25: .. | M25: .. | N25: .. | O25: .. | P25: .. | Q25: .. | R25: .. | S25: .. | T25: .. | U25: .. | V25: .. | W25: .. | X25: .. | Y25: .. | Z25: .. | AA25: .. | AB25: .. | AC25: .. | AD25: .. | AE25: .. | AF25: .. | AG25: .. | AH25: .. | AI25: .. | AJ25: .. | AK25: .. | AL25: .. | AM25: .. | AN25: .. | AO25: .. | AP25: .. | AQ25: .. | AR25: .. | AS25: .. | AT25: .. | AU25: .. | AV25: .. | AW25: .. | AX25: .. | AY25: ..
A26: Furnishings, household equipment and other goods and services related to the dwelling and property | B26: .. | C26: .. | D26: .. | E26: .. | F26: .. | G26: .. | H26: .. | I26: .. | J26: .. | K26: .. | L26: .. | M26: .. | N26: .. | O26: .. | P26: .. | Q26: .. | R26: .. | S26: .. | T26: .. | U26: .. | V26: .. | W26: .. | X26: .. | Y26: .. | Z26: .. | AA26: .. | AB26: .. | AC26: .. | AD26: .. | AE26: .. | AF26: .. | AG26: .. | AH26: .. | AI26: .. | AJ26: .. | AK26: .. | AL26: .. | AM26: .. | AN26: .. | AO26: .. | AP26: .. | AQ26: .. | AR26: .. | AS26: .. | AT26: .. | AU26: .. | AV26: .. | AW26: .. | AX26: .. | AY26: ..
A27: Health | B27: .. | C27: .. | D27: .. | E27: .. | F27: .. | G27: .. | H27: .. | I27: .. | J27: .. | K27: .. | L27: .. | M27: .. | N27: .. | O27: .. | P27: .. | Q27: .. | R27: .. | S27: .. | T27: .. | U27: .. | V27: .. | W27: .. | X27: .. | Y27: .. | Z27: .. | AA27: .. | AB27: .. | AC27: .. | AD27: .. | AE27: .. | AF27: .. | AG27: .. | AH27: .. | AI27: .. | AJ27: .. | AK27: .. | AL27: .. | AM27: .. | AN27: .. | AO27: .. | AP27: .. | AQ27: .. | AR27: .. | AS27: .. | AT27: .. | AU27: .. | AV27: .. | AW27: .. | AX27: .. | AY27: ..
A28: Transport | B28: .. | C28: .. | D28: .. | E28: .. | F28: .. | G28: .. | H28: .. | I28: .. | J28: .. | K28: .. | L28: .. | M28: .. | N28: .. | O28: .. | P28: .. | Q28: .. | R28: .. | S28: .. | T28: .. | U28: .. | V28: .. | W28: .. | X28: .. | Y28: .. | Z28: .. | AA28: .. | AB28: .. | AC28: .. | AD28: .. | AE28: .. | AF28: .. | AG28: .. | AH28: .. | AI28: .. | AJ28: .. | AK28: .. | AL28: .. | AM28: .. | AN28: .. | AO28: .. | AP28: .. | AQ28: .. | AR28: .. | AS28: .. | AT28: .. | AU28: .. | AV28: .. | AW28: .. | AX28: .. | AY28: ..
A29: Communications | B29: .. | C29: .. | D29: .. | E29: .. | F29: .. | G29: .. | H29: .. | I29: .. | J29: .. | K29: .. | L29: .. | M29: .. | N29: .. | O29: .. | P29: .. | Q29: .. | R29: .. | S29: .. | T29: .. | U29: .. | V29: .. | W29: .. | X29: .. | Y29: .. | Z29: .. | AA29: .. | AB29: .. | AC29: .. | AD29: .. | AE29: .. | AF29: .. | AG29: .. | AH29: .. | AI29: .. | AJ29: .. | AK29: .. | AL29: .. | AM29: .. | AN29: .. | AO29: .. | AP29: .. | AQ29: .. | AR29: .. | AS29: .. | AT29: .. | AU29: .. | AV29: .. | AW29: .. | AX29: .. | AY29: ..
A30: Recreation and culture | B30: .. | C30: .. | D30: .. | E30: .. | F30: .. | G30: .. | H30: .. | I30: .. | J30: .. | K30: .. | L30: .. | M30: .. | N30: .. | O30: .. | P30: .. | Q30: .. | R30: .. | S30: .. | T30: .. | U30: .. | V30: .. | W30: .. | X30: .. | Y30: .. | Z30: .. | AA30: .. | AB30: .. | AC30: .. | AD30: .. | AE30: .. | AF30: .. | AG30: .. | AH30: .. | AI30: .. | AJ30: .. | AK30: .. | AL30: .. | AM30: .. | AN30: .. | AO30: .. | AP30: .. | AQ30: .. | AR30: .. | AS30: .. | AT30: .. | AU30: .. | AV30: .. | AW30: .. | AX30: .. | AY30: ..
A31: Education | B31: .. | C31: .. | D31: .. | E31: .. | F31: .. | G31: .. | H31: .. | I31: .. | J31: .. | K31: .. | L31: .. | M31: .. | N31: .. | O31: .. | P31: .. | Q31: .. | R31: .. | S31: .. | T31: .. | U31: .. | V31: .. | W31: .. | X31: .. | Y31: .. | Z31: .. | AA31: .. | AB31: .. | AC31: .. | AD31: .. | AE31: .. | AF31: .. | AG31: .. | AH31: .. | AI31: .. | AJ31: .. | AK31: .. | AL31: .. | AM31: .. | AN31: .. | AO31: .. | AP31: .. | AQ31: .. | AR31: .. | AS31: .. | AT31: .. | AU31: .. | AV31: .. | AW31: .. | AX31: .. | AY31: ..
A32: Food, beverage and accommodation services | B32: .. | C32: .. | D32: .. | E32: .. | F32: .. | G32: .. | H32: .. | I32: .. | J32: .. | K32: .. | L32: .. | M32: .. | N32: .. | O32: .. | P32: .. | Q32: .. | R32: .. | S32: .. | T32: .. | U32: .. | V32: .. | W32: .. | X32: .. | Y32: .. | Z32: .. | AA32: .. | AB32: .. | AC32: .. | AD32: .. | AE32: .. | AF32: .. | AG32: .. | AH32: .. | AI32: .. | AJ32: .. | AK32: .. | AL32: .. | AM32: .. | AN32: .. | AO32: .. | AP32: .. | AQ32: .. | AR32: .. | AS32: .. | AT32: .. | AU32: .. | AV32: .. | AW32: .. | AX32: .. | AY32: ..
A33: Insurance and financial services | B33: .. | C33: .. | D33: .. | E33: .. | F33: .. | G33: .. | H33: .. | I33: .. | J33: .. | K33: .. | L33: .. | M33: .. | N33: .. | O33: .. | P33: .. | Q33: .. | R33: .. | S33: .. | T33: .. | U33: .. | V33: .. | W33: .. | X33: .. | Y33: .. | Z33: .. | AA33: .. | AB33: .. | AC33: .. | AD33: .. | AE33: .. | AF33: .. | AG33: .. | AH33: .. | AI33: .. | AJ33: .. | AK33: .. | AL33: .. | AM33: .. | AN33: .. | AO33: .. | AP33: .. | AQ33: .. | AR33: .. | AS33: .. | AT33: .. | AU33: .. | AV33: .. | AW33: .. | AX33: .. | AY33: ..
... A36: Household net saving | B36: .. | C36: .. | D36: .. | E36: .. | F36: .. | G36: .. | H36: .. | I36: .. | J36: .. | K36: .. | L36: .. | M36: .. | N36: .. | O36: .. | P36: .. | Q36: .. | R36: .. | S36: .. | T36: .. | U36: .. | V36: .. | W36: .. | X36: .. | Y36: .. | Z36: .. | AA36: .. | AB36: .. | AC36: .. | AD36: .. | AE36: .. | AF36: .. | AG36: .. | AH36: .. | AI36: .. | AJ36: .. | AK36: .. | AL36: .. | AM36: .. | AN36: .. | AO36: .. | AP36: .. | AQ36: .. | AR36: .. | AS36: .. | AT36: .. | AU36: .. | AV36: .. | AW36: .. | AX36: .. | AY36: ..
A38: Symbol legend:
A39: .. | B39: not available for a specific reference period
A44: Footnotes:
A45: 1 | B45: Income quintiles are assigned based on equivalized household disposable income, which takes into account differences in household size and composition using a method proposed by the Organization for Economic Co-operation and Development (OECD). The OECD-modified" equivalence scale assigns a value of 1 to the first adult | C45: 0.5 to each additional person aged 14 and over | D45: and 0.3 for all children under 14."
A46: 2 | B46: Age groups refer to the age group of the major income earner.
A50: How to cite: Statistics Canada. Table 36-10-0587-01 Distributions of household economic accounts, income, consumption and saving, by characteristic, annual (x 1,000,000)
A51: https://www150.statcan.gc.ca/t1/tbl1/en/tv.action?pid=3610058701

Sheet All Ages Over Time Data
A1: Distributions of household economic accounts, income, consumption and saving, by characteristic, annual
A2: Frequency: Annual
A3: Table: 36-10-0587-01 (formerly CANSIM 378-0152)
A4: Release date: 2024-07-17
A5: Geography: Canada
A6: https://www150.statcan.gc.ca/t1/tbl1/en/cv!recreate.action?pid=3610058701&selectedNodeIds=2D3,3D2,3D3,3D4,3D5,3D6,4D1,4D2,4D3,4D4,4D5,4D6,4D7,4D8,4D9,4D10,4D11,4D12,4D13,4D14,4D15,4D16,4D17,4D18,4D19,4D20,4D21,4D22,4D23&checkedLevels=0D1&refPeriods=19990101,20230101&dimensionLayouts=layout2,layout2,layout2,layout3,layout2&vectorDisplay=false
A9: Geography | B9: Canada
A10: Statistics | B10: Value per household
A11: Characteristics | B11: Lowest income quintile 1 | AA11: Second income quintile 1 | AZ11: Third income quintile 1 | BY11: Fourth income quintile 1 | CX11: Highest income quintile 1
A12: Income, consumption and savings | B12: 1999 | C12: 2000 | D12: 2001 | E12: 2002 | F12: 2003 | G12: 2004 | H12: 2005 | I12: 2006 | J12: 2007 | K12: 2008 | L12: 2009 | M12: 2010 | N12: 2011 | O12: 2012 | P12: 2013 | Q12: 2014 | R12: 2015 | S12: 2016 | T12: 2017 | U12: 2018 | V12: 2019 | W12: 2020 | X12: 2021 | Y12: 2022 | Z12: 2023 | AA12: 1999 | AB12: 2000 | AC12: 2001 | AD12: 2002 | AE12: 2003 | AF12: 2004 | AG12: 2005 | AH12: 2006 | AI12: 2007 | AJ12: 2008 | AK12: 2009 | AL12: 2010 | AM12: 2011 | AN12: 2012 | AO12: 2013 | AP12: 2014 | AQ12: 2015 | AR12: 2016 | AS12: 2017 | AT12: 2018 | AU12: 2019 | AV12: 2020 | AW12: 2021 | AX12: 2022 | AY12: 2023 | AZ12: 1999 | BA12: 2000 | BB12: 2001 | BC12: 2002 | BD12: 2003 | BE12: 2004 | BF12: 2005 | BG12: 2006 | BH12: 2007 | BI12: 2008 | BJ12: 2009 | BK12: 2010 | BL12: 2011 | BM12: 2012 | BN12: 2013 | BO12: 2014 | BP12: 2015 | BQ12: 2016 | BR12: 2017 | BS12: 2018 | BT12: 2019 | BU12: 2020 | BV12: 2021 | BW12: 2022 | BX12: 2023 | BY12: 1999 | BZ12: 2000 | CA12: 2001 | CB12: 2002 | CC12: 2003 | CD12: 2004 | CE12: 2005 | CF12: 2006 | CG12: 2007 | CH12: 2008 | CI12: 2009 | CJ12: 2010 | CK12: 2011 | CL12: 2012 | CM12: 2013 | CN12: 2014 | CO12: 2015 | CP12: 2016 | CQ12: 2017 | CR12: 2018 | CS12: 2019 | CT12: 2020 | CU12: 2021 | CV12: 2022 | CW12: 2023 | CX12: 1999 | CY12: 2000 | CZ12: 2001 | DA12: 2002 | DB12: 2003 | DC12: 2004 | DD12: 2005 | DE12: 2006 | DF12: 2007 | DG12: 2008 | DH12: 2009 | DI12: 2010 | DJ12: 2011 | DK12: 2012 | DL12: 2013 | DM12: 2014 | DN12: 2015 | DO12: 2016 | DP12: 2017 | DQ12: 2018 | DR12: 2019 | DS12: 2020 | DT12: 2021 | DU12: 2022 | DV12: 2023
B13: Dollars
A14: Household disposable income | B14: 14555 | C14: 14731 | D14: 15985 | E14: 16110 | F14: 16719 | G14: 16792 | H14: 16468 | I14: 18060 | J14: 19253 | K14: 19564 | L14: 20329 | M14: 21011 | N14: 21689 | O14: 23097 | P14: 22766 | Q14: 23215 | R14: 22867 | S14: 23637 | T14: 24025 | U14: 24888 | V14: 25566 | W14: 32930 | X14: 32346 | Y14: 31425 | Z14: 31604 | AA14: 28992 | AB14: 29772 | AC14: 31982 | AD14: 32572 | AE14: 32696 | AF14: 33458 | AG14: 34434 | AH14: 36489 | AI14: 38561 | AJ14: 39547 | AK14: 40208 | AL14: 42145 | AM14: 41886 | AN14: 44208 | AO14: 44566 | AP14: 45820 | AQ14: 47441 | AR14: 50267 | AS14: 50793 | AT14: 50870 | AU14: 51863 | AV14: 61111 | AW14: 60047 | AX14: 59345 | AY14: 59447 | AZ14: 40456 | BA14: 41187 | BB14: 42930 | BC14: 43409 | BD14: 44902 | BE14: 45754 | BF14: 46857 | BG14: 49509 | BH14: 50906 | BI14: 53477 | BJ14: 54206 | BK14: 57421 | BL14: 58051 | BM14: 59535 | BN14: 61727 | BO14: 62807 | BP14: 67701 | BQ14: 67952 | BR14: 68777 | BS14: 69381 | BT14: 71067 | BU14: 77443 | BV14: 78610 | BW14: 78188 | BX14: 78998 | BY14: 53967 | BZ14: 55257 | CA14: 57948 | CB14: 60528 | CC14: 60636 | CD14: 62590 | CE14: 64135 | CF14: 66336 | CG14: 68644 | CH14: 72288 | CI14: 73812 | CJ14: 77552 | CK14: 79990 | CL14: 81776 | CM14: 84751 | CN14: 87126 | CO14: 89151 | CP14: 88735 | CQ14: 91976 | CR14: 93084 | CS14: 95255 | CT14: 103347 | CU14: 110037 | CV14: 110849 | CW14: 114315 | CX14: 92502 | CY14: 99880 | CZ14: 102327 | DA14: 105850 | DB14: 108511 | DC14: 113861 | DD14: 117390 | DE14: 125058 | DF14: 129776 | DG14: 134548 | DH14: 135318 | DI14: 137421 | DJ14: 140240 | DK14: 143724 | DL14: 150019 | DM14: 152757 | DN14: 158829 | DO14: 152305 | DP14: 158796 | DQ14: 159751 | DR14: 165093 | DS14: 165803 | DT14: 175908 | DU14: 186643 | DV14: 197667
A15: Compensation of employees | B15: 6789 | C15: 7208 | D15: 7359 | E15: 7017 | F15: 7308 | G15: 7607 | H15: 7405 | I15: 8446 | J15: 9305 | K15: 9517 | L15: 8807 | M15: 8600 | N15: 9299 | O15: 10093 | P15: 10120 | Q15: 9602 | R15: 9554 | S15: 9539 | T15: 9664 | U15: 10555 | V15: 10835 | W15: 8886 | X15: 11303 | Y15: 11062 | Z15: 13234 | AA15: 19041 | AB15: 20608 | AC15: 21782 | AD15: 21540 | AE15: 21223 | AF15: 21376 | AG15: 22504 | AH15: 24999 | AI15: 26705 | AJ15: 28042 | AK15: 26328 | AL15: 26835 | AM15: 26998 | AN15: 29572 | AO15: 29246 | AP15: 30613 | AQ15: 31702 | AR15: 34011 | AS15: 33071 | AT15: 32501 | AU15: 33007 | AV15: 31418 | AW15: 35605 | AX15: 36358 | AY15: 37027 | AZ15: 36237 | BA15: 37042 | BB15: 38846 | BC15: 37283 | BD15: 40296 | BE15: 40734 | BF15: 42963 | BG15: 45292 | BH15: 47035 | BI15: 50024 | BJ15: 48714 | BK15: 50822 | BL15: 51926 | BM15: 53712 | BN15: 55141 | BO15: 55779 | BP15: 60358 | BQ15: 59008 | BR15: 58552 | BS15: 59296 | BT15: 60701 | BU15: 59775 | BV15: 64976 | BW15: 68540 | BX15: 69679 | BY15: 57463 | BZ15: 59613 | CA15: 61433 | CB15: 64069 | CC15: 64523 | CD15: 67632 | CE15: 69865 | CF15: 72057 | CG15: 74442 | CH15: 76888 | CI15: 77020 | CJ15: 79428 | CK15: 83614 | CL15: 86113 | CM15: 88972 | CN15: 91471 | CO15: 91410 | CP15: 91003 | CQ15: 94017 | CR15: 96715 | CS15: 99653 | CT15: 98747 | CU15: 106960 | CV15: 113837 | CW15: 120934 | CX15: 94301 | CY15: 104631 | CZ15: 105011 | DA15: 110137 | DB15: 113176 | DC15: 119790 | DD15: 125361 | DE15: 130519 | DF15: 136952 | DG15: 138546 | DH15: 135833 | DI15: 136547 | DJ15: 141253 | DK15: 144783 | DL15: 149901 | DM15: 154909 | DN15: 157049 | DO15: 152619 | DP15: 158331 | DQ15: 165569 | DR15: 168959 | DS15: 168197 | DT15: 183550 | DU15: 195306 | DV15: 202784
A16: Net mixed income | B16: 2329 | C16: 2562 | D16: 2388 | E16: 2646 | F16: 2856 | G16: 2793 | H16: 2820 | I16: 3387 | J16: 3316 | K16: 3241 | L16: 3288 | M16: 3441 | N16: 3298 | O16: 3255 | P16: 3221 | Q16: 3633 | R16: 3269 | S16: 3859 | T16: 4068 | U16: 4362 | V16: 4600 | W16: 4436 | X16: 4758 | Y16: 5244 | Z16: 5471 | AA16: 4801 | AB16: 4994 | AC16: 5280 | AD16: 5312 | AE16: 5366 | AF16: 5553 | AG16: 5634 | AH16: 5616 | AI16: 6428 | AJ16: 5942 | AK16: 6146 | AL16: 7096 | AM16: 6702 | AN16: 7151 | AO16: 7139 | AP16: 7598 | AQ16: 7772 | AR16: 8460 | AS16: 8773 | AT16: 9126 | AU16: 9389 | AV16: 8685 | AW16: 9095 | AX16: 10122 | AY16: 10806 | AZ16: 6769 | BA16: 7161 | BB16: 6869 | BC16: 7541 | BD16: 7343 | BE16: 7229 | BF16: 7004 | BG16: 7431 | BH16: 7870 | BI16: 8527 | BJ16: 8287 | BK16: 8402 | BL16: 8769 | BM16: 9785 | BN16: 10082 | BO16: 10792 | BP16: 10925 | BQ16: 10768 | BR16: 11078 | BS16: 11080 | BT16: 11753 | BU16: 11298 | BV16: 12037 | BW16: 12496 | BX16: 13610 | BY16: 8715 | BZ16: 9152 | CA16: 9264 | CB16: 9494 | CC16: 9071 | CD16: 9410 | CE16: 10004 | CF16: 9925 | CG16: 10900 | CH16: 11434 | CI16: 11053 | CJ16: 11388 | CK16: 12301 | CL16: 12885 | CM16: 13523 | CN16: 13131 | CO16: 13657 | CP16: 14145 | CQ16: 14407 | CR16: 14725 | CS16: 15244 | CT16: 15385 | CU16: 15395 | CV16: 16361 | CW16: 17590 | CX16: 18653 | CY16: 18819 | CZ16: 20139 | DA16: 19955 | DB16: 21655 | DC16: 22943 | DD16: 23180 | DE16: 23623 | DF16: 23726 | DG16: 24160 | DH16: 24183 | DI16: 24313 | DJ16: 24957 | DK16: 24260 | DL16: 24326 | DM16: 23983 | DN16: 25184 | DO16: 24822 | DP16: 24781 | DQ16: 24262 | DR16: 25432 | DS16: 26023 | DT16: 26855 | DU16: 28363 | DV16: 30226
A17: Property income received | B17: 1335 | C17: 1820 | D17: 1345 | E17: 1387 | F17: 1181 | G17: 1272 | H17: 1543 | I17: 1565 | J17: 1875 | K17: 1738 | L17: 1443 | M17: 1392 | N17: 1580 | O17: 1739 | P17: 1647 | Q17: 1665 | R17: 1694 | S17: 1789 | T17: 1949 | U17: 2062 | V17: 2139 | W17: 2281 | X17: 2514 | Y17: 2485 | Z17: 3079 | AA17: 3348 | AB17: 3809 | AC17: 3212 | AD17: 3054 | AE17: 2980 | AF17: 3154 | AG17: 3478 | AH17: 3588 | AI17: 3918 | AJ17: 3784 | AK17: 3214 | AL17: 3028 | AM17: 3489 | AN17: 3776 | AO17: 3529 | AP17: 3908 | AQ17: 3719 | AR17: 3732 | AS17: 3778 | AT17: 3790 | AU17: 4008 | AV17: 4172 | AW17: 4420 | AX17: 4600 | AY17: 4987 | AZ17: 6262 | BA17: 6141 | BB17: 6166 | BC17: 5682 | BD17: 5572 | BE17: 5913 | BF17: 5976 | BG17: 6081 | BH17: 6357 | BI17: 6469 | BJ17: 6135 | BK17: 6067 | BL17: 6533 | BM17: 6627 | BN17: 6149 | BO17: 6541 | BP17: 6909 | BQ17: 7076 | BR17: 7021 | BS17: 7112 | BT17: 7329 | BU17: 7408 | BV17: 7786 | BW17: 8008 | BX17: 8699 | BY17: 9693 | BZ17: 9313 | CA17: 9397 | CB17: 8483 | CC17: 8715 | CD17: 8378 | CE17: 9145 | CF17: 9400 | CG17: 10185 | CH17: 10471 | CI17: 10130 | CJ17: 10311 | CK17: 10130 | CL17: 10767 | CM17: 10794 | CN17: 10998 | CO17: 11546 | CP17: 11317 | CQ17: 11348 | CR17: 11526 | CS17: 11979 | CT17: 12150 | CU17: 12388 | CV17: 13090 | CW17: 14699 | CX17: 26528 | CY17: 27662 | CZ17: 27619 | DA17: 25378 | DB17: 24721 | DC17: 25649 | DD17: 27457 | DE17: 31677 | DF17: 35483 | DG17: 36805 | DH17: 34756 | DI17: 34345 | DJ17: 35888 | DK17: 37032 | DL17: 38825 | DM17: 39392 | DN17: 43848 | DO17: 40141 | DP17: 42945 | DQ17: 41229 | DR17: 44024 | DS17: 41529 | DT17: 43300 | DU17: 47220 | DV17: 57231
A18: Less: property income paid | B18: 1645 | C18: 1980 | D18: 1903 | E18: 1712 | F18: 1771 | G18: 1844 | H18: 2021 | I18: 2630 | J18: 2782 | K18: 2828 | L18: 2381 | M18: 2205 | N18: 2339 | O18: 2465 | P18: 2417 | Q18: 2295 | R18: 2375 | S18: 2334 | T18: 2461 | U18: 2898 | V18: 3308 | W18: 3021 | X18: 2774 | Y18: 3596 | Z18: 5956 | AA18: 2339 | AB18: 2643 | AC18: 2533 | AD18: 2273 | AE18: 2307 | AF18: 2331 | AG18: 2671 | AH18: 3159 | AI18: 3578 | AJ18: 3661 | AK18: 2975 | AL18: 2945 | AM18: 2947 | AN18: 3095 | AO18: 3093 | AP18: 2879 | AQ18: 2930 | AR18: 3036 | AS18: 3155 | AT18: 3561 | AU18: 3935 | AV18: 3731 | AW18: 3398 | AX18: 4149 | AY18: 6289 | AZ18: 2978 | BA18: 3344 | BB18: 3213 | BC18: 2818 | BD18: 2946 | BE18: 2984 | BF18: 3116 | BG18: 3740 | BH18: 4354 | BI18: 4524 | BJ18: 3981 | BK18: 3670 | BL18: 3739 | BM18: 3709 | BN18: 3701 | BO18: 3709 | BP18: 3786 | BQ18: 3600 | BR18: 3714 | BS18: 4200 | BT18: 4719 | BU18: 4468 | BV18: 4203 | BW18: 5063 | BX18: 7470 | BY18: 3704 | BZ18: 4247 | CA18: 4115 | CB18: 3699 | CC18: 3619 | CD18: 3707 | CE18: 3987 | CF18: 4485 | CG18: 5352 | CH18: 5396 | CI18: 4771 | CJ18: 4695 | CK18: 4601 | CL18: 4627 | CM18: 4647 | CN18: 4580 | CO18: 4516 | CP18: 4618 | CQ18: 4829 | CR18: 5532 | CS18: 6161 | CT18: 5516 | CU18: 4820 | CV18: 5940 | CW18: 9329 | CX18: 4693 | CY18: 5068 | CZ18: 5057 | DA18: 4503 | DB18: 4881 | DC18: 4870 | DD18: 4969 | DE18: 6068 | DF18: 7004 | DG18: 7267 | DH18: 6229 | DI18: 6060 | DJ18: 5768 | DK18: 5668 | DL18: 5687 | DM18: 5734 | DN18: 5534 | DO18: 5478 | DP18: 5798 | DQ18: 6621 | DR18: 7361 | DS18: 6474 | DT18: 6072 | DU18: 7287 | DV18: 11009
A19: Current transfers received | B19: 9974 | C19: 10793 | D19: 11262 | E19: 11473 | F19: 11737 | G19: 11635 | H19: 12179 | I19: 12689 | J19: 13812 | K19: 14072 | L19: 14894 | M19: 15360 | N19: 15869 | O19: 16180 | P19: 16424 | Q19: 16669 | R19: 16929 | S19: 17697 | T19: 18331 | U19: 18816 | V19: 19471 | W19: 28685 | X19: 25622 | Y19: 25510 | Z19: 26107 | AA19: 13064 | AB19: 13175 | AC19: 14001 | AD19: 14413 | AE19: 14966 | AF19: 15741 | AG19: 16294 | AH19: 16884 | AI19: 17511 | AJ19: 17766 | AK19: 18375 | AL19: 19060 | AM19: 19042 | AN19: 19959 | AO19: 20270 | AP19: 20306 | AQ19: 21059 | AR19: 21850 | AS19: 22697 | AT19: 23358 | AU19: 24113 | AV19: 34871 | AW19: 31505 | AX19: 30013 | AY19: 30786 | AZ19: 11942 | BA19: 11986 | BB19: 12727 | BC19: 13062 | BD19: 13162 | BE19: 14383 | BF19: 14374 | BG19: 15367 | BH19: 15391 | BI19: 15582 | BJ19: 16510 | BK19: 17634 | BL19: 17860 | BM19: 17816 | BN19: 18606 | BO19: 18819 | BP19: 20761 | BQ19: 22704 | BR19: 23272 | BS19: 23802 | BT19: 24329 | BU19: 31595 | BV19: 29812 | BW19: 27013 | BX19: 28248 | BY19: 10068 | BZ19: 9729 | CA19: 11204 | CB19: 10874 | CC19: 11450 | CD19: 11368 | CE19: 11536 | CF19: 13024 | CG19: 14158 | CH19: 15068 | CI19: 15626 | CJ19: 16599 | CK19: 16194 | CL19: 16147 | CM19: 17431 | CN19: 18128 | CO19: 20133 | CP19: 20835 | CQ19: 21174 | CR19: 21418 | CS19: 21479 | CT19: 28703 | CU19: 28563 | CV19: 24980 | CW19: 24546 | CX19: 9566 | CY19: 8954 | CZ19: 10274 | DA19: 9537 | DB19: 9537 | DC19: 9953 | DD19: 9737 | DE19: 11773 | DF19: 12324 | DG19: 13140 | DH19: 14494 | DI19: 15370 | DJ19: 15204 | DK19: 16487 | DL19: 17124 | DM19: 17545 | DN19: 19573 | DO19: 20712 | DP19: 20935 | DQ19: 21143 | DR19: 21126 | DS19: 25056 | DT19: 25538 | DU19: 22616 | DV19: 23596
A20: Less: current transfers paid | B20: 4226 | C20: 5673 | D20: 4466 | E20: 4701 | F20: 4592 | G20: 4671 | H20: 5457 | I20: 5397 | J20: 6275 | K20: 6176 | L20: 5722 | M20: 5578 | N20: 6018 | O20: 5705 | P20: 6229 | Q20: 6059 | R20: 6204 | S20: 6912 | T20: 7527 | U20: 8009 | V20: 8172 | W20: 8337 | X20: 9076 | Y20: 9280 | Z20: 10330 | AA20: 8923 | AB20: 10170 | AC20: 9759 | AD20: 9475 | AE20: 9532 | AF20: 10034 | AG20: 10805 | AH20: 11440 | AI20: 12423 | AJ20: 12326 | AK20: 10880 | AL20: 10929 | AM20: 11398 | AN20: 13154 | AO20: 12525 | AP20: 13727 | AQ20: 13881 | AR20: 14750 | AS20: 14371 | AT20: 14344 | AU20: 14719 | AV20: 14304 | AW20: 17179 | AX20: 17599 | AY20: 17871 | AZ20: 17776 | BA20: 17799 | BB20: 18465 | BC20: 17341 | BD20: 18526 | BE20: 19520 | BF20: 20344 | BG20: 20922 | BH20: 21394 | BI20: 22601 | BJ20: 21458 | BK20: 21835 | BL20: 23298 | BM20: 24696 | BN20: 24549 | BO20: 25414 | BP20: 27466 | BQ20: 28005 | BR20: 27432 | BS20: 27710 | BT20: 28326 | BU20: 28164 | BV20: 31797 | BW20: 32807 | BX20: 33768 | BY20: 28267 | BZ20: 28304 | CA20: 29235 | CB20: 28693 | CC20: 29505 | CD20: 30492 | CE20: 32429 | CF20: 33585 | CG20: 35687 | CH20: 36178 | CI20: 35247 | CJ20: 35479 | CK20: 37648 | CL20: 39510 | CM20: 41322 | CN20: 42022 | CO20: 43078 | CP20: 43948 | CQ20: 44141 | CR20: 45767 | CS20: 46939 | CT20: 46122 | CU20: 48450 | CV20: 51479 | CW20: 54126 | CX20: 51853 | CY20: 55119 | CZ20: 55659 | DA20: 54654 | DB20: 55697 | DC20: 59605 | DD20: 63375 | DE20: 66466 | DF20: 71704 | DG20: 70837 | DH20: 67718 | DI20: 67095 | DJ20: 71294 | DK20: 73169 | DL20: 74470 | DM20: 77338 | DN20: 81291 | DO20: 80511 | DP20: 82398 | DQ20: 85831 | DR20: 87087 | DS20: 88528 | DT20: 97261 | DU20: 99576 | DV20: 105162
A21: Household final consumption expenditure (HFCE) | B21: 24102 | C21: 25810 | D21: 25104 | E21: 27210 | F21: 27705 | G21: 29959 | H21: 32395 | I21: 35870 | J21: 37586 | K21: 39192 | L21: 38581 | M21: 40596 | N21: 40836 | O21: 42656 | P21: 44572 | Q21: 46450 | R21: 47229 | S21: 48530 | T21: 50146 | U21: 51713 | V21: 55544 | W21: 50287 | X21: 56338 | Y21: 60116 | Z21: 61968 | AA21: 35653 | AB21: 36532 | AC21: 37719 | AD21: 39584 | AE21: 40794 | AF21: 42638 | AG21: 44142 | AH21: 45967 | AI21: 49043 | AJ21: 50848 | AK21: 49921 | AL21: 51589 | AM21: 52826 | AN21: 53970 | AO21: 54322 | AP21: 56149 | AQ21: 58097 | AR21: 59080 | AS21: 60754 | AT21: 63111 | AU21: 65844 | AV21: 61676 | AW21: 67694 | AX21: 72387 | AY21: 75118 | AZ21: 45044 | BA21: 46513 | BB21: 48811 | BC21: 50036 | BD21: 51391 | BE21: 52277 | BF21: 54391 | BG21: 56189 | BH21: 58169 | BI21: 59297 | BJ21: 59069 | BK21: 61799 | BL21: 63688 | BM21: 65575 | BN21: 66820 | BO21: 70253 | BP21: 71629 | BQ21: 72369 | BR21: 74090 | BS21: 76698 | BT21: 78509 | BU21: 74897 | BV21: 82502 | BW21: 88863 | BX21: 91266 | BY21: 53527 | BZ21: 56197 | CA21: 58443 | CB21: 60269 | CC21: 63583 | CD21: 63006 | CE21: 65997 | CF21: 67937 | CG21: 70541 | CH21: 73010 | CI21: 72672 | CJ21: 75484 | CK21: 78677 | CL21: 78788 | CM21: 82191 | CN21: 83804 | CO21: 86323 | CP21: 87962 | CQ21: 90370 | CR21: 91346 | CS21: 91588 | CT21: 86472 | CU21: 94032 | CV21: 99956 | CW21: 103168 | CX21: 75203 | CY21: 79655 | CZ21: 81051 | DA21: 84998 | DB21: 87129 | DC21: 91512 | DD21: 94322 | DE21: 96839 | DF21: 101472 | DG21: 103040 | DH21: 102500 | DI21: 105584 | DJ21: 107597 | DK21: 110226 | DL21: 112898 | DM21: 116650 | DN21: 120047 | DO21: 122019 | DP21: 125567 | DQ21: 126648 | DR21: 123890 | DS21: 115968 | DT21: 122068 | DU21: 132591 | DV21: 137015
A22: Food and non-alcoholic beverages | B22: 3300 | C22: 3356 | D22: 3392 | E22: 3591 | F22: 3613 | G22: 3811 | H22: 3932 | I22: 4292 | J22: 4285 | K22: 4554 | L22: 4697 | M22: 4738 | N22: 4722 | O22: 4917 | P22: 5049 | Q22: 5099 | R22: 5316 | S22: 5547 | T22: 5633 | U22: 5623 | V22: 5871 | W22: 6303 | X22: 6301 | Y22: 6532 | Z22: 6876 | AA22: 4231 | AB22: 4310 | AC22: 4550 | AD22: 4589 | AE22: 4796 | AF22: 4877 | AG22: 4967 | AH22: 5059 | AI22: 5277 | AJ22: 5400 | AK22: 5699 | AL22: 5710 | AM22: 5811 | AN22: 5848 | AO22: 5807 | AP22: 5944 | AQ22: 6085 | AR22: 6242 | AS22: 6366 | AT22: 6411 | AU22: 6765 | AV22: 7443 | AW22: 7599 | AX22: 7890 | AY22: 8272 | AZ22: 4715 | BA22: 4794 | BB22: 5008 | BC22: 5084 | BD22: 5210 | BE22: 5448 | BF22: 5490 | BG22: 5538 | BH22: 5636 | BI22: 5753 | BJ22: 6113 | BK22: 6156 | BL22: 6100 | BM22: 6375 | BN22: 6533 | BO22: 7039 | BP22: 7278 | BQ22: 7228 | BR22: 7521 | BS22: 7482 | BT22: 7625 | BU22: 8402 | BV22: 8712 | BW22: 8939 | BX22: 9429 | BY22: 4819 | BZ22: 5071 | CA22: 5311 | CB22: 5407 | CC22: 5742 | CD22: 5724 | CE22: 6023 | CF22: 6108 | CG22: 6259 | CH22: 6515 | CI22: 6801 | CJ22: 6921 | CK22: 7107 | CL22: 7061 | CM22: 7349 | CN22: 7520 | CO22: 7835 | CP22: 7907 | CQ22: 8050 | CR22: 7982 | CS22: 8145 | CT22: 8948 | CU22: 9437 | CV22: 9701 | CW22: 10204 | CX22: 5665 | CY22: 5923 | CZ22: 6107 | DA22: 6358 | DB22: 6320 | DC22: 6414 | DD22: 6416 | DE22: 6561 | DF22: 6880 | DG22: 7185 | DH22: 7499 | DI22: 7650 | DJ22: 7896 | DK22: 8040 | DL22: 8120 | DM22: 8308 | DN22: 8556 | DO22: 8615 | DP22: 8781 | DQ22: 8751 | DR22: 8602 | DS22: 9338 | DT22: 9033 | DU22: 9338 | DV22: 9834
A23: Alcoholic beverages and tobacco | B23: 1193 | C23: 1227 | D23: 1232 | E23: 1364 | F23: 1546 | G23: 1589 | H23: 1617 | I23: 1703 | J23: 1745 | K23: 1754 | L23: 1753 | M23: 1770 | N23: 1668 | O23: 1707 | P23: 1710 | Q23: 1876 | R23: 2012 | S23: 2084 | T23: 2056 | U23: 2184 | V23: 2094 | W23: 2252 | X23: 2235 | Y23: 2170 | Z23: 2111 | AA23: 1802 | AB23: 1859 | AC23: 1909 | AD23: 2117 | AE23: 2207 | AF23: 2337 | AG23: 2255 | AH23: 2167 | AI23: 2214 | AJ23: 2172 | AK23: 2203 | AL23: 2269 | AM23: 2286 | AN23: 2458 | AO23: 2375 | AP23: 2542 | AQ23: 2528 | AR23: 2476 | AS23: 2494 | AT23: 2663 | AU23: 2871 | AV23: 2623 | AW23: 2613 | AX23: 2652 | AY23: 2550 | AZ23: 2192 | BA23: 2206 | BB23: 2390 | BC23: 2643 | BD23: 2762 | BE23: 2746 | BF23: 2672 | BG23: 2685 | BH23: 2668 | BI23: 2728 | BJ23: 2626 | BK23: 2713 | BL23: 2671 | BM23: 2735 | BN23: 2789 | BO23: 2884 | BP23: 2840 | BQ23: 2886 | BR23: 2951 | BS23: 3192 | BT23: 2880 | BU23: 3475 | BV23: 3649 | BW23: 3391 | BX23: 3275 | BY23: 2417 | BZ23: 2477 | CA23: 2641 | CB23: 2858 | CC23: 2993 | CD23: 3002 | CE23: 2974 | CF23: 2923 | CG23: 2981 | CH23: 2981 | CI23: 3027 | CJ23: 3047 | CK23: 3156 | CL23: 3034 | CM23: 3127 | CN23: 3187 | CO23: 3392 | CP23: 3405 | CQ23: 3360 | CR23: 3500 | CS23: 3502 | CT23: 3674 | CU23: 3710 | CV23: 3630 | CW23: 3517 | CX23: 2904 | CY23: 2992 | CZ23: 3141 | DA23: 3488 | DB23: 3636 | DC23: 3652 | DD23: 3694 | DE23: 3606 | DF23: 3525 | DG23: 3552 | DH23: 3581 | DI23: 3751 | DJ23: 3900 | DK23: 4081 | DL23: 4139 | DM23: 3962 | DN23: 4038 | DO23: 4199 | DP23: 4184 | DQ23: 4274 | DR23: 4167 | DS23: 4228 | DT23: 4115 | DU23: 3951 | DV23: 3803
A24: Clothing and footwear | B24: 1075 | C24: 1157 | D24: 1200 | E24: 1275 | F24: 1216 | G24: 1375 | H24: 1464 | I24: 1632 | J24: 1707 | K24: 1652 | L24: 1549 | M24: 1641 | N24: 1625 | O24: 1823 | P24: 1957 | Q24: 2018 | R24: 2173 | S24: 2280 | T24: 2268 | U24: 2904 | V24: 3308 | W24: 2351 | X24: 2645 | Y24: 3086 | Z24: 3130 | AA24: 1757 | AB24: 1737 | AC24: 1845 | AD24: 1903 | AE24: 1866 | AF24: 1923 | AG24: 1904 | AH24: 2000 | AI24: 2092 | AJ24: 2116 | AK24: 2016 | AL24: 2025 | AM24: 2220 | AN24: 2296 | AO24: 2253 | AP24: 2270 | AQ24: 2506 | AR24: 2548 | AS24: 2526 | AT24: 3114 | AU24: 3344 | AV24: 2352 | AW24: 2819 | AX24: 3262 | AY24: 3347 | AZ24: 2156 | BA24: 2196 | BB24: 2315 | BC24: 2300 | BD24: 2341 | BE24: 2400 | BF24: 2471 | BG24: 2522 | BH24: 2533 | BI24: 2474 | BJ24: 2435 | BK24: 2542 | BL24: 2663 | BM24: 2621 | BN24: 2654 | BO24: 2837 | BP24: 2952 | BQ24: 3024 | BR24: 3058 | BS24: 3731 | BT24: 3635 | BU24: 3133 | BV24: 3700 | BW24: 4352 | BX24: 4367 | BY24: 2662 | BZ24: 2848 | CA24: 2900 | CB24: 2930 | CC24: 3004 | CD24: 2873 | CE24: 2962 | CF24: 3041 | CG24: 3069 | CH24: 3111 | CI24: 3127 | CJ24: 3338 | CK24: 3254 | CL24: 3184 | CM24: 3228 | CN24: 3459 | CO24: 3624 | CP24: 3530 | CQ24: 3575 | CR24: 4390 | CS24: 4136 | CT24: 3351 | CU24: 3938 | CV24: 4522 | CW24: 4578 | CX24: 4029 | CY24: 4132 | CZ24: 4080 | DA24: 4102 | DB24: 4190 | DC24: 4188 | DD24: 4249 | DE24: 4355 | DF24: 4586 | DG24: 4539 | DH24: 4403 | DI24: 4437 | DJ24: 4461 | DK24: 4546 | DL24: 4630 | DM24: 4752 | DN24: 4904 | DO24: 4801 | DP24: 4917 | DQ24: 6004 | DR24: 5879 | DS24: 5055 | DT24: 5714 | DU24: 6714 | DV24: 6843
A25: Housing, water, electricity, gas and other fuels | B25: 6446 | C25: 6648 | D25: 6668 | E25: 7182 | F25: 7450 | G25: 7901 | H25: 8168 | I25: 8787 | J25: 9231 | K25: 9866 | L25: 9900 | M25: 10685 | N25: 10755 | O25: 11160 | P25: 11595 | Q25: 12190 | R25: 12451 | S25: 12652 | T25: 12958 | U25: 11947 | V25: 12166 | W25: 12884 | X25: 13608 | Y25: 14231 | Z25: 15022 | AA25: 8726 | AB25: 8825 | AC25: 9009 | AD25: 9650 | AE25: 9975 | AF25: 10220 | AG25: 10586 | AH25: 10728 | AI25: 11505 | AJ25: 12125 | AK25: 12207 | AL25: 12468 | AM25: 12986 | AN25: 13093 | AO25: 13465 | AP25: 13883 | AQ25: 14429 | AR25: 14731 | AS25: 14759 | AT25: 14101 | AU25: 14800 | AV25: 15689 | AW25: 16464 | AX25: 17151 | AY25: 18068 | AZ25: 10314 | BA25: 10881 | BB25: 11387 | BC25: 11261 | BD25: 11794 | BE25: 11946 | BF25: 12439 | BG25: 12552 | BH25: 13265 | BI25: 13678 | BJ25: 13810 | BK25: 14523 | BL25: 14814 | BM25: 15137 | BN25: 15793 | BO25: 16512 | BP25: 17060 | BQ25: 17196 | BR25: 17488 | BS25: 16489 | BT25: 17610 | BU25: 18670 | BV25: 19852 | BW25: 20598 | BX25: 21737 | BY25: 11969 | BZ25: 12412 | CA25: 12736 | CB25: 13044 | CC25: 13823 | CD25: 13754 | CE25: 14272 | CF25: 14717 | CG25: 15383 | CH25: 16234 | CI25: 16684 | CJ25: 16722 | CK25: 17397 | CL25: 17927 | CM25: 18887 | CN25: 19331 | CO25: 19706 | CP25: 20325 | CQ25: 21056 | CR25: 19417 | CS25: 19409 | CT25: 20078 | CU25: 21176 | CV25: 22180 | CW25: 23350 | CX25: 16322 | CY25: 16874 | CZ25: 17081 | DA25: 17347 | DB25: 17943 | DC25: 19043 | DD25: 19783 | DE25: 20770 | DF25: 21473 | DG25: 22228 | DH25: 22742 | DI25: 23167 | DJ25: 23753 | DK25: 24648 | DL25: 25225 | DM25: 26471 | DN25: 27565 | DO25: 28333 | DP25: 29450 | DQ25: 27692 | DR25: 28648 | DS25: 28642 | DT25: 29066 | DU25: 30632 | DV25: 32310
... A36: Household net saving | B36: -9381 | C36: -10792 | D36: -9111 | E36: -11284 | F36: -11106 | G36: -13218 | H36: -16101 | I36: -17960 | J36: -18331 | K36: -19540 | L36: -18470 | M36: -19816 | N36: -19561 | O36: -19744 | P36: -21954 | Q36: -23918 | R36: -24838 | S36: -25091 | T36: -26121 | U36: -26947 | V36: -30139 | W36: -17760 | X36: -24222 | Y36: -29019 | Z36: -30984 | AA36: -5981 | AB36: -5446 | AC36: -5326 | AD36: -6854 | AE36: -8030 | AF36: -9250 | AG36: -9544 | AH36: -9124 | AI36: -9804 | AJ36: -10550 | AK36: -9652 | AL36: -9230 | AM36: -10216 | AN36: -9645 | AO36: -10121 | AP36: -10266 | AQ36: -10607 | AR36: -8597 | AS36: -10013 | AT36: -12680 | AU36: -14475 | AV36: -1484 | AW36: -7894 | AX36: -14161 | AY36: -17105 | AZ36: -2311 | BA36: -2942 | BB36: -4034 | BC36: -5365 | BD36: -4776 | BE36: -4821 | BF36: -5372 | BG36: -4655 | BH36: -5103 | BI36: -3068 | BJ36: -2898 | BK36: -2499 | BL36: -3337 | BM36: -3517 | BN36: -3190 | BO36: -5113 | BP36: -1622 | BQ36: -2654 | BR36: -3782 | BS36: -6262 | BT36: -6182 | BU36: 4074 | BV36: -1794 | BW36: -9685 | BX36: -11380 | BY36: 4974 | BZ36: 3823 | CA36: 3586 | CB36: 4464 | CC36: 1468 | CD36: 4319 | CE36: 3917 | CF36: 3931 | CG36: 3557 | CH36: 4836 | CI36: 6011 | CJ36: 7231 | CK36: 7584 | CL36: 9190 | CM36: 9395 | CN36: 9539 | CO36: 8509 | CP36: 6635 | CQ36: 7404 | CR36: 7642 | CS36: 10081 | CT36: 22430 | CU36: 21129 | CV36: 16470 | CW36: 17517 | CX36: 23166 | CY36: 27240 | CZ36: 27028 | DA36: 27253 | DB36: 28168 | DC36: 29832 | DD36: 31248 | DE36: 35710 | DF36: 36335 | DG36: 39173 | DH36: 40070 | DI36: 38577 | DJ36: 40440 | DK36: 41540 | DL36: 44493 | DM36: 44136 | DN36: 46000 | DO36: 37222 | DP36: 40450 | DQ36: 40759 | DR36: 49344 | DS36: 56458 | DT36: 60588 | DU36: 61445 | DV36: 68660
A41: Footnotes:
A42: 1 | B42: Income quintiles are assigned based on equivalized household disposable income, which takes into account differences in household size and composition using a method proposed by the Organization for Economic Co-operation and Development (OECD). The OECD-modified" equivalence scale assigns a value of 1 to the first adult | C42: 0.5 to each additional person aged 14 and over | D42: and 0.3 for all children under 14."
A46: How to cite: Statistics Canada. Table 36-10-0587-01 Distributions of household economic accounts, income, consumption and saving, by characteristic, annual (x 1,000,000)
A47: https://www150.statcan.gc.ca/t1/tbl1/en/tv.action?pid=3610058701

Sheet 2023 by Age and Quintile
A1: Distributions of household economic accounts, income, consumption and saving, by characteristic, annual (x 1,000,000)
A2: Frequency: Annual
A3: Table: 36-10-0587-01 (formerly CANSIM 378-0152)
A4: Release date: 2024-07-17
A5: Geography: Canada
A6: https://www150.statcan.gc.ca/t1/tbl1/en/cv!recreate.action?pid=3610058701&selectedNodeIds=2D1,3D17,3D18,3D19,3D20,3D21,3D22,3D23,3D24,3D25,3D26,3D27,3D28,3D29,3D30,3D31,3D32,3D33,3D34,3D35,3D36,3D37,3D38,3D39,3D40,3D41,3D42,3D43,3D44,3D45,3D46,4D1,4D2,4D3,4D4,4D5,4D6,4D7,4D8,4D9,4D10,4D11,4D12,4D13,4D14,4D15,4D16,4D17,4D18,4D19,4D20,4D21,4D22,4D23&checkedLevels=0D1,2D1&refPeriods=20230101,20230101&dimensionLayouts=layout2,layout2,layout2,layout3,layout2&vectorDisplay=false
A9: Geography | B9: Canada
A10: Statistics | B10: Value
A11: Quintile | B11: All | C11: All | D11: All | E11: All | F11: All | G11: All | H11: 1 | I11: 1 | J11: 1 | K11: 1 | L11: 1 | M11: 2 | N11: 2 | O11: 2 | P11: 2 | Q11: 2 | R11: 3 | S11: 3 | T11: 3 | U11: 3 | V11: 3 | W11: 4 | X11: 4 | Y11: 4 | Z11: 4 | AA11: 4 | AB11: 5 | AC11: 5 | AD11: 5 | AE11: 5 | AF11: 5
A12: Age | B12: All | C12: Less than 35 years | D12: 35 to 44 years | E12: 45 to 54 years | F12: 55 to 64 years | G12: 65 years and over | H12: Less than 35 years | I12: 35 to 44 years | J12: 45 to 54 years | K12: 55 to 64 years | L12: 65 years and over | M12: Less than 35 years | N12: 35 to 44 years | O12: 45 to 54 years | P12: 55 to 64 years | Q12: 65 years and over | R12: Less than 35 years | S12: 35 to 44 years | T12: 45 to 54 years | U12: 55 to 64 years | V12: 65 years and over | W12: Less than 35 years | X12: 35 to 44 years | Y12: 45 to 54 years | Z12: 55 to 64 years | AA12: 65 years and over | AB12: Less than 35 years | AC12: 35 to 44 years | AD12: 45 to 54 years | AE12: 55 to 64 years | AF12: 65 years and over
A13: Characteristics | B13: All households | C13: Less than 35 years 1 | D13: 35 to 44 years 1 | E13: 45 to 54 years 1 | F13: 55 to 64 years 1 | G13: 65 years and over 1 | H13: Lowest income quintile, less than 35 years 1 2 | I13: Lowest income quintile, 35 to 44 years 1 2 | J13: Lowest income quintile, 45 to 54 years 1 2 | K13: Lowest income quintile, 55 to 64 years 1 2 | L13: Lowest income quintile, 65 years and over 1 2 | M13: Second income quintile, less than 35 years 1 2 | N13: Second income quintile, 35 to 44 years 1 2 | O13: Second income quintile, 45 to 54 years 1 2 | P13: Second income quintile, 55 to 64 years 1 2 | Q13: Second income quintile, 65 years and over 1 2 | R13: Third income quintile, less than 35 years 1 2 | S13: Third income quintile, 35 to 44 years 1 2 | T13: Third income quintile, 45 to 54 years 1 2 | U13: Third income quintile, 55 to 64 years 1 2 | V13: Third income quintile, 65 years and over 1 2 | W13: Fourth income quintile, less than 35 years 1 2 | X13: Fourth income quintile, 35 to 44 years 1 2 | Y13: Fourth income quintile, 45 to 54 years 1 2 | Z13: Fourth income quintile, 55 to 64 years 1 2 | AA13: Fourth income quintile, 65 years and over 1 2 | AB13: Highest income quintile, less than 35 years 1 2 | AC13: Highest income quintile, 35 to 44 years 1 2 | AD13: Highest income quintile, 45 to 54 years 1 2 | AE13: Highest income quintile, 55 to 64 years 1 2 | AF13: Highest income quintile, 65 years and over 1 2
A14: Income, consumption and savings | B14: 2023 | C14: 2023 | D14: 2023 | E14: 2023 | F14: 2023 | G14: 2023 | H14: 2023 | I14: 2023 | J14: 2023 | K14: 2023 | L14: 2023 | M14: 2023 | N14: 2023 | O14: 2023 | P14: 2023 | Q14: 2023 | R14: 2023 | S14: 2023 | T14: 2023 | U14: 2023 | V14: 2023 | W14: 2023 | X14: 2023 | Y14: 2023 | Z14: 2023 | AA14: 2023 | AB14: 2023 | AC14: 2023 | AD14: 2023 | AE14: 2023 | AF14: 2023
B15: Dollars
A16: Household disposable income | B16: 1597953 | C16: 296903 | D16: 334126 | E16: 340857 | F16: 294159 | G16: 331908 | H16: 20685 | I16: 19005 | J16: 15867 | K16: 12855 | L16: 36357 | M16: 42393 | N16: 42836 | O16: 29760 | P16: 24148 | Q16: 57932 | R16: 54906 | S16: 60626 | T16: 50882 | U16: 37300 | V16: 58168 | W16: 79512 | X16: 90079 | Y16: 82883 | Z16: 65618 | AA16: 60866 | AB16: 99408 | AC16: 121581 | AD16: 161465 | AE16: 154238 | AF16: 118586
A17: Compensation of employees | B17: 1470746 | C17: 337380 | D17: 380757 | E17: 392788 | F17: 297999 | G17: 61822 | H17: .. | I17: .. | J17: .. | K17: .. | L17: .. | M17: .. | N17: .. | O17: .. | P17: .. | Q17: .. | R17: .. | S17: .. | T17: .. | U17: .. | V17: .. | W17: .. | X17: .. | Y17: .. | Z17: .. | AA17: .. | AB17: .. | AC17: .. | AD17: .. | AE17: .. | AF17: ..
A18: Net mixed income | B18: 257594 | C18: 40299 | D18: 52873 | E18: 53325 | F18: 53018 | G18: 58080 | H18: .. | I18: .. | J18: .. | K18: .. | L18: .. | M18: .. | N18: .. | O18: .. | P18: .. | Q18: .. | R18: .. | S18: .. | T18: .. | U18: .. | V18: .. | W18: .. | X18: .. | Y18: .. | Z18: .. | AA18: .. | AB18: .. | AC18: .. | AD18: .. | AE18: .. | AF18: ..
A19: Property income received | B19: 294027 | C19: 22860 | D19: 39072 | E19: 50796 | F19: 61421 | G19: 119877 | H19: .. | I19: .. | J19: .. | K19: .. | L19: .. | M19: .. | N19: .. | O19: .. | P19: .. | Q19: .. | R19: .. | S19: .. | T19: .. | U19: .. | V19: .. | W19: .. | X19: .. | Y19: .. | Z19: .. | AA19: .. | AB19: .. | AC19: .. | AD19: .. | AE19: .. | AF19: ..
A20: Less: property income paid | B20: 132778 | C20: 27654 | D20: 36079 | E20: 29872 | F20: 21531 | G20: 17643 | H20: .. | I20: .. | J20: .. | K20: .. | L20: .. | M20: .. | N20: .. | O20: .. | P20: .. | Q20: .. | R20: .. | S20: .. | T20: .. | U20: .. | V20: .. | W20: .. | X20: .. | Y20: .. | Z20: .. | AA20: .. | AB20: .. | AC20: .. | AD20: .. | AE20: .. | AF20: ..
A21: Current transfers received | B21: 441837 | C21: 46420 | D21: 56162 | E21: 41146 | F21: 63914 | G21: 234195 | H21: .. | I21: .. | J21: .. | K21: .. | L21: .. | M21: .. | N21: .. | O21: .. | P21: .. | Q21: .. | R21: .. | S21: .. | T21: .. | U21: .. | V21: .. | W21: .. | X21: .. | Y21: .. | Z21: .. | AA21: .. | AB21: .. | AC21: .. | AD21: .. | AE21: .. | AF21: ..
A22: Less: current transfers paid | B22: 733473 | C22: 122402 | D22: 158658 | E22: 167326 | F22: 160662 | G22: 124424 | H22: .. | I22: .. | J22: .. | K22: .. | L22: .. | M22: .. | N22: .. | O22: .. | P22: .. | Q22: .. | R22: .. | S22: .. | T22: .. | U22: .. | V22: .. | W22: .. | X22: .. | Y22: .. | Z22: .. | AA22: .. | AB22: .. | AC22: .. | AD22: .. | AE22: .. | AF22: ..
A23: Household final consumption expenditure (HFCE) | B23: 1553214 | C23: 269860 | D23: 306717 | E23: 333373 | F23: 311362 | G23: 331898 | H23: 40387 | I23: 30643 | J23: 30670 | K23: 37211 | L23: 66516 | M23: 45881 | N23: 52449 | O23: 41246 | P23: 36872 | Q23: 72569 | R23: 54357 | S23: 64719 | T23: 65430 | U23: 49826 | V23: 68218 | W23: 58981 | X23: 73640 | Y23: 82718 | Z23: 70465 | AA23: 56201 | AB23: 70254 | AC23: 85266 | AD23: 113309 | AE23: 116988 | AF23: 68395
A24: Food and non-alcoholic beverages | B24: 147899 | C24: 24626 | D24: 30062 | E24: 31916 | F24: 28355 | G24: 32941 | H24: .. | I24: .. | J24: .. | K24: .. | L24: .. | M24: .. | N24: .. | O24: .. | P24: .. | Q24: .. | R24: .. | S24: .. | T24: .. | U24: .. | V24: .. | W24: .. | X24: .. | Y24: .. | Z24: .. | AA24: .. | AB24: .. | AC24: .. | AD24: .. | AE24: .. | AF24: ..
A25: Alcoholic beverages and tobacco | B25: 50575 | C25: 9139 | D25: 9577 | E25: 11013 | F25: 11080 | G25: 9769 | H25: .. | I25: .. | J25: .. | K25: .. | L25: .. | M25: .. | N25: .. | O25: .. | P25: .. | Q25: .. | R25: .. | S25: .. | T25: .. | U25: .. | V25: .. | W25: .. | X25: .. | Y25: .. | Z25: .. | AA25: .. | AB25: .. | AC25: .. | AD25: .. | AE25: .. | AF25: ..
A26: Clothing and footwear | B26: 73807 | C26: 15491 | D26: 17444 | E26: 16741 | F26: 13593 | G26: 10536 | H26: .. | I26: .. | J26: .. | K26: .. | L26: .. | M26: .. | N26: .. | O26: .. | P26: .. | Q26: .. | R26: .. | S26: .. | T26: .. | U26: .. | V26: .. | W26: .. | X26: .. | Y26: .. | Z26: .. | AA26: .. | AB26: .. | AC26: .. | AD26: .. | AE26: .. | AF26: ..
A27: Housing, water, electricity, gas and other fuels | B27: 366271 | C27: 65927 | D27: 67292 | E27: 73641 | F27: 73776 | G27: 85633 | H27: .. | I27: .. | J27: .. | K27: .. | L27: .. | M27: .. | N27: .. | O27: .. | P27: .. | Q27: .. | R27: .. | S27: .. | T27: .. | U27: .. | V27: .. | W27: .. | X27: .. | Y27: .. | Z27: .. | AA27: .. | AB27: .. | AC27: .. | AD27: .. | AE27: .. | AF27: ..
A28: Furnishings, household equipment and other goods and services related to the dwelling and property | B28: 93062 | C28: 15843 | D28: 19831 | E28: 19335 | F28: 19520 | G28: 18534 | H28: .. | I28: .. | J28: .. | K28: .. | L28: .. | M28: .. | N28: .. | O28: .. | P28: .. | Q28: .. | R28: .. | S28: .. | T28: .. | U28: .. | V28: .. | W28: .. | X28: .. | Y28: .. | Z28: .. | AA28: .. | AB28: .. | AC28: .. | AD28: .. | AE28: .. | AF28: ..
A29: Health | B29: 66112 | C29: 6826 | D29: 8660 | E29: 11763 | F29: 16007 | G29: 22854 | H29: .. | I29: .. | J29: .. | K29: .. | L29: .. | M29: .. | N29: .. | O29: .. | P29: .. | Q29: .. | R29: .. | S29: .. | T29: .. | U29: .. | V29: .. | W29: .. | X29: .. | Y29: .. | Z29: .. | AA29: .. | AB29: .. | AC29: .. | AD29: .. | AE29: .. | AF29: ..
A30: Transport | B30: 243275 | C30: 43386 | D30: 51706 | E30: 59549 | F30: 45599 | G30: 43033 | H30: .. | I30: .. | J30: .. | K30: .. | L30: .. | M30: .. | N30: .. | O30: .. | P30: .. | Q30: .. | R30: .. | S30: .. | T30: .. | U30: .. | V30: .. | W30: .. | X30: .. | Y30: .. | Z30: .. | AA30: .. | AB30: .. | AC30: .. | AD30: .. | AE30: .. | AF30: ..
A31: Communications | B31: 39258 | C31: 7783 | D31: 7781 | E31: 8120 | F31: 7699 | G31: 7872 | H31: .. | I31: .. | J31: .. | K31: .. | L31: .. | M31: .. | N31: .. | O31: .. | P31: .. | Q31: .. | R31: .. | S31: .. | T31: .. | U31: .. | V31: .. | W31: .. | X31: .. | Y31: .. | Z31: .. | AA31: .. | AB31: .. | AC31: .. | AD31: .. | AE31: .. | AF31: ..
A32: Recreation and culture | B32: 134389 | C32: 22463 | D32: 29801 | E32: 28642 | F32: 28238 | G32: 25243 | H32: .. | I32: .. | J32: .. | K32: .. | L32: .. | M32: .. | N32: .. | O32: .. | P32: .. | Q32: .. | R32: .. | S32: .. | T32: .. | U32: .. | V32: .. | W32: .. | X32: .. | Y32: .. | Z32: .. | AA32: .. | AB32: .. | AC32: .. | AD32: .. | AE32: .. | AF32: ..
A33: Education | B33: 19844 | C33: 5399 | D33: 3437 | E33: 6732 | F33: 3895 | G33: 379 | H33: .. | I33: .. | J33: .. | K33: .. | L33: .. | M33: .. | N33: .. | O33: .. | P33: .. | Q33: .. | R33: .. | S33: .. | T33: .. | U33: .. | V33: .. | W33: .. | X33: .. | Y33: .. | Z33: .. | AA33: .. | AB33: .. | AC33: .. | AD33: .. | AE33: .. | AF33: ..
A34: Food, beverage and accommodation services | B34: 116408 | C34: 18456 | D34: 22912 | E34: 27374 | F34: 26424 | G34: 21243 | H34: .. | I34: .. | J34: .. | K34: .. | L34: .. | M34: .. | N34: .. | O34: .. | P34: .. | Q34: .. | R34: .. | S34: .. | T34: .. | U34: .. | V34: .. | W34: .. | X34: .. | Y34: .. | Z34: .. | AA34: .. | AB34: .. | AC34: .. | AD34: .. | AE34: .. | AF34: ..
A35: Insurance and financial services | B35: 121084 | C35: 20064 | D35: 21327 | E35: 25174 | F35: 24574 | G35: 29944 | H35: .. | I35: .. | J35: .. | K35: .. | L35: .. | M35: .. | N35: .. | O35: .. | P35: .. | Q35: .. | R35: .. | S35: .. | T35: .. | U35: .. | V35: .. | W35: .. | X35: .. | Y35: .. | Z35: .. | AA35: .. | AB35: .. | AC35: .. | AD35: .. | AE35: .. | AF35: ..
... A38: Household net saving | B38: 88537 | C38: 55330 | D38: 67014 | E38: 43294 | F38: -7698 | G38: -69397 | H38: .. | I38: .. | J38: .. | K38: .. | L38: .. | M38: .. | N38: .. | O38: .. | P38: .. | Q38: .. | R38: .. | S38: .. | T38: .. | U38: .. | V38: .. | W38: .. | X38: .. | Y38: .. | Z38: .. | AA38: .. | AB38: .. | AC38: .. | AD38: .. | AE38: .. | AF38: ..
A40: Symbol legend:
A41: .. | B41: not available for a specific reference period
A46: Footnotes:
A47: 1 | B47: Age groups refer to the age group of the major income earner.
A48: 2 | B48: Income quintiles are assigned based on equivalized household disposable income, which takes into account differences in household size and composition using a method proposed by the Organization for Economic Co-operation and Development (OECD). The OECD-modified" equivalence scale assigns a value of 1 to the first adult | C48: 0.5 to each additional person aged 14 and over | D48: and 0.3 for all children under 14."
A52: How to cite: Statistics Canada. Table 36-10-0587-01 Distributions of household economic accounts, income, consumption and saving, by characteristic, annual (x 1,000,000)
A53: https://www150.statcan.gc.ca/t1/tbl1/en/tv.action?pid=3610058701

Sheet HH Savings by Income Quintile
A1: Distributions of household economic accounts, income, consumption and saving, by characteristic, annual (x 1,000,000)
A2: Frequency: Annual
A3: Table: 36-10-0587-01 (formerly CANSIM 378-0152)
A4: Release date: 2024-07-17
A5: Geography: Canada
A6: https://www150.statcan.gc.ca/t1/tbl1/en/cv!recreate.action?pid=3610058701&selectedNodeIds=2D1,3D2,3D3,3D4,3D5,3D6,4D1,4D2,4D3,4D4,4D5,4D6,4D7,4D8,4D9,4D10,4D11,4D12,4D13,4D14,4D15,4D16,4D17,4D18,4D19,4D20,4D21,4D22,4D23&checkedLevels=0D1,2D1&refPeriods=19990101,20230101&dimensionLayouts=layout2,layout2,layout2,layout3,layout2&vectorDisplay=false
A9: Geography | B9: Canada
A10: Statistics | B10: Value
A11: Characteristics | B11: All households | AA11: Lowest income quintile 1 | AZ11: Second income quintile 1 | BY11: Third income quintile 1 | CX11: Fourth income quintile 1 | DW11: Highest income quintile 1
A12: Income, consumption and savings | B12: 1999 | C12: 2000 | D12: 2001 | E12: 2002 | F12: 2003 | G12: 2004 | H12: 2005 | I12: 2006 | J12: 2007 | K12: 2008 | L12: 2009 | M12: 2010 | N12: 2011 | O12: 2012 | P12: 2013 | Q12: 2014 | R12: 2015 | S12: 2016 | T12: 2017 | U12: 2018 | V12: 2019 | W12: 2020 | X12: 2021 | Y12: 2022 | Z12: 2023 | AA12: 1999 | AB12: 2000 | AC12: 2001 | AD12: 2002 | AE12: 2003 | AF12: 2004 | AG12: 2005 | AH12: 2006 | AI12: 2007 | AJ12: 2008 | AK12: 2009 | AL12: 2010 | AM12: 2011 | AN12: 2012 | AO12: 2013 | AP12: 2014 | AQ12: 2015 | AR12: 2016 | AS12: 2017 | AT12: 2018 | AU12: 2019 | AV12: 2020 | AW12: 2021 | AX12: 2022 | AY12: 2023 | AZ12: 1999 | BA12: 2000 | BB12: 2001 | BC12: 2002 | BD12: 2003 | BE12: 2004 | BF12: 2005 | BG12: 2006 | BH12: 2007 | BI12: 2008 | BJ12: 2009 | BK12: 2010 | BL12: 2011 | BM12: 2012 | BN12: 2013 | BO12: 2014 | BP12: 2015 | BQ12: 2016 | BR12: 2017 | BS12: 2018 | BT12: 2019 | BU12: 2020 | BV12: 2021 | BW12: 2022 | BX12: 2023 | BY12: 1999 | BZ12: 2000 | CA12: 2001 | CB12: 2002 | CC12: 2003 | CD12: 2004 | CE12: 2005 | CF12: 2006 | CG12: 2007 | CH12: 2008 | CI12: 2009 | CJ12: 2010 | CK12: 2011 | CL12: 2012 | CM12: 2013 | CN12: 2014 | CO12: 2015 | CP12: 2016 | CQ12: 2017 | CR12: 2018 | CS12: 2019 | CT12: 2020 | CU12: 2021 | CV12: 2022 | CW12: 2023 | CX12: 1999 | CY12: 2000 | CZ12: 2001 | DA12: 2002 | DB12: 2003 | DC12: 2004 | DD12: 2005 | DE12: 2006 | DF12: 2007 | DG12: 2008 | DH12: 2009 | DI12: 2010 | DJ12: 2011 | DK12: 2012 | DL12: 2013 | DM12: 2014 | DN12: 2015 | DO12: 2016 | DP12: 2017 | DQ12: 2018 | DR12: 2019 | DS12: 2020 | DT12: 2021 | DU12: 2022 | DV12: 2023 | DW12: 1999 | DX12: 2000 | DY12: 2001 | DZ12: 2002 | EA12: 2003 | EB12: 2004 | EC12: 2005 | ED12: 2006 | EE12: 2007 | EF12: 2008 | EG12: 2009 | EH12: 2010 | EI12: 2011 | EJ12: 2012 | EK12: 2013 | EL12: 2014 | EM12: 2015 | EN12: 2016 | EO12: 2017 | EP12: 2018 | EQ12: 2019 | ER12: 2020 | ES12: 2021 | ET12: 2022 | EU12: 2023
B13: Dollars
A14: Household disposable income | B14: 546261 | C14: 579683 | D14: 615286 | E14: 642584 | F14: 663239 | G14: 695238 | H14: 721510 | I14: 774375 | J14: 816321 | K14: 862404 | L14: 884783 | M14: 928091 | N14: 962102 | O14: 1001254 | P14: 1046791 | Q14: 1081654 | R14: 1129875 | S14: 1132763 | T14: 1189366 | U14: 1224919 | V14: 1280362 | W14: 1387659 | X14: 1435372 | Y14: 1514289 | Z14: 1597953 | AA14: 34499 | AB14: 35458 | AC14: 39157 | AD14: 40052 | AE14: 42088 | AF14: 42850 | AG14: 42545 | AH14: 47335 | AI14: 51170 | AJ14: 52821 | AK14: 55537 | AL14: 58113 | AM14: 61040 | AN14: 65634 | AO14: 65502 | AP14: 67552 | AQ14: 66938 | AR14: 69928 | AS14: 72456 | AT14: 76603 | AU14: 80065 | AV14: 103704 | AW14: 101607 | AX14: 102019 | AY14: 104768 | AZ14: 68716 | BA14: 71662 | BB14: 78344 | BC14: 80977 | BD14: 82309 | BE14: 85376 | BF14: 88958 | BG14: 95636 | BH14: 102488 | BI14: 106771 | BJ14: 109843 | BK14: 116568 | BL14: 117882 | BM14: 125628 | BN14: 128224 | BO14: 133327 | BP14: 138869 | BQ14: 148711 | BR14: 153185 | BS14: 156572 | BT14: 162418 | BU14: 192454 | BV14: 188620 | BW14: 192659 | BX14: 197069 | BY14: 95888 | BZ14: 99140 | CA14: 105164 | CB14: 107920 | CC14: 113036 | CD14: 116754 | CE14: 121051 | CF14: 129762 | CG14: 135299 | CH14: 144380 | CI14: 148085 | CJ14: 158821 | CK14: 163375 | CL14: 169183 | CM14: 177598 | CN14: 182757 | CO14: 198176 | CP14: 201029 | CQ14: 207424 | CR14: 213546 | CS14: 222558 | CT14: 243885 | CU14: 246930 | CV14: 253830 | CW14: 261882 | CX14: 127911 | CY14: 133007 | CZ14: 141954 | DA14: 150479 | DB14: 152643 | DC14: 159714 | DD14: 165687 | DE14: 173866 | DF14: 182443 | DG14: 195169 | DH14: 201645 | DI14: 214499 | DJ14: 225120 | DK14: 232385 | DL14: 243841 | DM14: 253522 | DN14: 260965 | DO14: 262514 | DP14: 277390 | DQ14: 286502 | DR14: 298307 | DS14: 325463 | DT14: 345649 | DU14: 359861 | DV14: 378958 | DW14: 219247 | DX14: 240416 | DY14: 250667 | DZ14: 263156 | EA14: 273163 | EB14: 290544 | EC14: 303269 | ED14: 327776 | EE14: 344921 | EF14: 363263 | EG14: 369673 | EH14: 380090 | EI14: 394685 | EJ14: 408424 | EK14: 431626 | EL14: 444496 | EM14: 464927 | EN14: 450581 | EO14: 478911 | EP14: 491696 | EQ14: 517014 | ER14: 522153 | ES14: 552566 | ET14: 605920 | EU14: 655277
A15: Compensation of employees | B15: 506817 | C15: 551460 | D15: 574278 | E15: 596782 | F15: 620600 | G15: 656154 | H15: 692609 | I15: 737321 | J15: 782564 | K15: 818108 | L15: 810556 | M15: 835940 | N15: 881146 | O15: 921492 | P15: 959181 | Q15: 996247 | R15: 1024742 | S15: 1024142 | T15: 1066523 | U15: 1122304 | V15: 1168597 | W15: 1155842 | X15: 1264002 | Y15: 1380064 | Z15: 1470746 | AA15: 16091 | AB15: 17351 | AC15: 18028 | AD15: 17444 | AE15: 18397 | AF15: 19411 | AG15: 19129 | AH15: 22137 | AI15: 24731 | AJ15: 25695 | AK15: 24060 | AL15: 23787 | AM15: 26172 | AN15: 28682 | AO15: 29118 | AP15: 27939 | AQ15: 27967 | AR15: 28220 | AS15: 29147 | AT15: 32486 | AU15: 33932 | AV15: 27985 | AW15: 35505 | AX15: 35913 | AY15: 43870 | AZ15: 45131 | BA15: 49604 | BB15: 53358 | BC15: 53552 | BD15: 53427 | BE15: 54545 | BF15: 58137 | BG15: 65523 | BH15: 70978 | BI15: 75710 | BJ15: 71926 | BK15: 74222 | BL15: 75983 | BM15: 84034 | BN15: 84144 | BO15: 89078 | BP15: 92799 | BQ15: 100619 | BR15: 99739 | BS15: 100033 | BT15: 103367 | BU15: 98943 | BV15: 111842 | BW15: 118032 | BX15: 122746 | BY15: 85888 | BZ15: 89161 | CA15: 95160 | CB15: 92689 | CC15: 101441 | CD15: 103943 | CE15: 110991 | CF15: 118711 | CG15: 125011 | CH15: 135058 | CI15: 133080 | CJ15: 140568 | CK15: 146138 | CL15: 152634 | CM15: 158649 | CN15: 162306 | CO15: 176681 | CP15: 174569 | CQ15: 176585 | CR15: 182506 | CS15: 190096 | CT15: 188246 | CU15: 204102 | CV15: 222511 | CW15: 230988 | CX15: 136198 | CY15: 143491 | CZ15: 150491 | DA15: 159283 | DB15: 162429 | DC15: 172580 | DD15: 180492 | DE15: 188862 | DF15: 197852 | DG15: 207588 | DH15: 210410 | DI15: 219689 | DJ15: 235318 | DK15: 244710 | DL15: 255984 | DM15: 266164 | DN15: 267578 | DO15: 269225 | DP15: 283545 | DQ15: 297677 | DR15: 312080 | DS15: 310976 | DT15: 335984 | DU15: 369564 | DV15: 400903 | DW15: 223509 | DX15: 251853 | DY15: 257241 | DZ15: 273814 | EA15: 284906 | EB15: 305675 | EC15: 323860 | ED15: 342088 | EE15: 363992 | EF15: 374057 | EG15: 371080 | EH15: 377674 | EI15: 397535 | EJ15: 411432 | EK15: 431286 | EL15: 450760 | EM15: 459717 | EN15: 451509 | EO15: 477507 | EP15: 509602 | EQ15: 529122 | ER15: 529692 | ES15: 576569 | ET15: 634044 | EU15: 672239
A16: Net mixed income | B16: 97809 | C16: 102754 | D16: 107636 | E16: 111748 | F16: 116533 | G16: 122301 | H16: 125661 | I16: 131002 | J16: 138842 | K16: 143917 | L16: 144671 | M16: 151130 | N16: 157679 | O16: 162931 | P16: 167712 | Q16: 172078 | R16: 177994 | S16: 183581 | T16: 190323 | U16: 195618 | V16: 207999 | W16: 207305 | X16: 214041 | Y16: 235642 | Z16: 257594 | AA16: 5520 | AB16: 6167 | AC16: 5849 | AD16: 6579 | AE16: 7190 | AF16: 7127 | AG16: 7284 | AH16: 8876 | AI16: 8814 | AJ16: 8749 | AK16: 8983 | AL16: 9518 | AM16: 9281 | AN16: 9249 | AO16: 9266 | AP16: 10572 | AQ16: 9568 | AR16: 11416 | AS16: 12270 | AT16: 13427 | AU16: 14407 | AV16: 13969 | AW16: 14947 | AX16: 17023 | AY16: 18138 | AZ16: 11379 | BA16: 12020 | BB16: 12933 | BC16: 13207 | BD16: 13507 | BE16: 14171 | BF16: 14556 | BG16: 14720 | BH16: 17084 | BI16: 16044 | BJ16: 16790 | BK16: 19627 | BL16: 18861 | BM16: 20321 | BN16: 20541 | BO16: 22110 | BP16: 22750 | BQ16: 25027 | BR16: 26457 | BS16: 28089 | BT16: 29404 | BU16: 27352 | BV16: 28568 | BW16: 32859 | BX16: 35824 | BY16: 16043 | BZ16: 17238 | CA16: 16827 | CB16: 18749 | CC16: 18486 | CD16: 18446 | CE16: 18094 | CF16: 19477 | CG16: 20916 | CH16: 23023 | CI16: 22638 | CJ16: 23240 | CK16: 24680 | CL16: 27806 | CM16: 29007 | CN16: 31402 | CO16: 31981 | CP16: 31857 | CQ16: 33410 | CR16: 34104 | CS16: 36805 | CT16: 35580 | CU16: 37811 | CV16: 40568 | CW16: 45119 | CX16: 20655 | CY16: 22030 | CZ16: 22694 | DA16: 23602 | DB16: 22836 | DC16: 24012 | DD16: 25844 | DE16: 26013 | DF16: 28969 | DG16: 30871 | DH16: 30196 | DI16: 31497 | DJ16: 34620 | DK16: 36616 | DL16: 38909 | DM16: 38209 | DN16: 39976 | DO16: 41847 | DP16: 43449 | DQ16: 45322 | DR16: 47740 | DS16: 48450 | DT16: 48359 | DU16: 53114 | DV16: 58312 | DW16: 44212 | DX16: 45299 | DY16: 49333 | DZ16: 49611 | EA16: 54514 | EB16: 58545 | EC16: 59883 | ED16: 61916 | EE16: 63059 | EF16: 65230 | EG16: 66064 | EH16: 67248 | EI16: 70237 | EJ16: 68939 | EK16: 69989 | EL16: 69785 | EM16: 73719 | EN16: 73434 | EO16: 74737 | EP16: 74676 | EQ16: 79643 | ER16: 81954 | ES16: 84356 | ET16: 92078 | EU16: 100202
A17: Property income received | B17: 111791 | C17: 117332 | D17: 116942 | E17: 109346 | F17: 108675 | G17: 113209 | H17: 122970 | I17: 137105 | J17: 153667 | K17: 160013 | L17: 152106 | M17: 152519 | N17: 162165 | O17: 170336 | P17: 175342 | Q17: 181876 | R17: 198218 | S17: 189502 | T17: 202189 | U17: 202278 | V17: 217587 | W17: 212698 | X17: 221163 | Y17: 244788 | Z17: 294027 | AA17: 3163 | AB17: 4381 | AC17: 3294 | AD17: 3448 | AE17: 2972 | AF17: 3245 | AG17: 3985 | AH17: 4103 | AI17: 4984 | AJ17: 4693 | AK17: 3943 | AL17: 3850 | AM17: 4448 | AN17: 4941 | AO17: 4739 | AP17: 4846 | AQ17: 4960 | AR17: 5292 | AS17: 5879 | AT17: 6346 | AU17: 6700 | AV17: 7183 | AW17: 7896 | AX17: 8066 | AY17: 10205 | AZ17: 7935 | BA17: 9168 | BB17: 7868 | BC17: 7592 | BD17: 7502 | BE17: 8047 | BF17: 8986 | BG17: 9404 | BH17: 10412 | BI17: 10216 | BJ17: 8779 | BK17: 8375 | BL17: 9819 | BM17: 10729 | BN17: 10153 | BO17: 11371 | BP17: 10886 | BQ17: 11042 | BR17: 11393 | BS17: 11666 | BT17: 12552 | BU17: 13139 | BV17: 13883 | BW17: 14933 | BX17: 16534 | BY17: 14843 | BZ17: 14781 | CA17: 15104 | CB17: 14125 | CC17: 14028 | CD17: 15088 | CE17: 15439 | CF17: 15937 | CG17: 16896 | CH17: 17465 | CI17: 16761 | CJ17: 16782 | CK17: 18386 | CL17: 18833 | CM17: 17691 | CN17: 19034 | CO17: 20223 | CP17: 20935 | CQ17: 21176 | CR17: 21891 | CS17: 22952 | CT17: 23328 | CU17: 24456 | CV17: 25996 | CW17: 28836 | CX17: 22973 | CY17: 22418 | CZ17: 23019 | DA17: 21089 | DB17: 21940 | DC17: 21379 | DD17: 23626 | DE17: 24637 | DF17: 27069 | DG17: 28270 | DH17: 27675 | DI17: 28518 | DJ17: 28510 | DK17: 30598 | DL17: 31055 | DM17: 32002 | DN17: 33797 | DO17: 33479 | DP17: 34224 | DQ17: 35476 | DR17: 37514 | DS17: 38264 | DT17: 38914 | DU17: 42496 | DV17: 48728 | DW17: 62877 | DX17: 66584 | DY17: 67657 | DZ17: 63092 | EA17: 62233 | EB17: 65450 | EC17: 70934 | ED17: 83024 | EE17: 94306 | EF17: 99369 | EG17: 94948 | EH17: 94994 | EI17: 101002 | EJ17: 105235 | EK17: 111704 | EL17: 114623 | EM17: 128352 | EN17: 118754 | EO17: 129517 | EP17: 126899 | EQ17: 137869 | ER17: 130784 | ES17: 136014 | ET17: 153297 | EU17: 189723
A18: Less: property income paid | B18: 36406 | C18: 41597 | D18: 41204 | E18: 37300 | F18: 39081 | G18: 40156 | H18: 43309 | I18: 52632 | J18: 61313 | K18: 63921 | L18: 55559 | M18: 54143 | N18: 54580 | O18: 55598 | P18: 56232 | Q18: 55857 | R18: 56033 | S18: 56405 | T18: 60186 | U18: 70213 | V18: 79808 | W18: 73097 | X18: 66808 | Y18: 84518 | Z18: 132778 | AA18: 3899 | AB18: 4766 | AC18: 4661 | AD18: 4255 | AE18: 4458 | AF18: 4705 | AG18: 5220 | AH18: 6892 | AI18: 7393 | AJ18: 7634 | AK18: 6505 | AL18: 6100 | AM18: 6583 | AN18: 7005 | AO18: 6954 | AP18: 6677 | AQ18: 6953 | AR18: 6906 | AS18: 7423 | AT18: 8919 | AU18: 10359 | AV18: 9515 | AW18: 8715 | AX18: 11673 | AY18: 19746 | AZ18: 5545 | BA18: 6362 | BB18: 6205 | BC18: 5650 | BD18: 5808 | BE18: 5949 | BF18: 6901 | BG18: 8280 | BH18: 9509 | BI18: 9885 | BJ18: 8128 | BK18: 8146 | BL18: 8294 | BM18: 8796 | BN18: 8898 | BO18: 8376 | BP18: 8578 | BQ18: 8982 | BR18: 9515 | BS18: 10961 | BT18: 12324 | BU18: 11750 | BV18: 10674 | BW18: 13468 | BX18: 20850 | BY18: 7058 | BZ18: 8048 | CA18: 7870 | CB18: 7005 | CC18: 7416 | CD18: 7615 | CE18: 8051 | CF18: 9803 | CG18: 11571 | CH18: 12215 | CI18: 10875 | CJ18: 10151 | CK18: 10522 | CL18: 10540 | CM18: 10649 | CN18: 10793 | CO18: 11082 | CP18: 10650 | CQ18: 11200 | CR18: 12927 | CS18: 14779 | CT18: 14072 | CU18: 13204 | CV18: 16436 | CW18: 24762 | CX18: 8780 | CY18: 10223 | CZ18: 10080 | DA18: 9196 | DB18: 9111 | DC18: 9459 | DD18: 10299 | DE18: 11754 | DF18: 14225 | DG18: 14568 | DH18: 13034 | DI18: 12986 | DJ18: 12949 | DK18: 13150 | DL18: 13370 | DM18: 13326 | DN18: 13220 | DO18: 13661 | DP18: 14563 | DQ18: 17027 | DR18: 19293 | DS18: 17371 | DT18: 15140 | DU18: 19284 | DV18: 30926 | DW18: 11124 | DX18: 12198 | DY18: 12388 | DZ18: 11194 | EA18: 12288 | EB18: 12428 | EC18: 12838 | ED18: 15903 | EE18: 18615 | EF18: 19619 | EG18: 17017 | EH18: 16760 | EI18: 16232 | EJ18: 16107 | EK18: 16361 | EL18: 16685 | EM18: 16200 | EN18: 16206 | EO18: 17485 | EP18: 20379 | EQ18: 23053 | ER18: 20389 | ES18: 19075 | ET18: 23657 | EU18: 36494
A19: Current transfers received | B19: 129447 | C19: 131513 | D19: 145676 | E19: 147574 | F19: 153189 | G19: 160966 | H19: 165651 | I19: 182779 | J19: 194544 | K19: 204188 | L19: 218275 | M19: 232400 | N19: 236877 | O19: 246062 | P19: 258527 | Q19: 266153 | R19: 288200 | S19: 307078 | T19: 320918 | U19: 334066 | V19: 346107 | W19: 468952 | X19: 443036 | Y19: 422465 | Z19: 441837 | AA19: 23641 | AB19: 25979 | AC19: 27588 | AD19: 28524 | AE19: 29546 | AF19: 29690 | AG19: 31464 | AH19: 33257 | AI19: 36711 | AJ19: 37993 | AK19: 40689 | AL19: 42485 | AM19: 44660 | AN19: 45979 | AO19: 47254 | AP19: 48504 | AQ19: 49556 | AR19: 52356 | AS19: 55284 | AT19: 57915 | AU19: 60978 | AV19: 90336 | AW19: 80483 | AX19: 82817 | AY19: 86545 | AZ19: 30964 | BA19: 31712 | BB19: 34297 | BC19: 35833 | BD19: 37676 | BE19: 40166 | BF19: 42095 | BG19: 44252 | BH19: 46542 | BI19: 47966 | BJ19: 50199 | BK19: 52718 | BL19: 53590 | BM19: 56719 | BN19: 58321 | BO19: 59088 | BP19: 61644 | BQ19: 64641 | BR19: 68451 | BS19: 71893 | BT19: 75514 | BU19: 109816 | BV19: 98963 | BW19: 97436 | BX19: 102058 | BY19: 28305 | BZ19: 28850 | CA19: 31176 | CB19: 32474 | CC19: 33134 | CD19: 36703 | CE19: 37135 | CF19: 40277 | CG19: 40907 | CH19: 42070 | CI19: 45103 | CJ19: 48774 | CK19: 50263 | CL19: 50628 | CM19: 53532 | CN19: 54759 | CO19: 60771 | CP19: 67168 | CQ19: 70185 | CR19: 73260 | CS19: 76191 | CT19: 99499 | CU19: 93647 | CV19: 87696 | CW19: 93642 | CX19: 23863 | CY19: 23419 | CZ19: 27446 | DA19: 27034 | DB19: 28825 | DC19: 29009 | DD19: 29803 | DE19: 34135 | DF19: 37628 | DG19: 40683 | DH19: 42688 | DI19: 45911 | DJ19: 45575 | DK19: 45886 | DL19: 50151 | DM19: 52750 | DN19: 58934 | DO19: 61639 | DP19: 63859 | DQ19: 65921 | DR19: 67264 | DS19: 90394 | DT19: 89723 | DU19: 81094 | DV19: 81370 | DW19: 22674 | DX19: 21553 | DY19: 25169 | DZ19: 23709 | EA19: 24008 | EB19: 25398 | EC19: 25154 | ED19: 30858 | EE19: 32756 | EF19: 35476 | EG19: 39596 | EH19: 42512 | EI19: 42789 | EJ19: 46850 | EK19: 49269 | EL19: 51052 | EM19: 57295 | EN19: 61274 | EO19: 63139 | EP19: 65077 | EQ19: 66160 | ER19: 78907 | ES19: 80220 | ET19: 73422 | EU19: 78222
A20: Less: current transfers paid | B20: 263197 | C20: 281779 | D20: 288042 | E20: 285566 | F20: 296677 | G20: 317236 | H20: 342072 | I20: 361200 | J20: 391983 | K20: 399901 | L20: 385266 | M20: 389755 | N20: 421185 | O20: 443969 | P20: 457739 | Q20: 478843 | R20: 503246 | S20: 515135 | T20: 530401 | U20: 559134 | V20: 580120 | W20: 584041 | X20: 640062 | Y20: 684152 | Z20: 733473 | AA20: 10017 | AB20: 13654 | AC20: 10941 | AD20: 11688 | AE20: 11559 | AF20: 11918 | AG20: 14097 | AH20: 14146 | AI20: 16677 | AJ20: 16675 | AK20: 15633 | AL20: 15427 | AM20: 16938 | AN20: 16212 | AO20: 17921 | AP20: 17632 | AQ20: 18160 | AR20: 20450 | AS20: 22701 | AT20: 24652 | AU20: 25593 | AV20: 26254 | AW20: 28509 | AX20: 30127 | AY20: 34244 | AZ20: 21148 | BA20: 24480 | BB20: 23907 | BC20: 23557 | BD20: 23995 | BE20: 25604 | BF20: 27915 | BG20: 29983 | BH20: 33019 | BI20: 33280 | BJ20: 29723 | BK20: 30228 | BL20: 32077 | BM20: 37379 | BN20: 36037 | BO20: 39944 | BP20: 40632 | BQ20: 43636 | BR20: 43340 | BS20: 44148 | BT20: 46095 | BU20: 45046 | BV20: 53962 | BW20: 57133 | BX20: 59242 | BY20: 42133 | BZ20: 42842 | CA20: 45233 | CB20: 43112 | CC20: 46637 | CD20: 49811 | CE20: 52557 | CF20: 54837 | CG20: 56860 | CH20: 61021 | CI20: 58622 | CJ20: 60392 | CK20: 65570 | CL20: 70178 | CM20: 70632 | CN20: 73951 | CO20: 80398 | CP20: 82850 | CQ20: 82732 | CR20: 85288 | CS20: 88707 | CT20: 88696 | CU20: 99882 | CV20: 106505 | CW20: 111942 | CX20: 66998 | CY20: 68128 | CZ20: 71616 | DA20: 71333 | DB20: 74276 | DC20: 77807 | DD20: 83779 | DE20: 88027 | DF20: 94850 | DG20: 97675 | DH20: 96290 | DI20: 98130 | DJ20: 105954 | DK20: 112275 | DL20: 118888 | DM20: 122277 | DN20: 126100 | DO20: 130015 | DP20: 133124 | DQ20: 140867 | DR20: 146998 | DS20: 145250 | DT20: 152191 | DU20: 167123 | DV20: 179429 | DW20: 122901 | DX20: 132675 | DY20: 136345 | DZ20: 135876 | EA20: 140210 | EB20: 152096 | EC20: 163724 | ED20: 174207 | EE20: 190577 | EF20: 191250 | EG20: 184998 | EH20: 185578 | EI20: 200646 | EJ20: 207925 | EK20: 214261 | EL20: 225039 | EM20: 237956 | EN20: 238184 | EO20: 248504 | EP20: 264179 | EQ20: 272727 | ER20: 278795 | ES20: 305518 | ET20: 323264 | EU20: 348616
A21: Household final consumption expenditure (HFCE) | B21: 553506 | C21: 589026 | D21: 615180 | E21: 651605 | F21: 681206 | G21: 712940 | H21: 752414 | I21: 793640 | J21: 842023 | K21: 878505 | L21: 881692 | M21: 926716 | N21: 967078 | O21: 998055 | P21: 1038084 | Q21: 1086255 | R21: 1122080 | S21: 1153666 | T21: 1209153 | U21: 1260445 | V21: 1300815 | W21: 1225995 | X21: 1327587 | Y21: 1473589 | Z21: 1553214 | AA21: 57126 | AB21: 62127 | AC21: 61497 | AD21: 67648 | AE21: 69743 | AF21: 76448 | AG21: 83690 | AH21: 94015 | AI21: 99896 | AJ21: 105814 | AK21: 105398 | AL21: 112283 | AM21: 114927 | AN21: 121217 | AO21: 128240 | AP21: 135163 | AQ21: 138251 | AR21: 143573 | AS21: 151236 | AT21: 159168 | AU21: 173945 | AV21: 158364 | AW21: 176971 | AX21: 195163 | AY21: 205427 | AZ21: 84504 | BA21: 87935 | BB21: 92400 | BC21: 98410 | BD21: 102693 | BE21: 108802 | BF21: 114037 | BG21: 120479 | BH21: 130346 | BI21: 137284 | BJ21: 136377 | BK21: 142689 | BL21: 148671 | BM21: 153368 | BN21: 156293 | BO21: 163383 | BP21: 170062 | BQ21: 174783 | BR21: 183228 | BS21: 194248 | BT21: 206202 | BU21: 194231 | BV21: 212641 | BW21: 234998 | BX21: 249018 | BY21: 106763 | BZ21: 111960 | CA21: 119570 | CB21: 124396 | CC21: 129371 | CD21: 133399 | CE21: 140516 | CF21: 147271 | CG21: 154601 | CH21: 160095 | CI21: 161369 | CJ21: 170930 | CK21: 179240 | CL21: 186347 | CM21: 192252 | CN21: 204423 | CO21: 209675 | CP21: 214098 | CQ21: 223446 | CR21: 236067 | CS21: 245864 | CT21: 235869 | CU21: 259157 | CV21: 288485 | CW21: 302551 | CX21: 126868 | CY21: 135270 | CZ21: 143166 | DA21: 149836 | DB21: 160063 | DC21: 160775 | DD21: 170497 | DE21: 178062 | DF21: 187486 | DG21: 197118 | DH21: 198531 | DI21: 208781 | DJ21: 221424 | DK21: 223892 | DL21: 236476 | DM21: 243854 | DN21: 252687 | DO21: 260229 | DP21: 272547 | DQ21: 281152 | DR21: 286822 | DS21: 272322 | DT21: 295376 | DU21: 324498 | DV21: 342006 | DW21: 178245 | DX21: 191734 | DY21: 198547 | DZ21: 211315 | EA21: 219336 | EB21: 233516 | EC21: 243674 | ED21: 253813 | EE21: 269694 | EF21: 278194 | EG21: 280017 | EH21: 292033 | EI21: 302816 | EJ21: 313231 | EK21: 324823 | EL21: 339432 | EM21: 351405 | EN21: 360983 | EO21: 378696 | EP21: 389810 | EQ21: 387982 | ER21: 365209 | ES21: 383442 | ET21: 430445 | EU21: 454212
A22: Food and non-alcoholic beverages | B22: 53875 | C22: 56454 | D22: 59698 | E22: 62227 | F22: 64646 | G22: 67044 | H22: 69305 | I22: 72227 | J22: 75314 | K22: 79394 | L22: 84166 | M22: 86223 | N22: 89033 | O22: 91619 | P22: 94538 | Q22: 98670 | R22: 102658 | S22: 105137 | T22: 109628 | U22: 111574 | V22: 115896 | W22: 127336 | X22: 129048 | Y22: 137650 | Z22: 147899 | AA22: 7821 | AB22: 8077 | AC22: 8310 | AD22: 8928 | AE22: 9095 | AF22: 9725 | AG22: 10157 | AH22: 11250 | AI22: 11388 | AJ22: 12294 | AK22: 12831 | AL22: 13105 | AM22: 13290 | AN22: 13973 | AO22: 14527 | AP22: 14838 | AQ22: 15560 | AR22: 16409 | AS22: 16987 | AT22: 17308 | AU22: 18385 | AV22: 19849 | AW22: 19792 | AX22: 21207 | AY22: 22793 | AZ22: 10028 | BA22: 10375 | BB22: 11147 | BC22: 11410 | BD22: 12073 | BE22: 12445 | BF22: 12832 | BG22: 13259 | BH22: 14026 | BI22: 14579 | BJ22: 15568 | BK22: 15792 | BL22: 16353 | BM22: 16617 | BN22: 16709 | BO22: 17295 | BP22: 17813 | BQ22: 18467 | BR22: 19198 | BS22: 19732 | BT22: 21185 | BU22: 23439 | BV22: 23871 | BW22: 25615 | BX22: 27421 | BY22: 11176 | BZ22: 11540 | CA22: 12269 | CB22: 12639 | CC22: 13115 | CD22: 13902 | CE22: 14182 | CF22: 14514 | CG22: 14980 | CH22: 15532 | CI22: 16701 | CJ22: 17026 | CK22: 17167 | CL22: 18117 | CM22: 18796 | CN22: 20481 | CO22: 21304 | CP22: 21382 | CQ22: 22683 | CR22: 23030 | CS22: 23880 | CT22: 26461 | CU22: 27366 | CV22: 29019 | CW22: 31258 | CX22: 11422 | CY22: 12205 | CZ22: 13011 | DA22: 13443 | DB22: 14454 | DC22: 14605 | DD22: 15560 | DE22: 16008 | DF22: 16635 | DG22: 17590 | DH22: 18580 | DI22: 19142 | DJ22: 20001 | DK22: 20066 | DL22: 21143 | DM22: 21882 | DN22: 22936 | DO22: 23393 | DP22: 24279 | DQ22: 24569 | DR22: 25506 | DS22: 28180 | DT22: 29645 | DU22: 31495 | DV22: 33825 | DW22: 13428 | DX22: 14257 | DY22: 14961 | DZ22: 15807 | EA22: 15909 | EB22: 16367 | EC22: 16574 | ED22: 17196 | EE22: 18285 | EF22: 19399 | EG22: 20486 | EH22: 21158 | EI22: 22222 | EJ22: 22846 | EK22: 23363 | EL22: 24174 | EM22: 25045 | EN22: 25486 | EO22: 26481 | EP22: 26935 | EQ22: 26940 | ER22: 29407 | ES22: 28374 | ET22: 30314 | EU22: 32601
A23: Alcoholic beverages and tobacco | B23: 24905 | C23: 25900 | D23: 27713 | E23: 31002 | F23: 33087 | G23: 34003 | H23: 34130 | I23: 34294 | J23: 34907 | K23: 35605 | L23: 36033 | M23: 37477 | N23: 38506 | O23: 39828 | P23: 40679 | Q23: 42050 | R23: 43354 | S23: 44523 | T23: 45376 | U23: 48672 | V23: 48584 | W23: 51182 | X23: 51273 | Y23: 51275 | Z23: 50575 | AA23: 2827 | AB23: 2953 | AC23: 3018 | AD23: 3390 | AE23: 3891 | AF23: 4054 | AG23: 4177 | AH23: 4464 | AI23: 4639 | AJ23: 4736 | AK23: 4790 | AL23: 4897 | AM23: 4695 | AN23: 4851 | AO23: 4919 | AP23: 5459 | AQ23: 5889 | AR23: 6165 | AS23: 6202 | AT23: 6723 | AU23: 6557 | AV23: 7091 | AW23: 7021 | AX23: 7046 | AY23: 6999 | AZ23: 4270 | BA23: 4474 | BB23: 4676 | BC23: 5264 | BD23: 5555 | BE23: 5963 | BF23: 5825 | BG23: 5680 | BH23: 5884 | BI23: 5865 | BJ23: 6018 | BK23: 6275 | BL23: 6434 | BM23: 6986 | BN23: 6832 | BO23: 7396 | BP23: 7401 | BQ23: 7324 | BR23: 7521 | BS23: 8196 | BT23: 8990 | BU23: 8260 | BV23: 8209 | BW23: 8608 | BX23: 8452 | BY23: 5195 | BZ23: 5309 | CA23: 5855 | CB23: 6570 | CC23: 6953 | CD23: 7007 | CE23: 6903 | CF23: 7038 | CG23: 7091 | CH23: 7365 | CI23: 7174 | CJ23: 7503 | CK23: 7517 | CL23: 7772 | CM23: 8023 | CN23: 8391 | CO23: 8314 | CP23: 8539 | CQ23: 8900 | CR23: 9824 | CS23: 9019 | CT23: 10944 | CU23: 11463 | CV23: 11007 | CW23: 10857 | CX23: 5729 | CY23: 5963 | CZ23: 6470 | DA23: 7106 | DB23: 7534 | DC23: 7660 | DD23: 7682 | DE23: 7661 | DF23: 7923 | DG23: 8049 | DH23: 8269 | DI23: 8428 | DJ23: 8883 | DK23: 8621 | DL23: 8996 | DM23: 9274 | DN23: 9930 | DO23: 10074 | DP23: 10134 | DQ23: 10774 | DR23: 10967 | DS23: 11571 | DT23: 11653 | DU23: 11786 | DV23: 11660 | DW23: 6884 | DX23: 7201 | DY23: 7694 | DZ23: 8672 | EA23: 9154 | EB23: 9319 | EC23: 9543 | ED23: 9451 | EE23: 9370 | EF23: 9590 | EG23: 9782 | EH23: 10374 | EI23: 10977 | EJ23: 11598 | EK23: 11909 | EL23: 11530 | EM23: 11820 | EN23: 12421 | EO23: 12619 | EP23: 13155 | EQ23: 13051 | ER23: 13316 | ES23: 12927 | ET23: 12828 | EU23: 12607
A24: Clothing and footwear | B24: 27682 | C24: 29055 | D24: 30229 | E24: 31099 | F24: 31763 | G24: 32559 | H24: 33712 | I24: 35512 | J24: 37171 | K24: 37507 | L24: 36964 | M24: 38677 | N24: 40029 | O24: 41119 | P24: 42358 | Q24: 44626 | R24: 47299 | S24: 47876 | T24: 49289 | U24: 61997 | V24: 63580 | W24: 51152 | X24: 59105 | Y24: 71209 | Z24: 73807 | AA24: 2549 | AB24: 2786 | AC24: 2939 | AD24: 3170 | AE24: 3062 | AF24: 3509 | AG24: 3782 | AH24: 4277 | AI24: 4536 | AJ24: 4461 | AK24: 4233 | AL24: 4539 | AM24: 4572 | AN24: 5180 | AO24: 5632 | AP24: 5872 | AQ24: 6360 | AR24: 6745 | AS24: 6839 | AT24: 8938 | AU24: 10360 | AV24: 7405 | AW24: 8308 | AX24: 10017 | AY24: 10376 | AZ24: 4165 | BA24: 4181 | BB24: 4520 | BC24: 4731 | BD24: 4698 | BE24: 4907 | BF24: 4918 | BG24: 5242 | BH24: 5559 | BI24: 5714 | BJ24: 5508 | BK24: 5602 | BL24: 6249 | BM24: 6525 | BN24: 6481 | BO24: 6606 | BP24: 7336 | BQ24: 7539 | BR24: 7618 | BS24: 9585 | BT24: 10472 | BU24: 7408 | BV24: 8856 | BW24: 10590 | BX24: 11096 | BY24: 5109 | BZ24: 5285 | CA24: 5671 | CB24: 5717 | CC24: 5893 | CD24: 6125 | CE24: 6383 | CF24: 6609 | CG24: 6732 | CH24: 6679 | CI24: 6653 | CJ24: 7032 | CK24: 7496 | CL24: 7447 | CM24: 7635 | CN24: 8254 | CO24: 8640 | CP24: 8945 | CQ24: 9222 | CR24: 11483 | CS24: 11385 | CT24: 9866 | CU24: 11622 | CV24: 14127 | CW24: 14476 | CX24: 6309 | CY24: 6856 | CZ24: 7104 | DA24: 7284 | DB24: 7562 | DC24: 7331 | DD24: 7651 | DE24: 7970 | DF24: 8156 | DG24: 8398 | DH24: 8542 | DI24: 9232 | DJ24: 9158 | DK24: 9048 | DL24: 9288 | DM24: 10066 | DN24: 10607 | DO24: 10444 | DP24: 10781 | DQ24: 13512 | DR24: 12952 | DS24: 10554 | DT24: 12371 | DU24: 14680 | DV24: 15175 | DW24: 9550 | DX24: 9947 | DY24: 9995 | DZ24: 10197 | EA24: 10548 | EB24: 10687 | EC24: 10978 | ED24: 11414 | EE24: 12188 | EF24: 12255 | EG24: 12028 | EH24: 12272 | EI24: 12554 | EJ24: 12919 | EK24: 13322 | EL24: 13828 | EM24: 14356 | EN24: 14203 | EO24: 14829 | EP24: 18479 | EQ24: 18411 | ER24: 15919 | ES24: 17948 | ET24: 21795 | EU24: 22683
A25: Housing, water, electricity, gas and other fuels | B25: 127461 | C25: 133925 | D25: 139341 | E25: 145400 | F25: 153520 | G25: 160413 | H25: 168562 | I25: 177060 | J25: 188322 | K25: 200145 | L25: 205828 | M25: 214534 | N25: 224318 | O25: 232923 | P25: 244457 | Q25: 257191 | R25: 266997 | S25: 275833 | T25: 288655 | U25: 275918 | V25: 290097 | W25: 302209 | X25: 314641 | Y25: 340198 | Z25: 366271 | AA25: 15277 | AB25: 16001 | AC25: 16335 | AD25: 17855 | AE25: 18754 | AF25: 20161 | AG25: 21102 | AH25: 23031 | AI25: 24535 | AJ25: 26637 | AK25: 27046 | AL25: 29554 | AM25: 30268 | AN25: 31713 | AO25: 33361 | AP25: 35472 | AQ25: 36447 | AR25: 37429 | AS25: 39079 | AT25: 36770 | AU25: 38101 | AV25: 40575 | AW25: 42747 | AX25: 46200 | AY25: 49799 | AZ25: 20683 | BA25: 21242 | BB25: 22069 | BC25: 23992 | BD25: 25111 | BE25: 26078 | BF25: 27347 | BG25: 28118 | BH25: 30577 | BI25: 32737 | BJ25: 33347 | BK25: 34485 | BL25: 36548 | BM25: 37208 | BN25: 38740 | BO25: 40396 | BP25: 42237 | BQ25: 43579 | BR25: 44511 | BS25: 43401 | BT25: 46347 | BU25: 49408 | BV25: 51716 | BW25: 55679 | BX25: 59898 | BY25: 24445 | BZ25: 26190 | CA25: 27895 | CB25: 27997 | CC25: 29689 | CD25: 30483 | CE25: 32135 | CF25: 32899 | CG25: 35255 | CH25: 36928 | CI25: 37728 | CJ25: 40169 | CK25: 41691 | CL25: 43016 | CM25: 45440 | CN25: 48047 | CO25: 49938 | CP25: 50873 | CQ25: 52743 | CR25: 50750 | CS25: 55150 | CT25: 58795 | CU25: 62358 | CV25: 66870 | CW25: 72058 | CX25: 28369 | CY25: 29876 | CZ25: 31199 | DA25: 32429 | DB25: 34798 | DC25: 35098 | DD25: 36871 | DE25: 38573 | DF25: 40884 | DG25: 43829 | DH25: 45578 | DI25: 46250 | DJ25: 48961 | DK25: 50943 | DL25: 54340 | DM25: 56249 | DN25: 57685 | DO25: 60131 | DP25: 63503 | DQ25: 59763 | DR25: 60782 | DS25: 63230 | DT25: 66518 | DU25: 72006 | DV25: 77407 | DW25: 38687 | DX25: 40616 | DY25: 41843 | DZ25: 43127 | EA25: 45168 | EB25: 48593 | EC25: 51107 | ED25: 54439 | EE25: 57071 | EF25: 60014 | EG25: 62129 | EH25: 64076 | EI25: 66850 | EJ25: 70043 | EK25: 72576 | EL25: 77027 | EM25: 80690 | EN25: 83821 | EO25: 88819 | EP25: 85234 | EQ25: 89717 | ER25: 90201 | ES25: 91302 | ET25: 99443 | EU25: 107109
... A36: Household net saving | B36: 24810 | C36: 28603 | D36: 29749 | E36: 20423 | F36: 14409 | G36: 17511 | H36: 10716 | I36: 20714 | J36: 17683 | K36: 29296 | L36: 41148 | M36: 39451 | N36: 41961 | O36: 50651 | P36: 53583 | Q36: 41838 | R36: 51055 | S36: 22235 | T36: 23941 | U36: 7733 | V36: 27023 | W36: 200664 | X36: 150172 | Y36: 81326 | Z36: 88537 | AA36: -22235 | AB36: -25977 | AC36: -22319 | AD36: -28053 | AE36: -27957 | AF36: -33728 | AG36: -41595 | AH36: -47072 | AI36: -48721 | AJ36: -52756 | AK36: -50457 | AL36: -54809 | AM36: -55051 | AN36: -56107 | AO36: -63165 | AP36: -69596 | AQ36: -72707 | AR36: -74228 | AS36: -78779 | AT36: -82939 | AU36: -94385 | AV36: -55930 | AW36: -76088 | AX36: -94207 | AY36: -102715 | AZ36: -14175 | BA36: -13108 | BB36: -13046 | BC36: -17041 | BD36: -20214 | BE36: -23603 | BF36: -24657 | BG36: -23914 | BH36: -26057 | BI36: -28485 | BJ36: -26367 | BK36: -25528 | BL36: -28752 | BM36: -27409 | BN36: -29119 | BO36: -29871 | BP36: -31049 | BQ36: -25432 | BR36: -30199 | BS36: -39027 | BT36: -45330 | BU36: -4672 | BV36: -24796 | BW36: -45973 | BX36: -56703 | BY36: -5477 | BZ36: -7081 | CA36: -9881 | CB36: -13337 | CC36: -12024 | CD36: -12303 | CE36: -13879 | CF36: -12200 | CG36: -13564 | CH36: -8282 | CI36: -7917 | CJ36: -6913 | CK36: -9392 | CL36: -9994 | CM36: -9177 | CN36: -14879 | CO36: -4749 | CP36: -7852 | CQ36: -11406 | CR36: -19275 | CS36: -19360 | CT36: 12830 | CU36: -5634 | CV36: -31440 | CW36: -37724 | CX36: 11790 | CY36: 9201 | CZ36: 8785 | DA36: 11099 | DB36: 3695 | DC36: 11021 | DD36: 10119 | DE36: 10304 | DF36: 9453 | DG36: 13056 | DH36: 16422 | DI36: 20000 | DJ36: 21343 | DK36: 26116 | DL36: 27030 | DM36: 27757 | DN36: 24909 | DO36: 19630 | DP36: 22331 | DQ36: 23521 | DR36: 31569 | DS36: 70638 | DT36: 66370 | DU36: 53470 | DV36: 58069 | DW36: 54907 | DX36: 65568 | DY36: 66210 | DZ36: 67755 | EA36: 70909 | EB36: 76124 | EC36: 80728 | ED36: 93596 | EE36: 96572 | EF36: 105763 | EG36: 109467 | EH36: 106701 | EI36: 113813 | EJ36: 118045 | EK36: 128014 | EL36: 128427 | EM36: 134651 | EN36: 110117 | EO36: 121994 | EP36: 125453 | EQ36: 154529 | ER36: 177798 | ES36: 190320 | ET36: 199476 | EU36: 227611

Sheet HH Savings by Age
A1: Distributions of household economic accounts, income, consumption and saving, by characteristic, annual (x 1,000,000)
A2: Frequency: Annual
A3: Table: 36-10-0587-01 (formerly CANSIM 378-0152)
A4: Release date: 2024-07-17
A5: Geography: Canada
A9: Geography | B9: Canada
A10: Statistics | B10: Value
A11: Characteristics | B11: All households | AA11: Less than 35 years 1 | AZ11: 35 to 44 years 1 | BY11: 45 to 54 years 1 | CX11: 55 to 64 years 1 | DW11: 65 years and over 1
A12: Income, consumption and savings | B12: 1999 | C12: 2000 | D12: 2001 | E12: 2002 | F12: 2003 | G12: 2004 | H12: 2005 | I12: 2006 | J12: 2007 | K12: 2008 | L12: 2009 | M12: 2010 | N12: 2011 | O12: 2012 | P12: 2013 | Q12: 2014 | R12: 2015 | S12: 2016 | T12: 2017 | U12: 2018 | V12: 2019 | W12: 2020 | X12: 2021 | Y12: 2022 | Z12: 2023 | AA12: 1999 | AB12: 2000 | AC12: 2001 | AD12: 2002 | AE12: 2003 | AF12: 2004 | AG12: 2005 | AH12: 2006 | AI12: 2007 | AJ12: 2008 | AK12: 2009 | AL12: 2010 | AM12: 2011 | AN12: 2012 | AO12: 2013 | AP12: 2014 | AQ12: 2015 | AR12: 2016 | AS12: 2017 | AT12: 2018 | AU12: 2019 | AV12: 2020 | AW12: 2021 | AX12: 2022 | AY12: 2023 | AZ12: 1999 | BA12: 2000 | BB12: 2001 | BC12: 2002 | BD12: 2003 | BE12: 2004 | BF12: 2005 | BG12: 2006 | BH12: 2007 | BI12: 2008 | BJ12: 2009 | BK12: 2010 | BL12: 2011 | BM12: 2012 | BN12: 2013 | BO12: 2014 | BP12: 2015 | BQ12: 2016 | BR12: 2017 | BS12: 2018 | BT12: 2019 | BU12: 2020 | BV12: 2021 | BW12: 2022 | BX12: 2023 | BY12: 1999 | BZ12: 2000 | CA12: 2001 | CB12: 2002 | CC12: 2003 | CD12: 2004 | CE12: 2005 | CF12: 2006 | CG12: 2007 | CH12: 2008 | CI12: 2009 | CJ12: 2010 | CK12: 2011 | CL12: 2012 | CM12: 2013 | CN12: 2014 | CO12: 2015 | CP12: 2016 | CQ12: 2017 | CR12: 2018 | CS12: 2019 | CT12: 2020 | CU12: 2021 | CV12: 2022 | CW12: 2023 | CX12: 1999 | CY12: 2000 | CZ12: 2001 | DA12: 2002 | DB12: 2003 | DC12: 2004 | DD12: 2005 | DE12: 2006 | DF12: 2007 | DG12: 2008 | DH12: 2009 | DI12: 2010 | DJ12: 2011 | DK12: 2012 | DL12: 2013 | DM12: 2014 | DN12: 2015 | DO12: 2016 | DP12: 2017 | DQ12: 2018 | DR12: 2019 | DS12: 2020 | DT12: 2021 | DU12: 2022 | DV12: 2023 | DW12: 1999 | DX12: 2000 | DY12: 2001 | DZ12: 2002 | EA12: 2003 | EB12: 2004 | EC12: 2005 | ED12: 2006 | EE12: 2007 | EF12: 2008 | EG12: 2009 | EH12: 2010 | EI12: 2011 | EJ12: 2012 | EK12: 2013 | EL12: 2014 | EM12: 2015 | EN12: 2016 | EO12: 2017 | EP12: 2018 | EQ12: 2019 | ER12: 2020 | ES12: 2021 | ET12: 2022 | EU12: 2023
B13: Dollars
A14: Household disposable income | B14: 546261 | C14: 579683 | D14: 615286 | E14: 642584 | F14: 663239 | G14: 695238 | H14: 721510 | I14: 774375 | J14: 816321 | K14: 862404 | L14: 884783 | M14: 928091 | N14: 962102 | O14: 1001254 | P14: 1046791 | Q14: 1081654 | R14: 1129875 | S14: 1132763 | T14: 1189366 | U14: 1224919 | V14: 1280362 | W14: 1387659 | X14: 1435372 | Y14: 1514289 | Z14: 1597953 | AA14: 108971 | AB14: 115710 | AC14: 121341 | AD14: 127273 | AE14: 125919 | AF14: 135050 | AG14: 136097 | AH14: 144243 | AI14: 149092 | AJ14: 160612 | AK14: 161898 | AL14: 172264 | AM14: 175728 | AN14: 176946 | AO14: 177925 | AP14: 183523 | AQ14: 196735 | AR14: 198261 | AS14: 209653 | AT14: 216413 | AU14: 224463 | AV14: 252324 | AW14: 268137 | AX14: 284037 | AY14: 296903 | AZ14: 155005 | BA14: 164536 | BB14: 167980 | BC14: 173007 | BD14: 174156 | BE14: 177234 | BF14: 179863 | BG14: 182459 | BH14: 188940 | BI14: 194634 | BJ14: 196971 | BK14: 198869 | BL14: 204085 | BM14: 203979 | BN14: 210206 | BO14: 219338 | BP14: 223652 | BQ14: 222924 | BR14: 236984 | BS14: 245177 | BT14: 256622 | BU14: 284948 | BV14: 296649 | BW14: 321416 | BX14: 334126 | BY14: 134378 | BZ14: 145415 | CA14: 157731 | CB14: 165875 | CC14: 173260 | CD14: 185146 | CE14: 197247 | CF14: 214096 | CG14: 223293 | CH14: 238106 | CI14: 232754 | CJ14: 240250 | CK14: 252128 | CL14: 254938 | CM14: 268135 | CN14: 264425 | CO14: 272402 | CP14: 264329 | CQ14: 269326 | CR14: 270148 | CS14: 276089 | CT14: 299139 | CU14: 309314 | CV14: 327386 | CW14: 340857 | CX14: 67329 | CY14: 70371 | CZ14: 78270 | DA14: 83646 | DB14: 94568 | DC14: 98501 | DD14: 108238 | DE14: 119675 | DF14: 130400 | DG14: 136395 | DH14: 151272 | DI14: 163105 | DJ14: 166829 | DK14: 185302 | DL14: 195368 | DM14: 214164 | DN14: 218741 | DO14: 221976 | DP14: 234750 | DQ14: 242444 | DR14: 254746 | DS14: 267284 | DT14: 274723 | DU14: 282107 | DV14: 294159 | DW14: 80578 | DX14: 83651 | DY14: 89964 | DZ14: 92783 | EA14: 95336 | EB14: 99307 | EC14: 100065 | ED14: 113902 | EE14: 124596 | EF14: 132657 | EG14: 141888 | EH14: 153603 | EI14: 163332 | EJ14: 180089 | EK14: 195157 | EL14: 200204 | EM14: 218345 | EN14: 225273 | EO14: 238653 | EP14: 250737 | EQ14: 268442 | ER14: 283965 | ES14: 286551 | ET14: 299343 | EU14: 331908
